{
  "speed050": {
    "aim": [
      {
        "performance": 2.5020564,
        "time": 8.727273
      },
      {
        "performance": 1.9327153,
        "time": 9.272727
      },
      {
        "performance": 1.7545975,
        "time": 9.818182
      },
      {
        "performance": 1.4194193,
        "time": 10.363636
      },
      {
        "performance": 1.4224325,
        "time": 11.454545
      },
      {
        "performance": 0.9146655,
        "time": 12.545455
      },
      {
        "performance": 0.90376276,
        "time": 13.636364
      },
      {
        "performance": 0.5959067,
        "time": 14.181818
      },
      {
        "performance": 0.61300266,
        "time": 14.727273
      },
      {
        "performance": 0.39651528,
        "time": 15.818182
      },
      {
        "performance": 0.40789092,
        "time": 16.363636
      },
      {
        "performance": 0.28325182,
        "time": 17.454546
      },
      {
        "performance": 0.6839437,
        "time": 18.545454
      },
      {
        "performance": 0.7035653,
        "time": 19.09091
      },
      {
        "performance": 0.72374994,
        "time": 21.272728
      },
      {
        "performance": 1.2742493,
        "time": 21.818182
      },
      {
        "performance": 1.0387893,
        "time": 22.363636
      },
      {
        "performance": 0.8099175,
        "time": 22.90909
      },
      {
        "performance": 0.83315325,
        "time": 23.454546
      },
      {
        "performance": 0.5768449,
        "time": 25.636364
      },
      {
        "performance": 0.56303775,
        "time": 26.181818
      },
      {
        "performance": 0.9036964,
        "time": 27.272728
      },
      {
        "performance": 0.9296226,
        "time": 27.818182
      },
      {
        "performance": 1.0412189,
        "time": 30.0
      },
      {
        "performance": 1.120256,
        "time": 30.545454
      },
      {
        "performance": 0.77854794,
        "time": 31.636364
      },
      {
        "performance": 0.8008837,
        "time": 32.18182
      },
      {
        "performance": 0.58512866,
        "time": 33.272728
      },
      {
        "performance": 0.3776336,
        "time": 34.363636
      },
      {
        "performance": 0.2520009,
        "time": 34.909092
      },
      {
        "performance": 0.4040311,
        "time": 36.0
      },
      {
        "performance": 0.91527855,
        "time": 36.545456
      },
      {
        "performance": 1.0199432,
        "time": 38.727272
      },
      {
        "performance": 1.3204184,
        "time": 39.272728
      },
      {
        "performance": 1.1421884,
        "time": 39.81818
      },
      {
        "performance": 1.1749567,
        "time": 40.363636
      },
      {
        "performance": 0.900417,
        "time": 40.909092
      },
      {
        "performance": 0.88948846,
        "time": 42.0
      },
      {
        "performance": 0.915007,
        "time": 43.090908
      },
      {
        "performance": 0.639454,
        "time": 43.636364
      },
      {
        "performance": 0.42306978,
        "time": 44.727272
      },
      {
        "performance": 0.6568868,
        "time": 45.272728
      },
      {
        "performance": 0.8994909,
        "time": 46.363636
      },
      {
        "performance": 1.0395983,
        "time": 47.454544
      },
      {
        "performance": 1.0694234,
        "time": 48.0
      },
      {
        "performance": 0.86369026,
        "time": 49.636364
      },
      {
        "performance": 0.3776336,
        "time": 50.727272
      }
    ],
    "tap": [
      {
        "performance": 2.5020564,
        "time": 8.727273
      },
      {
        "performance": 1.9327153,
        "time": 9.272727
      },
      {
        "performance": 1.7545975,
        "time": 9.818182
      },
      {
        "performance": 1.4194193,
        "time": 10.363636
      },
      {
        "performance": 1.4224325,
        "time": 11.454545
      },
      {
        "performance": 0.9146655,
        "time": 12.545455
      },
      {
        "performance": 0.90376276,
        "time": 13.636364
      },
      {
        "performance": 0.5959067,
        "time": 14.181818
      },
      {
        "performance": 0.61300266,
        "time": 14.727273
      },
      {
        "performance": 0.39651528,
        "time": 15.818182
      },
      {
        "performance": 0.40789092,
        "time": 16.363636
      },
      {
        "performance": 0.28325182,
        "time": 17.454546
      },
      {
        "performance": 0.6839437,
        "time": 18.545454
      },
      {
        "performance": 0.7035653,
        "time": 19.09091
      },
      {
        "performance": 0.72374994,
        "time": 21.272728
      },
      {
        "performance": 1.2742493,
        "time": 21.818182
      },
      {
        "performance": 1.0387893,
        "time": 22.363636
      },
      {
        "performance": 0.8099175,
        "time": 22.90909
      },
      {
        "performance": 0.83315325,
        "time": 23.454546
      },
      {
        "performance": 0.5768449,
        "time": 25.636364
      },
      {
        "performance": 0.56303775,
        "time": 26.181818
      },
      {
        "performance": 0.9036964,
        "time": 27.272728
      },
      {
        "performance": 0.9296226,
        "time": 27.818182
      },
      {
        "performance": 1.0412189,
        "time": 30.0
      },
      {
        "performance": 1.120256,
        "time": 30.545454
      },
      {
        "performance": 0.77854794,
        "time": 31.636364
      },
      {
        "performance": 0.8008837,
        "time": 32.18182
      },
      {
        "performance": 0.58512866,
        "time": 33.272728
      },
      {
        "performance": 0.3776336,
        "time": 34.363636
      },
      {
        "performance": 0.2520009,
        "time": 34.909092
      },
      {
        "performance": 0.4040311,
        "time": 36.0
      },
      {
        "performance": 0.91527855,
        "time": 36.545456
      },
      {
        "performance": 1.0199432,
        "time": 38.727272
      },
      {
        "performance": 1.3204184,
        "time": 39.272728
      },
      {
        "performance": 1.1421884,
        "time": 39.81818
      },
      {
        "performance": 1.1749567,
        "time": 40.363636
      },
      {
        "performance": 0.900417,
        "time": 40.909092
      },
      {
        "performance": 0.88948846,
        "time": 42.0
      },
      {
        "performance": 0.915007,
        "time": 43.090908
      },
      {
        "performance": 0.639454,
        "time": 43.636364
      },
      {
        "performance": 0.42306978,
        "time": 44.727272
      },
      {
        "performance": 0.6568868,
        "time": 45.272728
      },
      {
        "performance": 0.8994909,
        "time": 46.363636
      },
      {
        "performance": 1.0395983,
        "time": 47.454544
      },
      {
        "performance": 1.0694234,
        "time": 48.0
      },
      {
        "performance": 0.86369026,
        "time": 49.636364
      },
      {
        "performance": 0.3776336,
        "time": 50.727272
      }
    ],
    "acc": [
      {
        "performance": 2.5020564,
        "time": 8.727273
      },
      {
        "performance": 1.9327153,
        "time": 9.272727
      },
      {
        "performance": 1.7545975,
        "time": 9.818182
      },
      {
        "performance": 1.4194193,
        "time": 10.363636
      },
      {
        "performance": 1.4224325,
        "time": 11.454545
      },
      {
        "performance": 0.9146655,
        "time": 12.545455
      },
      {
        "performance": 0.90376276,
        "time": 13.636364
      },
      {
        "performance": 0.5959067,
        "time": 14.181818
      },
      {
        "performance": 0.61300266,
        "time": 14.727273
      },
      {
        "performance": 0.39651528,
        "time": 15.818182
      },
      {
        "performance": 0.40789092,
        "time": 16.363636
      },
      {
        "performance": 0.28325182,
        "time": 17.454546
      },
      {
        "performance": 0.6839437,
        "time": 18.545454
      },
      {
        "performance": 0.7035653,
        "time": 19.09091
      },
      {
        "performance": 0.72374994,
        "time": 21.272728
      },
      {
        "performance": 1.2742493,
        "time": 21.818182
      },
      {
        "performance": 1.0387893,
        "time": 22.363636
      },
      {
        "performance": 0.8099175,
        "time": 22.90909
      },
      {
        "performance": 0.83315325,
        "time": 23.454546
      },
      {
        "performance": 0.5768449,
        "time": 25.636364
      },
      {
        "performance": 0.56303775,
        "time": 26.181818
      },
      {
        "performance": 0.9036964,
        "time": 27.272728
      },
      {
        "performance": 0.9296226,
        "time": 27.818182
      },
      {
        "performance": 1.0412189,
        "time": 30.0
      },
      {
        "performance": 1.120256,
        "time": 30.545454
      },
      {
        "performance": 0.77854794,
        "time": 31.636364
      },
      {
        "performance": 0.8008837,
        "time": 32.18182
      },
      {
        "performance": 0.58512866,
        "time": 33.272728
      },
      {
        "performance": 0.3776336,
        "time": 34.363636
      },
      {
        "performance": 0.2520009,
        "time": 34.909092
      },
      {
        "performance": 0.4040311,
        "time": 36.0
      },
      {
        "performance": 0.91527855,
        "time": 36.545456
      },
      {
        "performance": 1.0199432,
        "time": 38.727272
      },
      {
        "performance": 1.3204184,
        "time": 39.272728
      },
      {
        "performance": 1.1421884,
        "time": 39.81818
      },
      {
        "performance": 1.1749567,
        "time": 40.363636
      },
      {
        "performance": 0.900417,
        "time": 40.909092
      },
      {
        "performance": 0.88948846,
        "time": 42.0
      },
      {
        "performance": 0.915007,
        "time": 43.090908
      },
      {
        "performance": 0.639454,
        "time": 43.636364
      },
      {
        "performance": 0.42306978,
        "time": 44.727272
      },
      {
        "performance": 0.6568868,
        "time": 45.272728
      },
      {
        "performance": 0.8994909,
        "time": 46.363636
      },
      {
        "performance": 1.0395983,
        "time": 47.454544
      },
      {
        "performance": 1.0694234,
        "time": 48.0
      },
      {
        "performance": 0.86369026,
        "time": 49.636364
      },
      {
        "performance": 0.3776336,
        "time": 50.727272
      }
    ]
  },
  "speed075": {
    "aim": [
      {
        "performance": 2.9939694,
        "time": 5.818182
      },
      {
        "performance": 2.4062207,
        "time": 6.181818
      },
      {
        "performance": 2.0210946,
        "time": 6.5454545
      },
      {
        "performance": 1.3826166,
        "time": 6.909091
      },
      {
        "performance": 1.5448052,
        "time": 7.6363635
      },
      {
        "performance": 1.0194987,
        "time": 8.363636
      },
      {
        "performance": 0.5996195,
        "time": 9.090909
      },
      {
        "performance": 0.616822,
        "time": 9.454545
      },
      {
        "performance": 0.634518,
        "time": 9.818182
      },
      {
        "performance": 0.6943424,
        "time": 10.545455
      },
      {
        "performance": 0.71426237,
        "time": 10.909091
      },
      {
        "performance": 0.2931935,
        "time": 11.636364
      },
      {
        "performance": 0.30160493,
        "time": 12.363636
      },
      {
        "performance": 0.31025767,
        "time": 12.727273
      },
      {
        "performance": 1.136615,
        "time": 14.181818
      },
      {
        "performance": 0.82064253,
        "time": 14.545455
      },
      {
        "performance": 0.84418595,
        "time": 14.909091
      },
      {
        "performance": 0.8684048,
        "time": 15.272727
      },
      {
        "performance": 0.8933185,
        "time": 15.636364
      },
      {
        "performance": 1.5166095,
        "time": 17.09091
      },
      {
        "performance": 0.92310244,
        "time": 17.454546
      },
      {
        "performance": 1.1552978,
        "time": 18.181818
      },
      {
        "performance": 1.188442,
        "time": 18.545454
      },
      {
        "performance": 1.6597071,
        "time": 20.0
      },
      {
        "performance": 1.1595751,
        "time": 20.363636
      },
      {
        "performance": 0.8058737,
        "time": 21.09091
      },
      {
        "performance": 0.82899344,
        "time": 21.454546
      },
      {
        "performance": 0.7344499,
        "time": 22.181818
      },
      {
        "performance": 0.5233668,
        "time": 22.90909
      },
      {
        "performance": 0.5693771,
        "time": 23.272728
      },
      {
        "performance": 0.7856872,
        "time": 24.0
      },
      {
        "performance": 0.80822784,
        "time": 24.363636
      },
      {
        "performance": 1.316451,
        "time": 25.818182
      },
      {
        "performance": 1.3542186,
        "time": 26.181818
      },
      {
        "performance": 1.3930699,
        "time": 26.545454
      },
      {
        "performance": 1.6430097,
        "time": 26.90909
      },
      {
        "performance": 1.1428125,
        "time": 27.272728
      },
      {
        "performance": 1.1315005,
        "time": 28.0
      },
      {
        "performance": 1.1639621,
        "time": 28.727272
      },
      {
        "performance": 0.8531888,
        "time": 29.09091
      },
      {
        "performance": 1.0899422,
        "time": 29.818182
      },
      {
        "performance": 1.4863149,
        "time": 30.181818
      },
      {
        "performance": 1.2655492,
        "time": 30.90909
      },
      {
        "performance": 1.043923,
        "time": 31.636364
      },
      {
        "performance": 1.0738722,
        "time": 32.0
      },
      {
        "performance": 0.8940044,
        "time": 33.090908
      },
      {
        "performance": 0.39088792,
        "time": 33.81818
      }
    ],
    "tap": [
      {
        "performance": 2.9939694,
        "time": 5.818182
      },
      {
        "performance": 2.4062207,
        "time": 6.181818
      },
      {
        "performance": 2.0210946,
        "time": 6.5454545
      },
      {
        "performance": 1.3826166,
        "time": 6.909091
      },
      {
        "performance": 1.5448052,
        "time": 7.6363635
      },
      {
        "performance": 1.0194987,
        "time": 8.363636
      },
      {
        "performance": 0.5996195,
        "time": 9.090909
      },
      {
        "performance": 0.616822,
        "time": 9.454545
      },
      {
        "performance": 0.634518,
        "time": 9.818182
      },
      {
        "performance": 0.6943424,
        "time": 10.545455
      },
      {
        "performance": 0.71426237,
        "time": 10.909091
      },
      {
        "performance": 0.2931935,
        "time": 11.636364
      },
      {
        "performance": 0.30160493,
        "time": 12.363636
      },
      {
        "performance": 0.31025767,
        "time": 12.727273
      },
      {
        "performance": 1.136615,
        "time": 14.181818
      },
      {
        "performance": 0.82064253,
        "time": 14.545455
      },
      {
        "performance": 0.84418595,
        "time": 14.909091
      },
      {
        "performance": 0.8684048,
        "time": 15.272727
      },
      {
        "performance": 0.8933185,
        "time": 15.636364
      },
      {
        "performance": 1.5166095,
        "time": 17.09091
      },
      {
        "performance": 0.92310244,
        "time": 17.454546
      },
      {
        "performance": 1.1552978,
        "time": 18.181818
      },
      {
        "performance": 1.188442,
        "time": 18.545454
      },
      {
        "performance": 1.6597071,
        "time": 20.0
      },
      {
        "performance": 1.1595751,
        "time": 20.363636
      },
      {
        "performance": 0.8058737,
        "time": 21.09091
      },
      {
        "performance": 0.82899344,
        "time": 21.454546
      },
      {
        "performance": 0.7344499,
        "time": 22.181818
      },
      {
        "performance": 0.5233668,
        "time": 22.90909
      },
      {
        "performance": 0.5693771,
        "time": 23.272728
      },
      {
        "performance": 0.7856872,
        "time": 24.0
      },
      {
        "performance": 0.80822784,
        "time": 24.363636
      },
      {
        "performance": 1.316451,
        "time": 25.818182
      },
      {
        "performance": 1.3542186,
        "time": 26.181818
      },
      {
        "performance": 1.3930699,
        "time": 26.545454
      },
      {
        "performance": 1.6430097,
        "time": 26.90909
      },
      {
        "performance": 1.1428125,
        "time": 27.272728
      },
      {
        "performance": 1.1315005,
        "time": 28.0
      },
      {
        "performance": 1.1639621,
        "time": 28.727272
      },
      {
        "performance": 0.8531888,
        "time": 29.09091
      },
      {
        "performance": 1.0899422,
        "time": 29.818182
      },
      {
        "performance": 1.4863149,
        "time": 30.181818
      },
      {
        "performance": 1.2655492,
        "time": 30.90909
      },
      {
        "performance": 1.043923,
        "time": 31.636364
      },
      {
        "performance": 1.0738722,
        "time": 32.0
      },
      {
        "performance": 0.8940044,
        "time": 33.090908
      },
      {
        "performance": 0.39088792,
        "time": 33.81818
      }
    ],
    "acc": [
      {
        "performance": 2.9939694,
        "time": 5.818182
      },
      {
        "performance": 2.4062207,
        "time": 6.181818
      },
      {
        "performance": 2.0210946,
        "time": 6.5454545
      },
      {
        "performance": 1.3826166,
        "time": 6.909091
      },
      {
        "performance": 1.5448052,
        "time": 7.6363635
      },
      {
        "performance": 1.0194987,
        "time": 8.363636
      },
      {
        "performance": 0.5996195,
        "time": 9.090909
      },
      {
        "performance": 0.616822,
        "time": 9.454545
      },
      {
        "performance": 0.634518,
        "time": 9.818182
      },
      {
        "performance": 0.6943424,
        "time": 10.545455
      },
      {
        "performance": 0.71426237,
        "time": 10.909091
      },
      {
        "performance": 0.2931935,
        "time": 11.636364
      },
      {
        "performance": 0.30160493,
        "time": 12.363636
      },
      {
        "performance": 0.31025767,
        "time": 12.727273
      },
      {
        "performance": 1.136615,
        "time": 14.181818
      },
      {
        "performance": 0.82064253,
        "time": 14.545455
      },
      {
        "performance": 0.84418595,
        "time": 14.909091
      },
      {
        "performance": 0.8684048,
        "time": 15.272727
      },
      {
        "performance": 0.8933185,
        "time": 15.636364
      },
      {
        "performance": 1.5166095,
        "time": 17.09091
      },
      {
        "performance": 0.92310244,
        "time": 17.454546
      },
      {
        "performance": 1.1552978,
        "time": 18.181818
      },
      {
        "performance": 1.188442,
        "time": 18.545454
      },
      {
        "performance": 1.6597071,
        "time": 20.0
      },
      {
        "performance": 1.1595751,
        "time": 20.363636
      },
      {
        "performance": 0.8058737,
        "time": 21.09091
      },
      {
        "performance": 0.82899344,
        "time": 21.454546
      },
      {
        "performance": 0.7344499,
        "time": 22.181818
      },
      {
        "performance": 0.5233668,
        "time": 22.90909
      },
      {
        "performance": 0.5693771,
        "time": 23.272728
      },
      {
        "performance": 0.7856872,
        "time": 24.0
      },
      {
        "performance": 0.80822784,
        "time": 24.363636
      },
      {
        "performance": 1.316451,
        "time": 25.818182
      },
      {
        "performance": 1.3542186,
        "time": 26.181818
      },
      {
        "performance": 1.3930699,
        "time": 26.545454
      },
      {
        "performance": 1.6430097,
        "time": 26.90909
      },
      {
        "performance": 1.1428125,
        "time": 27.272728
      },
      {
        "performance": 1.1315005,
        "time": 28.0
      },
      {
        "performance": 1.1639621,
        "time": 28.727272
      },
      {
        "performance": 0.8531888,
        "time": 29.09091
      },
      {
        "performance": 1.0899422,
        "time": 29.818182
      },
      {
        "performance": 1.4863149,
        "time": 30.181818
      },
      {
        "performance": 1.2655492,
        "time": 30.90909
      },
      {
        "performance": 1.043923,
        "time": 31.636364
      },
      {
        "performance": 1.0738722,
        "time": 32.0
      },
      {
        "performance": 0.8940044,
        "time": 33.090908
      },
      {
        "performance": 0.39088792,
        "time": 33.81818
      }
    ]
  },
  "speed100": {
    "aim": [
      {
        "performance": 3.4534736,
        "time": 4.3636365
      },
      {
        "performance": 2.819488,
        "time": 4.6363635
      },
      {
        "performance": 2.583995,
        "time": 4.909091
      },
      {
        "performance": 1.9058633,
        "time": 5.181818
      },
      {
        "performance": 1.6685803,
        "time": 5.7272725
      },
      {
        "performance": 1.1011844,
        "time": 6.2727275
      },
      {
        "performance": 0.93632966,
        "time": 6.818182
      },
      {
        "performance": 0.96319205,
        "time": 7.090909
      },
      {
        "performance": 0.99082506,
        "time": 7.3636365
      },
      {
        "performance": 0.74997544,
        "time": 7.909091
      },
      {
        "performance": 0.7714915,
        "time": 8.181818
      },
      {
        "performance": 0.5987477,
        "time": 8.727273
      },
      {
        "performance": 1.1714643,
        "time": 9.272727
      },
      {
        "performance": 1.2050724,
        "time": 9.545455
      },
      {
        "performance": 1.2396448,
        "time": 10.636364
      },
      {
        "performance": 1.0346513,
        "time": 10.909091
      },
      {
        "performance": 1.5338506,
        "time": 11.181818
      },
      {
        "performance": 1.5778552,
        "time": 11.454545
      },
      {
        "performance": 1.9730791,
        "time": 11.727273
      },
      {
        "performance": 1.8590848,
        "time": 12.818182
      },
      {
        "performance": 1.4340444,
        "time": 13.090909
      },
      {
        "performance": 1.8478527,
        "time": 13.636364
      },
      {
        "performance": 1.9008657,
        "time": 13.909091
      },
      {
        "performance": 1.7926885,
        "time": 15.0
      },
      {
        "performance": 1.3920981,
        "time": 15.272727
      },
      {
        "performance": 1.010601,
        "time": 15.818182
      },
      {
        "performance": 1.0395942,
        "time": 16.09091
      },
      {
        "performance": 1.2553567,
        "time": 16.636364
      },
      {
        "performance": 1.2497756,
        "time": 17.181818
      },
      {
        "performance": 0.83079404,
        "time": 17.454546
      },
      {
        "performance": 1.322322,
        "time": 18.0
      },
      {
        "performance": 1.5745821,
        "time": 18.272728
      },
      {
        "performance": 1.6302763,
        "time": 19.363636
      },
      {
        "performance": 1.8905392,
        "time": 19.636364
      },
      {
        "performance": 1.9447769,
        "time": 19.90909
      },
      {
        "performance": 2.0005705,
        "time": 20.181818
      },
      {
        "performance": 1.4611765,
        "time": 20.454546
      },
      {
        "performance": 1.4146045,
        "time": 21.0
      },
      {
        "performance": 1.9481802,
        "time": 21.545454
      },
      {
        "performance": 1.7904519,
        "time": 21.818182
      },
      {
        "performance": 1.552719,
        "time": 22.363636
      },
      {
        "performance": 1.597265,
        "time": 22.636364
      },
      {
        "performance": 1.3587791,
        "time": 23.181818
      },
      {
        "performance": 1.1193635,
        "time": 23.727272
      },
      {
        "performance": 1.151477,
        "time": 24.0
      },
      {
        "performance": 0.9656351,
        "time": 24.818182
      },
      {
        "performance": 0.4222072,
        "time": 25.363636
      }
    ],
    "tap": [
      {
        "performance": 3.4534736,
        "time": 4.3636365
      },
      {
        "performance": 2.819488,
        "time": 4.6363635
      },
      {
        "performance": 2.583995,
        "time": 4.909091
      },
      {
        "performance": 1.9058633,
        "time": 5.181818
      },
      {
        "performance": 1.6685803,
        "time": 5.7272725
      },
      {
        "performance": 1.1011844,
        "time": 6.2727275
      },
      {
        "performance": 0.93632966,
        "time": 6.818182
      },
      {
        "performance": 0.96319205,
        "time": 7.090909
      },
      {
        "performance": 0.99082506,
        "time": 7.3636365
      },
      {
        "performance": 0.74997544,
        "time": 7.909091
      },
      {
        "performance": 0.7714915,
        "time": 8.181818
      },
      {
        "performance": 0.5987477,
        "time": 8.727273
      },
      {
        "performance": 1.1714643,
        "time": 9.272727
      },
      {
        "performance": 1.2050724,
        "time": 9.545455
      },
      {
        "performance": 1.2396448,
        "time": 10.636364
      },
      {
        "performance": 1.0346513,
        "time": 10.909091
      },
      {
        "performance": 1.5338506,
        "time": 11.181818
      },
      {
        "performance": 1.5778552,
        "time": 11.454545
      },
      {
        "performance": 1.9730791,
        "time": 11.727273
      },
      {
        "performance": 1.8590848,
        "time": 12.818182
      },
      {
        "performance": 1.4340444,
        "time": 13.090909
      },
      {
        "performance": 1.8478527,
        "time": 13.636364
      },
      {
        "performance": 1.9008657,
        "time": 13.909091
      },
      {
        "performance": 1.7926885,
        "time": 15.0
      },
      {
        "performance": 1.3920981,
        "time": 15.272727
      },
      {
        "performance": 1.010601,
        "time": 15.818182
      },
      {
        "performance": 1.0395942,
        "time": 16.09091
      },
      {
        "performance": 1.2553567,
        "time": 16.636364
      },
      {
        "performance": 1.2497756,
        "time": 17.181818
      },
      {
        "performance": 0.83079404,
        "time": 17.454546
      },
      {
        "performance": 1.322322,
        "time": 18.0
      },
      {
        "performance": 1.5745821,
        "time": 18.272728
      },
      {
        "performance": 1.6302763,
        "time": 19.363636
      },
      {
        "performance": 1.8905392,
        "time": 19.636364
      },
      {
        "performance": 1.9447769,
        "time": 19.90909
      },
      {
        "performance": 2.0005705,
        "time": 20.181818
      },
      {
        "performance": 1.4611765,
        "time": 20.454546
      },
      {
        "performance": 1.4146045,
        "time": 21.0
      },
      {
        "performance": 1.9481802,
        "time": 21.545454
      },
      {
        "performance": 1.7904519,
        "time": 21.818182
      },
      {
        "performance": 1.552719,
        "time": 22.363636
      },
      {
        "performance": 1.597265,
        "time": 22.636364
      },
      {
        "performance": 1.3587791,
        "time": 23.181818
      },
      {
        "performance": 1.1193635,
        "time": 23.727272
      },
      {
        "performance": 1.151477,
        "time": 24.0
      },
      {
        "performance": 0.9656351,
        "time": 24.818182
      },
      {
        "performance": 0.4222072,
        "time": 25.363636
      }
    ],
    "acc": [
      {
        "performance": 3.4534736,
        "time": 4.3636365
      },
      {
        "performance": 2.819488,
        "time": 4.6363635
      },
      {
        "performance": 2.583995,
        "time": 4.909091
      },
      {
        "performance": 1.9058633,
        "time": 5.181818
      },
      {
        "performance": 1.6685803,
        "time": 5.7272725
      },
      {
        "performance": 1.1011844,
        "time": 6.2727275
      },
      {
        "performance": 0.93632966,
        "time": 6.818182
      },
      {
        "performance": 0.96319205,
        "time": 7.090909
      },
      {
        "performance": 0.99082506,
        "time": 7.3636365
      },
      {
        "performance": 0.74997544,
        "time": 7.909091
      },
      {
        "performance": 0.7714915,
        "time": 8.181818
      },
      {
        "performance": 0.5987477,
        "time": 8.727273
      },
      {
        "performance": 1.1714643,
        "time": 9.272727
      },
      {
        "performance": 1.2050724,
        "time": 9.545455
      },
      {
        "performance": 1.2396448,
        "time": 10.636364
      },
      {
        "performance": 1.0346513,
        "time": 10.909091
      },
      {
        "performance": 1.5338506,
        "time": 11.181818
      },
      {
        "performance": 1.5778552,
        "time": 11.454545
      },
      {
        "performance": 1.9730791,
        "time": 11.727273
      },
      {
        "performance": 1.8590848,
        "time": 12.818182
      },
      {
        "performance": 1.4340444,
        "time": 13.090909
      },
      {
        "performance": 1.8478527,
        "time": 13.636364
      },
      {
        "performance": 1.9008657,
        "time": 13.909091
      },
      {
        "performance": 1.7926885,
        "time": 15.0
      },
      {
        "performance": 1.3920981,
        "time": 15.272727
      },
      {
        "performance": 1.010601,
        "time": 15.818182
      },
      {
        "performance": 1.0395942,
        "time": 16.09091
      },
      {
        "performance": 1.2553567,
        "time": 16.636364
      },
      {
        "performance": 1.2497756,
        "time": 17.181818
      },
      {
        "performance": 0.83079404,
        "time": 17.454546
      },
      {
        "performance": 1.322322,
        "time": 18.0
      },
      {
        "performance": 1.5745821,
        "time": 18.272728
      },
      {
        "performance": 1.6302763,
        "time": 19.363636
      },
      {
        "performance": 1.8905392,
        "time": 19.636364
      },
      {
        "performance": 1.9447769,
        "time": 19.90909
      },
      {
        "performance": 2.0005705,
        "time": 20.181818
      },
      {
        "performance": 1.4611765,
        "time": 20.454546
      },
      {
        "performance": 1.4146045,
        "time": 21.0
      },
      {
        "performance": 1.9481802,
        "time": 21.545454
      },
      {
        "performance": 1.7904519,
        "time": 21.818182
      },
      {
        "performance": 1.552719,
        "time": 22.363636
      },
      {
        "performance": 1.597265,
        "time": 22.636364
      },
      {
        "performance": 1.3587791,
        "time": 23.181818
      },
      {
        "performance": 1.1193635,
        "time": 23.727272
      },
      {
        "performance": 1.151477,
        "time": 24.0
      },
      {
        "performance": 0.9656351,
        "time": 24.818182
      },
      {
        "performance": 0.4222072,
        "time": 25.363636
      }
    ]
  },
  "speed125": {
    "aim": [
      {
        "performance": 4.1529956,
        "time": 3.490909
      },
      {
        "performance": 3.4710236,
        "time": 3.709091
      },
      {
        "performance": 2.7863936,
        "time": 3.9272728
      },
      {
        "performance": 2.0551453,
        "time": 4.1454544
      },
      {
        "performance": 1.7992764,
        "time": 4.581818
      },
      {
        "performance": 1.4975063,
        "time": 5.018182
      },
      {
        "performance": 1.0096703,
        "time": 5.4545455
      },
      {
        "performance": 1.0386367,
        "time": 5.672727
      },
      {
        "performance": 1.0684341,
        "time": 5.890909
      },
      {
        "performance": 1.1093793,
        "time": 6.327273
      },
      {
        "performance": 1.7212915,
        "time": 6.5454545
      },
      {
        "performance": 1.2343278,
        "time": 6.981818
      },
      {
        "performance": 1.2697394,
        "time": 7.418182
      },
      {
        "performance": 1.306167,
        "time": 7.6363635
      },
      {
        "performance": 1.9833003,
        "time": 8.509091
      },
      {
        "performance": 1.9645163,
        "time": 8.727273
      },
      {
        "performance": 2.0208762,
        "time": 8.945455
      },
      {
        "performance": 2.0788531,
        "time": 9.163636
      },
      {
        "performance": 2.3696048,
        "time": 9.381818
      },
      {
        "performance": 2.6282914,
        "time": 10.254545
      },
      {
        "performance": 1.9403769,
        "time": 10.472727
      },
      {
        "performance": 1.9960444,
        "time": 10.909091
      },
      {
        "performance": 2.053309,
        "time": 11.127273
      },
      {
        "performance": 2.0861943,
        "time": 12.0
      },
      {
        "performance": 1.5042738,
        "time": 12.218182
      },
      {
        "performance": 1.5694959,
        "time": 12.654546
      },
      {
        "performance": 1.8329235,
        "time": 12.872727
      },
      {
        "performance": 1.5761884,
        "time": 13.309091
      },
      {
        "performance": 1.83937,
        "time": 13.745455
      },
      {
        "performance": 1.6078875,
        "time": 13.963636
      },
      {
        "performance": 1.6540161,
        "time": 14.4
      },
      {
        "performance": 1.925262,
        "time": 14.618182
      },
      {
        "performance": 1.9817659,
        "time": 15.490909
      },
      {
        "performance": 2.0386207,
        "time": 15.709091
      },
      {
        "performance": 2.2937138,
        "time": 15.927273
      },
      {
        "performance": 2.359518,
        "time": 16.145454
      },
      {
        "performance": 2.2934375,
        "time": 16.363636
      },
      {
        "performance": 2.4372401,
        "time": 16.8
      },
      {
        "performance": 2.507162,
        "time": 17.236364
      },
      {
        "performance": 1.9268823,
        "time": 17.454546
      },
      {
        "performance": 1.6705134,
        "time": 17.89091
      },
      {
        "performance": 1.7184387,
        "time": 18.10909
      },
      {
        "performance": 1.4612575,
        "time": 18.545454
      },
      {
        "performance": 1.2030737,
        "time": 18.981817
      },
      {
        "performance": 1.2375888,
        "time": 19.2
      },
      {
        "performance": 1.0412711,
        "time": 19.854546
      },
      {
        "performance": 0.45527774,
        "time": 20.290909
      }
    ],
    "tap": [
      {
        "performance": 4.1529956,
        "time": 3.490909
      },
      {
        "performance": 3.4710236,
        "time": 3.709091
      },
      {
        "performance": 2.7863936,
        "time": 3.9272728
      },
      {
        "performance": 2.0551453,
        "time": 4.1454544
      },
      {
        "performance": 1.7992764,
        "time": 4.581818
      },
      {
        "performance": 1.4975063,
        "time": 5.018182
      },
      {
        "performance": 1.0096703,
        "time": 5.4545455
      },
      {
        "performance": 1.0386367,
        "time": 5.672727
      },
      {
        "performance": 1.0684341,
        "time": 5.890909
      },
      {
        "performance": 1.1093793,
        "time": 6.327273
      },
      {
        "performance": 1.7212915,
        "time": 6.5454545
      },
      {
        "performance": 1.2343278,
        "time": 6.981818
      },
      {
        "performance": 1.2697394,
        "time": 7.418182
      },
      {
        "performance": 1.306167,
        "time": 7.6363635
      },
      {
        "performance": 1.9833003,
        "time": 8.509091
      },
      {
        "performance": 1.9645163,
        "time": 8.727273
      },
      {
        "performance": 2.0208762,
        "time": 8.945455
      },
      {
        "performance": 2.0788531,
        "time": 9.163636
      },
      {
        "performance": 2.3696048,
        "time": 9.381818
      },
      {
        "performance": 2.6282914,
        "time": 10.254545
      },
      {
        "performance": 1.9403769,
        "time": 10.472727
      },
      {
        "performance": 1.9960444,
        "time": 10.909091
      },
      {
        "performance": 2.053309,
        "time": 11.127273
      },
      {
        "performance": 2.0861943,
        "time": 12.0
      },
      {
        "performance": 1.5042738,
        "time": 12.218182
      },
      {
        "performance": 1.5694959,
        "time": 12.654546
      },
      {
        "performance": 1.8329235,
        "time": 12.872727
      },
      {
        "performance": 1.5761884,
        "time": 13.309091
      },
      {
        "performance": 1.83937,
        "time": 13.745455
      },
      {
        "performance": 1.6078875,
        "time": 13.963636
      },
      {
        "performance": 1.6540161,
        "time": 14.4
      },
      {
        "performance": 1.925262,
        "time": 14.618182
      },
      {
        "performance": 1.9817659,
        "time": 15.490909
      },
      {
        "performance": 2.0386207,
        "time": 15.709091
      },
      {
        "performance": 2.2937138,
        "time": 15.927273
      },
      {
        "performance": 2.359518,
        "time": 16.145454
      },
      {
        "performance": 2.2934375,
        "time": 16.363636
      },
      {
        "performance": 2.4372401,
        "time": 16.8
      },
      {
        "performance": 2.507162,
        "time": 17.236364
      },
      {
        "performance": 1.9268823,
        "time": 17.454546
      },
      {
        "performance": 1.6705134,
        "time": 17.89091
      },
      {
        "performance": 1.7184387,
        "time": 18.10909
      },
      {
        "performance": 1.4612575,
        "time": 18.545454
      },
      {
        "performance": 1.2030737,
        "time": 18.981817
      },
      {
        "performance": 1.2375888,
        "time": 19.2
      },
      {
        "performance": 1.0412711,
        "time": 19.854546
      },
      {
        "performance": 0.45527774,
        "time": 20.290909
      }
    ],
    "acc": [
      {
        "performance": 4.1529956,
        "time": 3.490909
      },
      {
        "performance": 3.4710236,
        "time": 3.709091
      },
      {
        "performance": 2.7863936,
        "time": 3.9272728
      },
      {
        "performance": 2.0551453,
        "time": 4.1454544
      },
      {
        "performance": 1.7992764,
        "time": 4.581818
      },
      {
        "performance": 1.4975063,
        "time": 5.018182
      },
      {
        "performance": 1.0096703,
        "time": 5.4545455
      },
      {
        "performance": 1.0386367,
        "time": 5.672727
      },
      {
        "performance": 1.0684341,
        "time": 5.890909
      },
      {
        "performance": 1.1093793,
        "time": 6.327273
      },
      {
        "performance": 1.7212915,
        "time": 6.5454545
      },
      {
        "performance": 1.2343278,
        "time": 6.981818
      },
      {
        "performance": 1.2697394,
        "time": 7.418182
      },
      {
        "performance": 1.306167,
        "time": 7.6363635
      },
      {
        "performance": 1.9833003,
        "time": 8.509091
      },
      {
        "performance": 1.9645163,
        "time": 8.727273
      },
      {
        "performance": 2.0208762,
        "time": 8.945455
      },
      {
        "performance": 2.0788531,
        "time": 9.163636
      },
      {
        "performance": 2.3696048,
        "time": 9.381818
      },
      {
        "performance": 2.6282914,
        "time": 10.254545
      },
      {
        "performance": 1.9403769,
        "time": 10.472727
      },
      {
        "performance": 1.9960444,
        "time": 10.909091
      },
      {
        "performance": 2.053309,
        "time": 11.127273
      },
      {
        "performance": 2.0861943,
        "time": 12.0
      },
      {
        "performance": 1.5042738,
        "time": 12.218182
      },
      {
        "performance": 1.5694959,
        "time": 12.654546
      },
      {
        "performance": 1.8329235,
        "time": 12.872727
      },
      {
        "performance": 1.5761884,
        "time": 13.309091
      },
      {
        "performance": 1.83937,
        "time": 13.745455
      },
      {
        "performance": 1.6078875,
        "time": 13.963636
      },
      {
        "performance": 1.6540161,
        "time": 14.4
      },
      {
        "performance": 1.925262,
        "time": 14.618182
      },
      {
        "performance": 1.9817659,
        "time": 15.490909
      },
      {
        "performance": 2.0386207,
        "time": 15.709091
      },
      {
        "performance": 2.2937138,
        "time": 15.927273
      },
      {
        "performance": 2.359518,
        "time": 16.145454
      },
      {
        "performance": 2.2934375,
        "time": 16.363636
      },
      {
        "performance": 2.4372401,
        "time": 16.8
      },
      {
        "performance": 2.507162,
        "time": 17.236364
      },
      {
        "performance": 1.9268823,
        "time": 17.454546
      },
      {
        "performance": 1.6705134,
        "time": 17.89091
      },
      {
        "performance": 1.7184387,
        "time": 18.10909
      },
      {
        "performance": 1.4612575,
        "time": 18.545454
      },
      {
        "performance": 1.2030737,
        "time": 18.981817
      },
      {
        "performance": 1.2375888,
        "time": 19.2
      },
      {
        "performance": 1.0412711,
        "time": 19.854546
      },
      {
        "performance": 0.45527774,
        "time": 20.290909
      }
    ]
  },
  "speed150": {
    "aim": [
      {
        "performance": 4.447132,
        "time": 2.909091
      },
      {
        "performance": 3.7168596,
        "time": 3.090909
      },
      {
        "performance": 3.3040085,
        "time": 3.2727273
      },
      {
        "performance": 2.5301576,
        "time": 3.4545455
      },
      {
        "performance": 2.2574506,
        "time": 3.8181818
      },
      {
        "performance": 1.6035675,
        "time": 4.181818
      },
      {
        "performance": 1.3880979,
        "time": 4.5454545
      },
      {
        "performance": 2.0126476,
        "time": 4.7272725
      },
      {
        "performance": 2.0703883,
        "time": 4.909091
      },
      {
        "performance": 1.7958896,
        "time": 5.2727275
      },
      {
        "performance": 1.8474119,
        "time": 5.4545455
      },
      {
        "performance": 1.3259752,
        "time": 5.818182
      },
      {
        "performance": 2.0132294,
        "time": 6.181818
      },
      {
        "performance": 2.0709867,
        "time": 6.3636365
      },
      {
        "performance": 2.7266438,
        "time": 7.090909
      },
      {
        "performance": 2.3376591,
        "time": 7.2727275
      },
      {
        "performance": 2.6376848,
        "time": 7.4545455
      },
      {
        "performance": 3.116857,
        "time": 7.6363635
      },
      {
        "performance": 3.2062767,
        "time": 7.818182
      },
      {
        "performance": 2.8166716,
        "time": 8.545455
      },
      {
        "performance": 2.0800438,
        "time": 8.727273
      },
      {
        "performance": 2.2966022,
        "time": 9.090909
      },
      {
        "performance": 2.3624895,
        "time": 9.272727
      },
      {
        "performance": 2.9680054,
        "time": 10.0
      },
      {
        "performance": 2.3477314,
        "time": 10.181818
      },
      {
        "performance": 2.4023674,
        "time": 10.545455
      },
      {
        "performance": 2.471289,
        "time": 10.727273
      },
      {
        "performance": 2.4248161,
        "time": 11.090909
      },
      {
        "performance": 2.4304194,
        "time": 11.454545
      },
      {
        "performance": 1.9504695,
        "time": 11.636364
      },
      {
        "performance": 2.2384827,
        "time": 12.0
      },
      {
        "performance": 2.3027024,
        "time": 12.181818
      },
      {
        "performance": 2.823453,
        "time": 12.909091
      },
      {
        "performance": 3.3048277,
        "time": 13.090909
      },
      {
        "performance": 3.3996398,
        "time": 13.272727
      },
      {
        "performance": 3.497172,
        "time": 13.454545
      },
      {
        "performance": 2.8789604,
        "time": 13.636364
      },
      {
        "performance": 2.6076133,
        "time": 14.0
      },
      {
        "performance": 2.682423,
        "time": 14.363636
      },
      {
        "performance": 2.0610359,
        "time": 14.545455
      },
      {
        "performance": 1.7865005,
        "time": 14.909091
      },
      {
        "performance": 1.8377534,
        "time": 15.090909
      },
      {
        "performance": 1.5623479,
        "time": 15.454545
      },
      {
        "performance": 1.2858689,
        "time": 15.818182
      },
      {
        "performance": 1.3227592,
        "time": 16.0
      },
      {
        "performance": 1.1150193,
        "time": 16.545454
      },
      {
        "performance": 0.48752287,
        "time": 16.90909
      }
    ],
    "tap": [
      {
        "performance": 4.447132,
        "time": 2.909091
      },
      {
        "performance": 3.7168596,
        "time": 3.090909
      },
      {
        "performance": 3.3040085,
        "time": 3.2727273
      },
      {
        "performance": 2.5301576,
        "time": 3.4545455
      },
      {
        "performance": 2.2574506,
        "time": 3.8181818
      },
      {
        "performance": 1.6035675,
        "time": 4.181818
      },
      {
        "performance": 1.3880979,
        "time": 4.5454545
      },
      {
        "performance": 2.0126476,
        "time": 4.7272725
      },
      {
        "performance": 2.0703883,
        "time": 4.909091
      },
      {
        "performance": 1.7958896,
        "time": 5.2727275
      },
      {
        "performance": 1.8474119,
        "time": 5.4545455
      },
      {
        "performance": 1.3259752,
        "time": 5.818182
      },
      {
        "performance": 2.0132294,
        "time": 6.181818
      },
      {
        "performance": 2.0709867,
        "time": 6.3636365
      },
      {
        "performance": 2.7266438,
        "time": 7.090909
      },
      {
        "performance": 2.3376591,
        "time": 7.2727275
      },
      {
        "performance": 2.6376848,
        "time": 7.4545455
      },
      {
        "performance": 3.116857,
        "time": 7.6363635
      },
      {
        "performance": 3.2062767,
        "time": 7.818182
      },
      {
        "performance": 2.8166716,
        "time": 8.545455
      },
      {
        "performance": 2.0800438,
        "time": 8.727273
      },
      {
        "performance": 2.2966022,
        "time": 9.090909
      },
      {
        "performance": 2.3624895,
        "time": 9.272727
      },
      {
        "performance": 2.9680054,
        "time": 10.0
      },
      {
        "performance": 2.3477314,
        "time": 10.181818
      },
      {
        "performance": 2.4023674,
        "time": 10.545455
      },
      {
        "performance": 2.471289,
        "time": 10.727273
      },
      {
        "performance": 2.4248161,
        "time": 11.090909
      },
      {
        "performance": 2.4304194,
        "time": 11.454545
      },
      {
        "performance": 1.9504695,
        "time": 11.636364
      },
      {
        "performance": 2.2384827,
        "time": 12.0
      },
      {
        "performance": 2.3027024,
        "time": 12.181818
      },
      {
        "performance": 2.823453,
        "time": 12.909091
      },
      {
        "performance": 3.3048277,
        "time": 13.090909
      },
      {
        "performance": 3.3996398,
        "time": 13.272727
      },
      {
        "performance": 3.497172,
        "time": 13.454545
      },
      {
        "performance": 2.8789604,
        "time": 13.636364
      },
      {
        "performance": 2.6076133,
        "time": 14.0
      },
      {
        "performance": 2.682423,
        "time": 14.363636
      },
      {
        "performance": 2.0610359,
        "time": 14.545455
      },
      {
        "performance": 1.7865005,
        "time": 14.909091
      },
      {
        "performance": 1.8377534,
        "time": 15.090909
      },
      {
        "performance": 1.5623479,
        "time": 15.454545
      },
      {
        "performance": 1.2858689,
        "time": 15.818182
      },
      {
        "performance": 1.3227592,
        "time": 16.0
      },
      {
        "performance": 1.1150193,
        "time": 16.545454
      },
      {
        "performance": 0.48752287,
        "time": 16.90909
      }
    ],
    "acc": [
      {
        "performance": 4.447132,
        "time": 2.909091
      },
      {
        "performance": 3.7168596,
        "time": 3.090909
      },
      {
        "performance": 3.3040085,
        "time": 3.2727273
      },
      {
        "performance": 2.5301576,
        "time": 3.4545455
      },
      {
        "performance": 2.2574506,
        "time": 3.8181818
      },
      {
        "performance": 1.6035675,
        "time": 4.181818
      },
      {
        "performance": 1.3880979,
        "time": 4.5454545
      },
      {
        "performance": 2.0126476,
        "time": 4.7272725
      },
      {
        "performance": 2.0703883,
        "time": 4.909091
      },
      {
        "performance": 1.7958896,
        "time": 5.2727275
      },
      {
        "performance": 1.8474119,
        "time": 5.4545455
      },
      {
        "performance": 1.3259752,
        "time": 5.818182
      },
      {
        "performance": 2.0132294,
        "time": 6.181818
      },
      {
        "performance": 2.0709867,
        "time": 6.3636365
      },
      {
        "performance": 2.7266438,
        "time": 7.090909
      },
      {
        "performance": 2.3376591,
        "time": 7.2727275
      },
      {
        "performance": 2.6376848,
        "time": 7.4545455
      },
      {
        "performance": 3.116857,
        "time": 7.6363635
      },
      {
        "performance": 3.2062767,
        "time": 7.818182
      },
      {
        "performance": 2.8166716,
        "time": 8.545455
      },
      {
        "performance": 2.0800438,
        "time": 8.727273
      },
      {
        "performance": 2.2966022,
        "time": 9.090909
      },
      {
        "performance": 2.3624895,
        "time": 9.272727
      },
      {
        "performance": 2.9680054,
        "time": 10.0
      },
      {
        "performance": 2.3477314,
        "time": 10.181818
      },
      {
        "performance": 2.4023674,
        "time": 10.545455
      },
      {
        "performance": 2.471289,
        "time": 10.727273
      },
      {
        "performance": 2.4248161,
        "time": 11.090909
      },
      {
        "performance": 2.4304194,
        "time": 11.454545
      },
      {
        "performance": 1.9504695,
        "time": 11.636364
      },
      {
        "performance": 2.2384827,
        "time": 12.0
      },
      {
        "performance": 2.3027024,
        "time": 12.181818
      },
      {
        "performance": 2.823453,
        "time": 12.909091
      },
      {
        "performance": 3.3048277,
        "time": 13.090909
      },
      {
        "performance": 3.3996398,
        "time": 13.272727
      },
      {
        "performance": 3.497172,
        "time": 13.454545
      },
      {
        "performance": 2.8789604,
        "time": 13.636364
      },
      {
        "performance": 2.6076133,
        "time": 14.0
      },
      {
        "performance": 2.682423,
        "time": 14.363636
      },
      {
        "performance": 2.0610359,
        "time": 14.545455
      },
      {
        "performance": 1.7865005,
        "time": 14.909091
      },
      {
        "performance": 1.8377534,
        "time": 15.090909
      },
      {
        "performance": 1.5623479,
        "time": 15.454545
      },
      {
        "performance": 1.2858689,
        "time": 15.818182
      },
      {
        "performance": 1.3227592,
        "time": 16.0
      },
      {
        "performance": 1.1150193,
        "time": 16.545454
      },
      {
        "performance": 0.48752287,
        "time": 16.90909
      }
    ]
  },
  "speed175": {
    "aim": [
      {
        "performance": 5.066901,
        "time": 2.4935064
      },
      {
        "performance": 4.2916636,
        "time": 2.6493506
      },
      {
        "performance": 3.5134046,
        "time": 2.8051949
      },
      {
        "performance": 2.6905096,
        "time": 2.961039
      },
      {
        "performance": 2.4005196,
        "time": 3.2727273
      },
      {
        "performance": 2.6351805,
        "time": 3.5844157
      },
      {
        "performance": 2.083311,
        "time": 3.8961039
      },
      {
        "performance": 2.1430793,
        "time": 4.051948
      },
      {
        "performance": 2.204562,
        "time": 4.2077923
      },
      {
        "performance": 1.912678,
        "time": 4.5194807
      },
      {
        "performance": 2.126553,
        "time": 4.6753244
      },
      {
        "performance": 2.0855403,
        "time": 4.987013
      },
      {
        "performance": 2.5169597,
        "time": 5.2987013
      },
      {
        "performance": 2.5891688,
        "time": 5.4545455
      },
      {
        "performance": 3.5480452,
        "time": 6.077922
      },
      {
        "performance": 3.1369362,
        "time": 6.233766
      },
      {
        "performance": 3.2269316,
        "time": 6.3896103
      },
      {
        "performance": 3.319509,
        "time": 6.5454545
      },
      {
        "performance": 3.4147425,
        "time": 6.7012987
      },
      {
        "performance": 3.1597304,
        "time": 7.3246756
      },
      {
        "performance": 2.3770595,
        "time": 7.4805193
      },
      {
        "performance": 2.9541194,
        "time": 7.7922077
      },
      {
        "performance": 3.0388703,
        "time": 7.948052
      },
      {
        "performance": 3.6770263,
        "time": 8.571428
      },
      {
        "performance": 3.019472,
        "time": 8.727273
      },
      {
        "performance": 2.7893364,
        "time": 9.038961
      },
      {
        "performance": 2.8693597,
        "time": 9.194805
      },
      {
        "performance": 2.813258,
        "time": 9.506494
      },
      {
        "performance": 2.82502,
        "time": 9.818182
      },
      {
        "performance": 2.3155904,
        "time": 9.974026
      },
      {
        "performance": 2.583419,
        "time": 10.285714
      },
      {
        "performance": 2.6575348,
        "time": 10.441559
      },
      {
        "performance": 3.414863,
        "time": 11.064935
      },
      {
        "performance": 3.5128322,
        "time": 11.220779
      },
      {
        "performance": 3.6136117,
        "time": 11.376623
      },
      {
        "performance": 3.7172825,
        "time": 11.532468
      },
      {
        "performance": 3.059885,
        "time": 11.688312
      },
      {
        "performance": 2.771335,
        "time": 12.0
      },
      {
        "performance": 2.8508418,
        "time": 12.311688
      },
      {
        "performance": 2.190067,
        "time": 12.467532
      },
      {
        "performance": 1.8981265,
        "time": 12.779221
      },
      {
        "performance": 1.9525819,
        "time": 12.935065
      },
      {
        "performance": 1.6597157,
        "time": 13.246754
      },
      {
        "performance": 1.365708,
        "time": 13.558441
      },
      {
        "performance": 1.4048889,
        "time": 13.714286
      },
      {
        "performance": 1.1856852,
        "time": 14.181818
      },
      {
        "performance": 0.5184203,
        "time": 14.493506
      }
    ],
    "tap": [
      {
        "performance": 5.066901,
        "time": 2.4935064
      },
      {
        "performance": 4.2916636,
        "time": 2.6493506
      },
      {
        "performance": 3.5134046,
        "time": 2.8051949
      },
      {
        "performance": 2.6905096,
        "time": 2.961039
      },
      {
        "performance": 2.4005196,
        "time": 3.2727273
      },
      {
        "performance": 2.6351805,
        "time": 3.5844157
      },
      {
        "performance": 2.083311,
        "time": 3.8961039
      },
      {
        "performance": 2.1430793,
        "time": 4.051948
      },
      {
        "performance": 2.204562,
        "time": 4.2077923
      },
      {
        "performance": 1.912678,
        "time": 4.5194807
      },
      {
        "performance": 2.126553,
        "time": 4.6753244
      },
      {
        "performance": 2.0855403,
        "time": 4.987013
      },
      {
        "performance": 2.5169597,
        "time": 5.2987013
      },
      {
        "performance": 2.5891688,
        "time": 5.4545455
      },
      {
        "performance": 3.5480452,
        "time": 6.077922
      },
      {
        "performance": 3.1369362,
        "time": 6.233766
      },
      {
        "performance": 3.2269316,
        "time": 6.3896103
      },
      {
        "performance": 3.319509,
        "time": 6.5454545
      },
      {
        "performance": 3.4147425,
        "time": 6.7012987
      },
      {
        "performance": 3.1597304,
        "time": 7.3246756
      },
      {
        "performance": 2.3770595,
        "time": 7.4805193
      },
      {
        "performance": 2.9541194,
        "time": 7.7922077
      },
      {
        "performance": 3.0388703,
        "time": 7.948052
      },
      {
        "performance": 3.6770263,
        "time": 8.571428
      },
      {
        "performance": 3.019472,
        "time": 8.727273
      },
      {
        "performance": 2.7893364,
        "time": 9.038961
      },
      {
        "performance": 2.8693597,
        "time": 9.194805
      },
      {
        "performance": 2.813258,
        "time": 9.506494
      },
      {
        "performance": 2.82502,
        "time": 9.818182
      },
      {
        "performance": 2.3155904,
        "time": 9.974026
      },
      {
        "performance": 2.583419,
        "time": 10.285714
      },
      {
        "performance": 2.6575348,
        "time": 10.441559
      },
      {
        "performance": 3.414863,
        "time": 11.064935
      },
      {
        "performance": 3.5128322,
        "time": 11.220779
      },
      {
        "performance": 3.6136117,
        "time": 11.376623
      },
      {
        "performance": 3.7172825,
        "time": 11.532468
      },
      {
        "performance": 3.059885,
        "time": 11.688312
      },
      {
        "performance": 2.771335,
        "time": 12.0
      },
      {
        "performance": 2.8508418,
        "time": 12.311688
      },
      {
        "performance": 2.190067,
        "time": 12.467532
      },
      {
        "performance": 1.8981265,
        "time": 12.779221
      },
      {
        "performance": 1.9525819,
        "time": 12.935065
      },
      {
        "performance": 1.6597157,
        "time": 13.246754
      },
      {
        "performance": 1.365708,
        "time": 13.558441
      },
      {
        "performance": 1.4048889,
        "time": 13.714286
      },
      {
        "performance": 1.1856852,
        "time": 14.181818
      },
      {
        "performance": 0.5184203,
        "time": 14.493506
      }
    ],
    "acc": [
      {
        "performance": 5.066901,
        "time": 2.4935064
      },
      {
        "performance": 4.2916636,
        "time": 2.6493506
      },
      {
        "performance": 3.5134046,
        "time": 2.8051949
      },
      {
        "performance": 2.6905096,
        "time": 2.961039
      },
      {
        "performance": 2.4005196,
        "time": 3.2727273
      },
      {
        "performance": 2.6351805,
        "time": 3.5844157
      },
      {
        "performance": 2.083311,
        "time": 3.8961039
      },
      {
        "performance": 2.1430793,
        "time": 4.051948
      },
      {
        "performance": 2.204562,
        "time": 4.2077923
      },
      {
        "performance": 1.912678,
        "time": 4.5194807
      },
      {
        "performance": 2.126553,
        "time": 4.6753244
      },
      {
        "performance": 2.0855403,
        "time": 4.987013
      },
      {
        "performance": 2.5169597,
        "time": 5.2987013
      },
      {
        "performance": 2.5891688,
        "time": 5.4545455
      },
      {
        "performance": 3.5480452,
        "time": 6.077922
      },
      {
        "performance": 3.1369362,
        "time": 6.233766
      },
      {
        "performance": 3.2269316,
        "time": 6.3896103
      },
      {
        "performance": 3.319509,
        "time": 6.5454545
      },
      {
        "performance": 3.4147425,
        "time": 6.7012987
      },
      {
        "performance": 3.1597304,
        "time": 7.3246756
      },
      {
        "performance": 2.3770595,
        "time": 7.4805193
      },
      {
        "performance": 2.9541194,
        "time": 7.7922077
      },
      {
        "performance": 3.0388703,
        "time": 7.948052
      },
      {
        "performance": 3.6770263,
        "time": 8.571428
      },
      {
        "performance": 3.019472,
        "time": 8.727273
      },
      {
        "performance": 2.7893364,
        "time": 9.038961
      },
      {
        "performance": 2.8693597,
        "time": 9.194805
      },
      {
        "performance": 2.813258,
        "time": 9.506494
      },
      {
        "performance": 2.82502,
        "time": 9.818182
      },
      {
        "performance": 2.3155904,
        "time": 9.974026
      },
      {
        "performance": 2.583419,
        "time": 10.285714
      },
      {
        "performance": 2.6575348,
        "time": 10.441559
      },
      {
        "performance": 3.414863,
        "time": 11.064935
      },
      {
        "performance": 3.5128322,
        "time": 11.220779
      },
      {
        "performance": 3.6136117,
        "time": 11.376623
      },
      {
        "performance": 3.7172825,
        "time": 11.532468
      },
      {
        "performance": 3.059885,
        "time": 11.688312
      },
      {
        "performance": 2.771335,
        "time": 12.0
      },
      {
        "performance": 2.8508418,
        "time": 12.311688
      },
      {
        "performance": 2.190067,
        "time": 12.467532
      },
      {
        "performance": 1.8981265,
        "time": 12.779221
      },
      {
        "performance": 1.9525819,
        "time": 12.935065
      },
      {
        "performance": 1.6597157,
        "time": 13.246754
      },
      {
        "performance": 1.365708,
        "time": 13.558441
      },
      {
        "performance": 1.4048889,
        "time": 13.714286
      },
      {
        "performance": 1.1856852,
        "time": 14.181818
      },
      {
        "performance": 0.5184203,
        "time": 14.493506
      }
    ]
  },
  "speed200": {
    "aim": [
      {
        "performance": 5.3553057,
        "time": 2.1818182
      },
      {
        "performance": 4.535942,
        "time": 2.3181818
      },
      {
        "performance": 4.0497236,
        "time": 2.4545455
      },
      {
        "performance": 3.821075,
        "time": 2.590909
      },
      {
        "performance": 3.5183887,
        "time": 2.8636363
      },
      {
        "performance": 2.787312,
        "time": 3.1363637
      },
      {
        "performance": 2.204039,
        "time": 3.409091
      },
      {
        "performance": 2.4264402,
        "time": 3.5454545
      },
      {
        "performance": 3.0188818,
        "time": 3.6818182
      },
      {
        "performance": 3.0827649,
        "time": 3.9545455
      },
      {
        "performance": 3.1712062,
        "time": 4.090909
      },
      {
        "performance": 2.823246,
        "time": 4.3636365
      },
      {
        "performance": 3.1438327,
        "time": 4.6363635
      },
      {
        "performance": 3.649009,
        "time": 4.7727275
      },
      {
        "performance": 3.7536955,
        "time": 5.318182
      },
      {
        "performance": 3.3192008,
        "time": 5.4545455
      },
      {
        "performance": 3.4144251,
        "time": 5.590909
      },
      {
        "performance": 3.680161,
        "time": 5.7272725
      },
      {
        "performance": 3.7857413,
        "time": 5.8636365
      },
      {
        "performance": 3.862686,
        "time": 6.409091
      },
      {
        "performance": 3.2704134,
        "time": 6.5454545
      },
      {
        "performance": 3.3642383,
        "time": 6.818182
      },
      {
        "performance": 3.9944155,
        "time": 6.9545455
      },
      {
        "performance": 4.1320357,
        "time": 7.5
      },
      {
        "performance": 3.675745,
        "time": 7.6363635
      },
      {
        "performance": 3.425668,
        "time": 7.909091
      },
      {
        "performance": 3.523947,
        "time": 8.045455
      },
      {
        "performance": 3.2201028,
        "time": 8.318182
      },
      {
        "performance": 3.1922112,
        "time": 8.590909
      },
      {
        "performance": 3.1882498,
        "time": 8.727273
      },
      {
        "performance": 3.7032974,
        "time": 9.0
      },
      {
        "performance": 3.8095415,
        "time": 9.136364
      },
      {
        "performance": 3.608199,
        "time": 9.681818
      },
      {
        "performance": 3.7117145,
        "time": 9.818182
      },
      {
        "performance": 3.8181999,
        "time": 9.954545
      },
      {
        "performance": 3.9277403,
        "time": 10.090909
      },
      {
        "performance": 3.2329197,
        "time": 10.227273
      },
      {
        "performance": 2.927941,
        "time": 10.5
      },
      {
        "performance": 3.0119407,
        "time": 10.772727
      },
      {
        "performance": 2.3135507,
        "time": 10.909091
      },
      {
        "performance": 2.0049884,
        "time": 11.181818
      },
      {
        "performance": 2.0625095,
        "time": 11.318182
      },
      {
        "performance": 1.752969,
        "time": 11.590909
      },
      {
        "performance": 1.4422219,
        "time": 11.863636
      },
      {
        "performance": 1.4835978,
        "time": 12.0
      },
      {
        "performance": 1.2531736,
        "time": 12.409091
      },
      {
        "performance": 0.5479284,
        "time": 12.681818
      }
    ],
    "tap": [
      {
        "performance": 5.3553057,
        "time": 2.1818182
      },
      {
        "performance": 4.535942,
        "time": 2.3181818
      },
      {
        "performance": 4.0497236,
        "time": 2.4545455
      },
      {
        "performance": 3.821075,
        "time": 2.590909
      },
      {
        "performance": 3.5183887,
        "time": 2.8636363
      },
      {
        "performance": 2.787312,
        "time": 3.1363637
      },
      {
        "performance": 2.204039,
        "time": 3.409091
      },
      {
        "performance": 2.4264402,
        "time": 3.5454545
      },
      {
        "performance": 3.0188818,
        "time": 3.6818182
      },
      {
        "performance": 3.0827649,
        "time": 3.9545455
      },
      {
        "performance": 3.1712062,
        "time": 4.090909
      },
      {
        "performance": 2.823246,
        "time": 4.3636365
      },
      {
        "performance": 3.1438327,
        "time": 4.6363635
      },
      {
        "performance": 3.649009,
        "time": 4.7727275
      },
      {
        "performance": 3.7536955,
        "time": 5.318182
      },
      {
        "performance": 3.3192008,
        "time": 5.4545455
      },
      {
        "performance": 3.4144251,
        "time": 5.590909
      },
      {
        "performance": 3.680161,
        "time": 5.7272725
      },
      {
        "performance": 3.7857413,
        "time": 5.8636365
      },
      {
        "performance": 3.862686,
        "time": 6.409091
      },
      {
        "performance": 3.2704134,
        "time": 6.5454545
      },
      {
        "performance": 3.3642383,
        "time": 6.818182
      },
      {
        "performance": 3.9944155,
        "time": 6.9545455
      },
      {
        "performance": 4.1320357,
        "time": 7.5
      },
      {
        "performance": 3.675745,
        "time": 7.6363635
      },
      {
        "performance": 3.425668,
        "time": 7.909091
      },
      {
        "performance": 3.523947,
        "time": 8.045455
      },
      {
        "performance": 3.2201028,
        "time": 8.318182
      },
      {
        "performance": 3.1922112,
        "time": 8.590909
      },
      {
        "performance": 3.1882498,
        "time": 8.727273
      },
      {
        "performance": 3.7032974,
        "time": 9.0
      },
      {
        "performance": 3.8095415,
        "time": 9.136364
      },
      {
        "performance": 3.608199,
        "time": 9.681818
      },
      {
        "performance": 3.7117145,
        "time": 9.818182
      },
      {
        "performance": 3.8181999,
        "time": 9.954545
      },
      {
        "performance": 3.9277403,
        "time": 10.090909
      },
      {
        "performance": 3.2329197,
        "time": 10.227273
      },
      {
        "performance": 2.927941,
        "time": 10.5
      },
      {
        "performance": 3.0119407,
        "time": 10.772727
      },
      {
        "performance": 2.3135507,
        "time": 10.909091
      },
      {
        "performance": 2.0049884,
        "time": 11.181818
      },
      {
        "performance": 2.0625095,
        "time": 11.318182
      },
      {
        "performance": 1.752969,
        "time": 11.590909
      },
      {
        "performance": 1.4422219,
        "time": 11.863636
      },
      {
        "performance": 1.4835978,
        "time": 12.0
      },
      {
        "performance": 1.2531736,
        "time": 12.409091
      },
      {
        "performance": 0.5479284,
        "time": 12.681818
      }
    ],
    "acc": [
      {
        "performance": 5.3553057,
        "time": 2.1818182
      },
      {
        "performance": 4.535942,
        "time": 2.3181818
      },
      {
        "performance": 4.0497236,
        "time": 2.4545455
      },
      {
        "performance": 3.821075,
        "time": 2.590909
      },
      {
        "performance": 3.5183887,
        "time": 2.8636363
      },
      {
        "performance": 2.787312,
        "time": 3.1363637
      },
      {
        "performance": 2.204039,
        "time": 3.409091
      },
      {
        "performance": 2.4264402,
        "time": 3.5454545
      },
      {
        "performance": 3.0188818,
        "time": 3.6818182
      },
      {
        "performance": 3.0827649,
        "time": 3.9545455
      },
      {
        "performance": 3.1712062,
        "time": 4.090909
      },
      {
        "performance": 2.823246,
        "time": 4.3636365
      },
      {
        "performance": 3.1438327,
        "time": 4.6363635
      },
      {
        "performance": 3.649009,
        "time": 4.7727275
      },
      {
        "performance": 3.7536955,
        "time": 5.318182
      },
      {
        "performance": 3.3192008,
        "time": 5.4545455
      },
      {
        "performance": 3.4144251,
        "time": 5.590909
      },
      {
        "performance": 3.680161,
        "time": 5.7272725
      },
      {
        "performance": 3.7857413,
        "time": 5.8636365
      },
      {
        "performance": 3.862686,
        "time": 6.409091
      },
      {
        "performance": 3.2704134,
        "time": 6.5454545
      },
      {
        "performance": 3.3642383,
        "time": 6.818182
      },
      {
        "performance": 3.9944155,
        "time": 6.9545455
      },
      {
        "performance": 4.1320357,
        "time": 7.5
      },
      {
        "performance": 3.675745,
        "time": 7.6363635
      },
      {
        "performance": 3.425668,
        "time": 7.909091
      },
      {
        "performance": 3.523947,
        "time": 8.045455
      },
      {
        "performance": 3.2201028,
        "time": 8.318182
      },
      {
        "performance": 3.1922112,
        "time": 8.590909
      },
      {
        "performance": 3.1882498,
        "time": 8.727273
      },
      {
        "performance": 3.7032974,
        "time": 9.0
      },
      {
        "performance": 3.8095415,
        "time": 9.136364
      },
      {
        "performance": 3.608199,
        "time": 9.681818
      },
      {
        "performance": 3.7117145,
        "time": 9.818182
      },
      {
        "performance": 3.8181999,
        "time": 9.954545
      },
      {
        "performance": 3.9277403,
        "time": 10.090909
      },
      {
        "performance": 3.2329197,
        "time": 10.227273
      },
      {
        "performance": 2.927941,
        "time": 10.5
      },
      {
        "performance": 3.0119407,
        "time": 10.772727
      },
      {
        "performance": 2.3135507,
        "time": 10.909091
      },
      {
        "performance": 2.0049884,
        "time": 11.181818
      },
      {
        "performance": 2.0625095,
        "time": 11.318182
      },
      {
        "performance": 1.752969,
        "time": 11.590909
      },
      {
        "performance": 1.4422219,
        "time": 11.863636
      },
      {
        "performance": 1.4835978,
        "time": 12.0
      },
      {
        "performance": 1.2531736,
        "time": 12.409091
      },
      {
        "performance": 0.5479284,
        "time": 12.681818
      }
    ]
  }
}
