{
  "speed050": {
    "aim": [
      {
        "performance": 3.0436425,
        "time": 3.137255
      },
      {
        "performance": 3.0704718,
        "time": 3.3333333
      },
      {
        "performance": 3.0442855,
        "time": 3.5294118
      },
      {
        "performance": 3.1820009,
        "time": 3.72549
      },
      {
        "performance": 3.005065,
        "time": 4.117647
      },
      {
        "performance": 3.0160327,
        "time": 4.3137255
      },
      {
        "performance": 2.8784194,
        "time": 4.509804
      },
      {
        "performance": 2.7814813,
        "time": 4.7058825
      },
      {
        "performance": 2.759511,
        "time": 5.098039
      },
      {
        "performance": 3.1235092,
        "time": 5.490196
      },
      {
        "performance": 3.5838,
        "time": 5.6862745
      },
      {
        "performance": 3.6754684,
        "time": 6.27451
      },
      {
        "performance": 3.5923958,
        "time": 6.470588
      },
      {
        "performance": 3.5453513,
        "time": 6.6666665
      },
      {
        "performance": 3.689754,
        "time": 6.8627453
      },
      {
        "performance": 3.470965,
        "time": 7.254902
      },
      {
        "performance": 3.4711483,
        "time": 7.45098
      },
      {
        "performance": 3.3017566,
        "time": 7.647059
      },
      {
        "performance": 3.1808963,
        "time": 7.8431373
      },
      {
        "performance": 3.146922,
        "time": 8.235294
      },
      {
        "performance": 3.458914,
        "time": 8.627451
      },
      {
        "performance": 3.4312866,
        "time": 8.823529
      },
      {
        "performance": 3.1383579,
        "time": 9.411765
      },
      {
        "performance": 2.8745005,
        "time": 9.607843
      },
      {
        "performance": 2.5749495,
        "time": 9.803922
      },
      {
        "performance": 2.1417975,
        "time": 10.0
      },
      {
        "performance": 1.9717948,
        "time": 10.392157
      },
      {
        "performance": 1.913783,
        "time": 10.588235
      },
      {
        "performance": 1.7917696,
        "time": 10.784314
      },
      {
        "performance": 1.6991248,
        "time": 10.980392
      },
      {
        "performance": 2.051987,
        "time": 11.372549
      },
      {
        "performance": 2.11963,
        "time": 11.764706
      },
      {
        "performance": 2.0021515,
        "time": 11.960784
      },
      {
        "performance": 2.151363,
        "time": 12.54902
      },
      {
        "performance": 2.2405503,
        "time": 12.941176
      },
      {
        "performance": 2.1157606,
        "time": 13.529411
      },
      {
        "performance": 1.9917657,
        "time": 14.313725
      },
      {
        "performance": 1.8585025,
        "time": 14.509804
      },
      {
        "performance": 1.7025255,
        "time": 14.705882
      },
      {
        "performance": 1.3459423,
        "time": 15.09804
      },
      {
        "performance": 1.1040967,
        "time": 15.294118
      },
      {
        "performance": 0.7895507,
        "time": 15.490196
      },
      {
        "performance": 0.66261053,
        "time": 15.882353
      },
      {
        "performance": 0.48150983,
        "time": 16.470589
      },
      {
        "performance": 0.20825933,
        "time": 16.666666
      },
      {
        "performance": 0.36223492,
        "time": 17.058823
      },
      {
        "performance": 0.2778229,
        "time": 23.529411
      },
      {
        "performance": 0.0,
        "time": 23.72549
      }
    ],
    "tap": [
      {
        "performance": 3.0436425,
        "time": 3.137255
      },
      {
        "performance": 3.0704718,
        "time": 3.3333333
      },
      {
        "performance": 3.0442855,
        "time": 3.5294118
      },
      {
        "performance": 3.1820009,
        "time": 3.72549
      },
      {
        "performance": 3.005065,
        "time": 4.117647
      },
      {
        "performance": 3.0160327,
        "time": 4.3137255
      },
      {
        "performance": 2.8784194,
        "time": 4.509804
      },
      {
        "performance": 2.7814813,
        "time": 4.7058825
      },
      {
        "performance": 2.759511,
        "time": 5.098039
      },
      {
        "performance": 3.1235092,
        "time": 5.490196
      },
      {
        "performance": 3.5838,
        "time": 5.6862745
      },
      {
        "performance": 3.6754684,
        "time": 6.27451
      },
      {
        "performance": 3.5923958,
        "time": 6.470588
      },
      {
        "performance": 3.5453513,
        "time": 6.6666665
      },
      {
        "performance": 3.689754,
        "time": 6.8627453
      },
      {
        "performance": 3.470965,
        "time": 7.254902
      },
      {
        "performance": 3.4711483,
        "time": 7.45098
      },
      {
        "performance": 3.3017566,
        "time": 7.647059
      },
      {
        "performance": 3.1808963,
        "time": 7.8431373
      },
      {
        "performance": 3.146922,
        "time": 8.235294
      },
      {
        "performance": 3.458914,
        "time": 8.627451
      },
      {
        "performance": 3.4312866,
        "time": 8.823529
      },
      {
        "performance": 3.1383579,
        "time": 9.411765
      },
      {
        "performance": 2.8745005,
        "time": 9.607843
      },
      {
        "performance": 2.5749495,
        "time": 9.803922
      },
      {
        "performance": 2.1417975,
        "time": 10.0
      },
      {
        "performance": 1.9717948,
        "time": 10.392157
      },
      {
        "performance": 1.913783,
        "time": 10.588235
      },
      {
        "performance": 1.7917696,
        "time": 10.784314
      },
      {
        "performance": 1.6991248,
        "time": 10.980392
      },
      {
        "performance": 2.051987,
        "time": 11.372549
      },
      {
        "performance": 2.11963,
        "time": 11.764706
      },
      {
        "performance": 2.0021515,
        "time": 11.960784
      },
      {
        "performance": 2.151363,
        "time": 12.54902
      },
      {
        "performance": 2.2405503,
        "time": 12.941176
      },
      {
        "performance": 2.1157606,
        "time": 13.529411
      },
      {
        "performance": 1.9917657,
        "time": 14.313725
      },
      {
        "performance": 1.8585025,
        "time": 14.509804
      },
      {
        "performance": 1.7025255,
        "time": 14.705882
      },
      {
        "performance": 1.3459423,
        "time": 15.09804
      },
      {
        "performance": 1.1040967,
        "time": 15.294118
      },
      {
        "performance": 0.7895507,
        "time": 15.490196
      },
      {
        "performance": 0.66261053,
        "time": 15.882353
      },
      {
        "performance": 0.48150983,
        "time": 16.470589
      },
      {
        "performance": 0.20825933,
        "time": 16.666666
      },
      {
        "performance": 0.36223492,
        "time": 17.058823
      },
      {
        "performance": 0.2778229,
        "time": 23.529411
      },
      {
        "performance": 0.0,
        "time": 23.72549
      }
    ],
    "acc": [
      {
        "performance": 3.0436425,
        "time": 3.137255
      },
      {
        "performance": 3.0704718,
        "time": 3.3333333
      },
      {
        "performance": 3.0442855,
        "time": 3.5294118
      },
      {
        "performance": 3.1820009,
        "time": 3.72549
      },
      {
        "performance": 3.005065,
        "time": 4.117647
      },
      {
        "performance": 3.0160327,
        "time": 4.3137255
      },
      {
        "performance": 2.8784194,
        "time": 4.509804
      },
      {
        "performance": 2.7814813,
        "time": 4.7058825
      },
      {
        "performance": 2.759511,
        "time": 5.098039
      },
      {
        "performance": 3.1235092,
        "time": 5.490196
      },
      {
        "performance": 3.5838,
        "time": 5.6862745
      },
      {
        "performance": 3.6754684,
        "time": 6.27451
      },
      {
        "performance": 3.5923958,
        "time": 6.470588
      },
      {
        "performance": 3.5453513,
        "time": 6.6666665
      },
      {
        "performance": 3.689754,
        "time": 6.8627453
      },
      {
        "performance": 3.470965,
        "time": 7.254902
      },
      {
        "performance": 3.4711483,
        "time": 7.45098
      },
      {
        "performance": 3.3017566,
        "time": 7.647059
      },
      {
        "performance": 3.1808963,
        "time": 7.8431373
      },
      {
        "performance": 3.146922,
        "time": 8.235294
      },
      {
        "performance": 3.458914,
        "time": 8.627451
      },
      {
        "performance": 3.4312866,
        "time": 8.823529
      },
      {
        "performance": 3.1383579,
        "time": 9.411765
      },
      {
        "performance": 2.8745005,
        "time": 9.607843
      },
      {
        "performance": 2.5749495,
        "time": 9.803922
      },
      {
        "performance": 2.1417975,
        "time": 10.0
      },
      {
        "performance": 1.9717948,
        "time": 10.392157
      },
      {
        "performance": 1.913783,
        "time": 10.588235
      },
      {
        "performance": 1.7917696,
        "time": 10.784314
      },
      {
        "performance": 1.6991248,
        "time": 10.980392
      },
      {
        "performance": 2.051987,
        "time": 11.372549
      },
      {
        "performance": 2.11963,
        "time": 11.764706
      },
      {
        "performance": 2.0021515,
        "time": 11.960784
      },
      {
        "performance": 2.151363,
        "time": 12.54902
      },
      {
        "performance": 2.2405503,
        "time": 12.941176
      },
      {
        "performance": 2.1157606,
        "time": 13.529411
      },
      {
        "performance": 1.9917657,
        "time": 14.313725
      },
      {
        "performance": 1.8585025,
        "time": 14.509804
      },
      {
        "performance": 1.7025255,
        "time": 14.705882
      },
      {
        "performance": 1.3459423,
        "time": 15.09804
      },
      {
        "performance": 1.1040967,
        "time": 15.294118
      },
      {
        "performance": 0.7895507,
        "time": 15.490196
      },
      {
        "performance": 0.66261053,
        "time": 15.882353
      },
      {
        "performance": 0.48150983,
        "time": 16.470589
      },
      {
        "performance": 0.20825933,
        "time": 16.666666
      },
      {
        "performance": 0.36223492,
        "time": 17.058823
      },
      {
        "performance": 0.2778229,
        "time": 23.529411
      },
      {
        "performance": 0.0,
        "time": 23.72549
      }
    ]
  },
  "speed075": {
    "aim": [
      {
        "performance": 4.689435,
        "time": 2.0915034
      },
      {
        "performance": 4.5611005,
        "time": 2.2222223
      },
      {
        "performance": 4.6210766,
        "time": 2.3529413
      },
      {
        "performance": 4.8587623,
        "time": 2.4836602
      },
      {
        "performance": 5.0286503,
        "time": 2.745098
      },
      {
        "performance": 5.0113664,
        "time": 2.875817
      },
      {
        "performance": 5.1408944,
        "time": 3.006536
      },
      {
        "performance": 5.287144,
        "time": 3.137255
      },
      {
        "performance": 5.6588483,
        "time": 3.3986928
      },
      {
        "performance": 6.036398,
        "time": 3.6601307
      },
      {
        "performance": 6.0338125,
        "time": 3.7908497
      },
      {
        "performance": 6.0331287,
        "time": 4.183007
      },
      {
        "performance": 5.6815834,
        "time": 4.3137255
      },
      {
        "performance": 5.6207185,
        "time": 4.4444447
      },
      {
        "performance": 5.3460865,
        "time": 4.5751634
      },
      {
        "performance": 5.116327,
        "time": 4.8366013
      },
      {
        "performance": 5.0028,
        "time": 4.9673204
      },
      {
        "performance": 4.995092,
        "time": 5.098039
      },
      {
        "performance": 4.62312,
        "time": 5.2287583
      },
      {
        "performance": 4.76082,
        "time": 5.490196
      },
      {
        "performance": 5.105666,
        "time": 5.751634
      },
      {
        "performance": 5.125969,
        "time": 5.882353
      },
      {
        "performance": 5.3419952,
        "time": 6.27451
      },
      {
        "performance": 5.124755,
        "time": 6.4052286
      },
      {
        "performance": 4.774941,
        "time": 6.535948
      },
      {
        "performance": 4.391963,
        "time": 6.6666665
      },
      {
        "performance": 4.0596924,
        "time": 6.9281044
      },
      {
        "performance": 3.9994664,
        "time": 7.0588236
      },
      {
        "performance": 3.9378817,
        "time": 7.1895423
      },
      {
        "performance": 3.6430724,
        "time": 7.3202615
      },
      {
        "performance": 3.5608456,
        "time": 7.5816994
      },
      {
        "performance": 3.6809912,
        "time": 7.8431373
      },
      {
        "performance": 3.4031756,
        "time": 7.973856
      },
      {
        "performance": 3.1761115,
        "time": 8.366014
      },
      {
        "performance": 3.0473726,
        "time": 8.627451
      },
      {
        "performance": 2.817068,
        "time": 9.019608
      },
      {
        "performance": 2.6615436,
        "time": 9.542483
      },
      {
        "performance": 2.4737418,
        "time": 9.6732025
      },
      {
        "performance": 2.2588744,
        "time": 9.803922
      },
      {
        "performance": 1.7927727,
        "time": 10.065359
      },
      {
        "performance": 1.470746,
        "time": 10.196078
      },
      {
        "performance": 1.0566242,
        "time": 10.3267975
      },
      {
        "performance": 0.8429528,
        "time": 10.588235
      },
      {
        "performance": 0.6245699,
        "time": 10.980392
      },
      {
        "performance": 0.2663472,
        "time": 11.111111
      },
      {
        "performance": 0.44212565,
        "time": 11.372549
      },
      {
        "performance": 0.3624159,
        "time": 15.686275
      },
      {
        "performance": 0.0,
        "time": 15.816994
      }
    ],
    "tap": [
      {
        "performance": 4.689435,
        "time": 2.0915034
      },
      {
        "performance": 4.5611005,
        "time": 2.2222223
      },
      {
        "performance": 4.6210766,
        "time": 2.3529413
      },
      {
        "performance": 4.8587623,
        "time": 2.4836602
      },
      {
        "performance": 5.0286503,
        "time": 2.745098
      },
      {
        "performance": 5.0113664,
        "time": 2.875817
      },
      {
        "performance": 5.1408944,
        "time": 3.006536
      },
      {
        "performance": 5.287144,
        "time": 3.137255
      },
      {
        "performance": 5.6588483,
        "time": 3.3986928
      },
      {
        "performance": 6.036398,
        "time": 3.6601307
      },
      {
        "performance": 6.0338125,
        "time": 3.7908497
      },
      {
        "performance": 6.0331287,
        "time": 4.183007
      },
      {
        "performance": 5.6815834,
        "time": 4.3137255
      },
      {
        "performance": 5.6207185,
        "time": 4.4444447
      },
      {
        "performance": 5.3460865,
        "time": 4.5751634
      },
      {
        "performance": 5.116327,
        "time": 4.8366013
      },
      {
        "performance": 5.0028,
        "time": 4.9673204
      },
      {
        "performance": 4.995092,
        "time": 5.098039
      },
      {
        "performance": 4.62312,
        "time": 5.2287583
      },
      {
        "performance": 4.76082,
        "time": 5.490196
      },
      {
        "performance": 5.105666,
        "time": 5.751634
      },
      {
        "performance": 5.125969,
        "time": 5.882353
      },
      {
        "performance": 5.3419952,
        "time": 6.27451
      },
      {
        "performance": 5.124755,
        "time": 6.4052286
      },
      {
        "performance": 4.774941,
        "time": 6.535948
      },
      {
        "performance": 4.391963,
        "time": 6.6666665
      },
      {
        "performance": 4.0596924,
        "time": 6.9281044
      },
      {
        "performance": 3.9994664,
        "time": 7.0588236
      },
      {
        "performance": 3.9378817,
        "time": 7.1895423
      },
      {
        "performance": 3.6430724,
        "time": 7.3202615
      },
      {
        "performance": 3.5608456,
        "time": 7.5816994
      },
      {
        "performance": 3.6809912,
        "time": 7.8431373
      },
      {
        "performance": 3.4031756,
        "time": 7.973856
      },
      {
        "performance": 3.1761115,
        "time": 8.366014
      },
      {
        "performance": 3.0473726,
        "time": 8.627451
      },
      {
        "performance": 2.817068,
        "time": 9.019608
      },
      {
        "performance": 2.6615436,
        "time": 9.542483
      },
      {
        "performance": 2.4737418,
        "time": 9.6732025
      },
      {
        "performance": 2.2588744,
        "time": 9.803922
      },
      {
        "performance": 1.7927727,
        "time": 10.065359
      },
      {
        "performance": 1.470746,
        "time": 10.196078
      },
      {
        "performance": 1.0566242,
        "time": 10.3267975
      },
      {
        "performance": 0.8429528,
        "time": 10.588235
      },
      {
        "performance": 0.6245699,
        "time": 10.980392
      },
      {
        "performance": 0.2663472,
        "time": 11.111111
      },
      {
        "performance": 0.44212565,
        "time": 11.372549
      },
      {
        "performance": 0.3624159,
        "time": 15.686275
      },
      {
        "performance": 0.0,
        "time": 15.816994
      }
    ],
    "acc": [
      {
        "performance": 4.689435,
        "time": 2.0915034
      },
      {
        "performance": 4.5611005,
        "time": 2.2222223
      },
      {
        "performance": 4.6210766,
        "time": 2.3529413
      },
      {
        "performance": 4.8587623,
        "time": 2.4836602
      },
      {
        "performance": 5.0286503,
        "time": 2.745098
      },
      {
        "performance": 5.0113664,
        "time": 2.875817
      },
      {
        "performance": 5.1408944,
        "time": 3.006536
      },
      {
        "performance": 5.287144,
        "time": 3.137255
      },
      {
        "performance": 5.6588483,
        "time": 3.3986928
      },
      {
        "performance": 6.036398,
        "time": 3.6601307
      },
      {
        "performance": 6.0338125,
        "time": 3.7908497
      },
      {
        "performance": 6.0331287,
        "time": 4.183007
      },
      {
        "performance": 5.6815834,
        "time": 4.3137255
      },
      {
        "performance": 5.6207185,
        "time": 4.4444447
      },
      {
        "performance": 5.3460865,
        "time": 4.5751634
      },
      {
        "performance": 5.116327,
        "time": 4.8366013
      },
      {
        "performance": 5.0028,
        "time": 4.9673204
      },
      {
        "performance": 4.995092,
        "time": 5.098039
      },
      {
        "performance": 4.62312,
        "time": 5.2287583
      },
      {
        "performance": 4.76082,
        "time": 5.490196
      },
      {
        "performance": 5.105666,
        "time": 5.751634
      },
      {
        "performance": 5.125969,
        "time": 5.882353
      },
      {
        "performance": 5.3419952,
        "time": 6.27451
      },
      {
        "performance": 5.124755,
        "time": 6.4052286
      },
      {
        "performance": 4.774941,
        "time": 6.535948
      },
      {
        "performance": 4.391963,
        "time": 6.6666665
      },
      {
        "performance": 4.0596924,
        "time": 6.9281044
      },
      {
        "performance": 3.9994664,
        "time": 7.0588236
      },
      {
        "performance": 3.9378817,
        "time": 7.1895423
      },
      {
        "performance": 3.6430724,
        "time": 7.3202615
      },
      {
        "performance": 3.5608456,
        "time": 7.5816994
      },
      {
        "performance": 3.6809912,
        "time": 7.8431373
      },
      {
        "performance": 3.4031756,
        "time": 7.973856
      },
      {
        "performance": 3.1761115,
        "time": 8.366014
      },
      {
        "performance": 3.0473726,
        "time": 8.627451
      },
      {
        "performance": 2.817068,
        "time": 9.019608
      },
      {
        "performance": 2.6615436,
        "time": 9.542483
      },
      {
        "performance": 2.4737418,
        "time": 9.6732025
      },
      {
        "performance": 2.2588744,
        "time": 9.803922
      },
      {
        "performance": 1.7927727,
        "time": 10.065359
      },
      {
        "performance": 1.470746,
        "time": 10.196078
      },
      {
        "performance": 1.0566242,
        "time": 10.3267975
      },
      {
        "performance": 0.8429528,
        "time": 10.588235
      },
      {
        "performance": 0.6245699,
        "time": 10.980392
      },
      {
        "performance": 0.2663472,
        "time": 11.111111
      },
      {
        "performance": 0.44212565,
        "time": 11.372549
      },
      {
        "performance": 0.3624159,
        "time": 15.686275
      },
      {
        "performance": 0.0,
        "time": 15.816994
      }
    ]
  },
  "speed100": {
    "aim": [
      {
        "performance": 6.3881416,
        "time": 1.5686275
      },
      {
        "performance": 6.540649,
        "time": 1.6666666
      },
      {
        "performance": 6.625546,
        "time": 1.7647059
      },
      {
        "performance": 6.588212,
        "time": 1.862745
      },
      {
        "performance": 6.785149,
        "time": 2.0588236
      },
      {
        "performance": 6.932982,
        "time": 2.1568627
      },
      {
        "performance": 6.9016175,
        "time": 2.254902
      },
      {
        "performance": 6.848108,
        "time": 2.3529413
      },
      {
        "performance": 7.177805,
        "time": 2.5490196
      },
      {
        "performance": 7.685221,
        "time": 2.745098
      },
      {
        "performance": 7.925211,
        "time": 2.8431373
      },
      {
        "performance": 7.7540464,
        "time": 3.137255
      },
      {
        "performance": 7.4936123,
        "time": 3.235294
      },
      {
        "performance": 7.3834486,
        "time": 3.3333333
      },
      {
        "performance": 7.080156,
        "time": 3.4313726
      },
      {
        "performance": 7.1392746,
        "time": 3.627451
      },
      {
        "performance": 7.2724175,
        "time": 3.72549
      },
      {
        "performance": 7.367413,
        "time": 3.8235295
      },
      {
        "performance": 7.134453,
        "time": 3.9215686
      },
      {
        "performance": 7.204925,
        "time": 4.117647
      },
      {
        "performance": 7.649419,
        "time": 4.3137255
      },
      {
        "performance": 7.7890635,
        "time": 4.4117646
      },
      {
        "performance": 7.6481657,
        "time": 4.7058825
      },
      {
        "performance": 7.087259,
        "time": 4.8039217
      },
      {
        "performance": 6.6738496,
        "time": 4.901961
      },
      {
        "performance": 6.0077515,
        "time": 5.0
      },
      {
        "performance": 5.604099,
        "time": 5.1960783
      },
      {
        "performance": 5.3362665,
        "time": 5.2941175
      },
      {
        "performance": 4.967488,
        "time": 5.392157
      },
      {
        "performance": 4.3888774,
        "time": 5.490196
      },
      {
        "performance": 4.2826614,
        "time": 5.6862745
      },
      {
        "performance": 4.405369,
        "time": 5.882353
      },
      {
        "performance": 4.063551,
        "time": 5.980392
      },
      {
        "performance": 3.8007658,
        "time": 6.27451
      },
      {
        "performance": 3.5945163,
        "time": 6.470588
      },
      {
        "performance": 3.2544708,
        "time": 6.7647057
      },
      {
        "performance": 3.0703156,
        "time": 7.1568627
      },
      {
        "performance": 2.8558798,
        "time": 7.254902
      },
      {
        "performance": 2.6093006,
        "time": 7.352941
      },
      {
        "performance": 2.0834782,
        "time": 7.54902
      },
      {
        "performance": 1.7153766,
        "time": 7.647059
      },
      {
        "performance": 1.3222901,
        "time": 7.745098
      },
      {
        "performance": 1.4185319,
        "time": 7.9411764
      },
      {
        "performance": 1.1909788,
        "time": 8.235294
      },
      {
        "performance": 0.7894329,
        "time": 8.333333
      },
      {
        "performance": 0.49671143,
        "time": 8.529411
      },
      {
        "performance": 0.41576564,
        "time": 11.764706
      },
      {
        "performance": 0.0,
        "time": 11.862745
      }
    ],
    "tap": [
      {
        "performance": 6.3881416,
        "time": 1.5686275
      },
      {
        "performance": 6.540649,
        "time": 1.6666666
      },
      {
        "performance": 6.625546,
        "time": 1.7647059
      },
      {
        "performance": 6.588212,
        "time": 1.862745
      },
      {
        "performance": 6.785149,
        "time": 2.0588236
      },
      {
        "performance": 6.932982,
        "time": 2.1568627
      },
      {
        "performance": 6.9016175,
        "time": 2.254902
      },
      {
        "performance": 6.848108,
        "time": 2.3529413
      },
      {
        "performance": 7.177805,
        "time": 2.5490196
      },
      {
        "performance": 7.685221,
        "time": 2.745098
      },
      {
        "performance": 7.925211,
        "time": 2.8431373
      },
      {
        "performance": 7.7540464,
        "time": 3.137255
      },
      {
        "performance": 7.4936123,
        "time": 3.235294
      },
      {
        "performance": 7.3834486,
        "time": 3.3333333
      },
      {
        "performance": 7.080156,
        "time": 3.4313726
      },
      {
        "performance": 7.1392746,
        "time": 3.627451
      },
      {
        "performance": 7.2724175,
        "time": 3.72549
      },
      {
        "performance": 7.367413,
        "time": 3.8235295
      },
      {
        "performance": 7.134453,
        "time": 3.9215686
      },
      {
        "performance": 7.204925,
        "time": 4.117647
      },
      {
        "performance": 7.649419,
        "time": 4.3137255
      },
      {
        "performance": 7.7890635,
        "time": 4.4117646
      },
      {
        "performance": 7.6481657,
        "time": 4.7058825
      },
      {
        "performance": 7.087259,
        "time": 4.8039217
      },
      {
        "performance": 6.6738496,
        "time": 4.901961
      },
      {
        "performance": 6.0077515,
        "time": 5.0
      },
      {
        "performance": 5.604099,
        "time": 5.1960783
      },
      {
        "performance": 5.3362665,
        "time": 5.2941175
      },
      {
        "performance": 4.967488,
        "time": 5.392157
      },
      {
        "performance": 4.3888774,
        "time": 5.490196
      },
      {
        "performance": 4.2826614,
        "time": 5.6862745
      },
      {
        "performance": 4.405369,
        "time": 5.882353
      },
      {
        "performance": 4.063551,
        "time": 5.980392
      },
      {
        "performance": 3.8007658,
        "time": 6.27451
      },
      {
        "performance": 3.5945163,
        "time": 6.470588
      },
      {
        "performance": 3.2544708,
        "time": 6.7647057
      },
      {
        "performance": 3.0703156,
        "time": 7.1568627
      },
      {
        "performance": 2.8558798,
        "time": 7.254902
      },
      {
        "performance": 2.6093006,
        "time": 7.352941
      },
      {
        "performance": 2.0834782,
        "time": 7.54902
      },
      {
        "performance": 1.7153766,
        "time": 7.647059
      },
      {
        "performance": 1.3222901,
        "time": 7.745098
      },
      {
        "performance": 1.4185319,
        "time": 7.9411764
      },
      {
        "performance": 1.1909788,
        "time": 8.235294
      },
      {
        "performance": 0.7894329,
        "time": 8.333333
      },
      {
        "performance": 0.49671143,
        "time": 8.529411
      },
      {
        "performance": 0.41576564,
        "time": 11.764706
      },
      {
        "performance": 0.0,
        "time": 11.862745
      }
    ],
    "acc": [
      {
        "performance": 6.3881416,
        "time": 1.5686275
      },
      {
        "performance": 6.540649,
        "time": 1.6666666
      },
      {
        "performance": 6.625546,
        "time": 1.7647059
      },
      {
        "performance": 6.588212,
        "time": 1.862745
      },
      {
        "performance": 6.785149,
        "time": 2.0588236
      },
      {
        "performance": 6.932982,
        "time": 2.1568627
      },
      {
        "performance": 6.9016175,
        "time": 2.254902
      },
      {
        "performance": 6.848108,
        "time": 2.3529413
      },
      {
        "performance": 7.177805,
        "time": 2.5490196
      },
      {
        "performance": 7.685221,
        "time": 2.745098
      },
      {
        "performance": 7.925211,
        "time": 2.8431373
      },
      {
        "performance": 7.7540464,
        "time": 3.137255
      },
      {
        "performance": 7.4936123,
        "time": 3.235294
      },
      {
        "performance": 7.3834486,
        "time": 3.3333333
      },
      {
        "performance": 7.080156,
        "time": 3.4313726
      },
      {
        "performance": 7.1392746,
        "time": 3.627451
      },
      {
        "performance": 7.2724175,
        "time": 3.72549
      },
      {
        "performance": 7.367413,
        "time": 3.8235295
      },
      {
        "performance": 7.134453,
        "time": 3.9215686
      },
      {
        "performance": 7.204925,
        "time": 4.117647
      },
      {
        "performance": 7.649419,
        "time": 4.3137255
      },
      {
        "performance": 7.7890635,
        "time": 4.4117646
      },
      {
        "performance": 7.6481657,
        "time": 4.7058825
      },
      {
        "performance": 7.087259,
        "time": 4.8039217
      },
      {
        "performance": 6.6738496,
        "time": 4.901961
      },
      {
        "performance": 6.0077515,
        "time": 5.0
      },
      {
        "performance": 5.604099,
        "time": 5.1960783
      },
      {
        "performance": 5.3362665,
        "time": 5.2941175
      },
      {
        "performance": 4.967488,
        "time": 5.392157
      },
      {
        "performance": 4.3888774,
        "time": 5.490196
      },
      {
        "performance": 4.2826614,
        "time": 5.6862745
      },
      {
        "performance": 4.405369,
        "time": 5.882353
      },
      {
        "performance": 4.063551,
        "time": 5.980392
      },
      {
        "performance": 3.8007658,
        "time": 6.27451
      },
      {
        "performance": 3.5945163,
        "time": 6.470588
      },
      {
        "performance": 3.2544708,
        "time": 6.7647057
      },
      {
        "performance": 3.0703156,
        "time": 7.1568627
      },
      {
        "performance": 2.8558798,
        "time": 7.254902
      },
      {
        "performance": 2.6093006,
        "time": 7.352941
      },
      {
        "performance": 2.0834782,
        "time": 7.54902
      },
      {
        "performance": 1.7153766,
        "time": 7.647059
      },
      {
        "performance": 1.3222901,
        "time": 7.745098
      },
      {
        "performance": 1.4185319,
        "time": 7.9411764
      },
      {
        "performance": 1.1909788,
        "time": 8.235294
      },
      {
        "performance": 0.7894329,
        "time": 8.333333
      },
      {
        "performance": 0.49671143,
        "time": 8.529411
      },
      {
        "performance": 0.41576564,
        "time": 11.764706
      },
      {
        "performance": 0.0,
        "time": 11.862745
      }
    ]
  },
  "speed125": {
    "aim": [
      {
        "performance": 7.0947285,
        "time": 1.254902
      },
      {
        "performance": 7.28328,
        "time": 1.3333334
      },
      {
        "performance": 7.397754,
        "time": 1.4117647
      },
      {
        "performance": 7.372181,
        "time": 1.4901961
      },
      {
        "performance": 7.616087,
        "time": 1.6470588
      },
      {
        "performance": 7.7940044,
        "time": 1.7254902
      },
      {
        "performance": 7.770218,
        "time": 1.8039216
      },
      {
        "performance": 7.720016,
        "time": 1.882353
      },
      {
        "performance": 8.103249,
        "time": 2.0392158
      },
      {
        "performance": 8.708935,
        "time": 2.1960785
      },
      {
        "performance": 9.021303,
        "time": 2.27451
      },
      {
        "performance": 8.994681,
        "time": 2.509804
      },
      {
        "performance": 8.724567,
        "time": 2.5882354
      },
      {
        "performance": 8.610225,
        "time": 2.6666667
      },
      {
        "performance": 8.428547,
        "time": 2.745098
      },
      {
        "performance": 8.433678,
        "time": 2.9019608
      },
      {
        "performance": 8.653499,
        "time": 2.9803922
      },
      {
        "performance": 8.676735,
        "time": 3.0588236
      },
      {
        "performance": 8.388403,
        "time": 3.137255
      },
      {
        "performance": 8.742479,
        "time": 3.2941177
      },
      {
        "performance": 9.297515,
        "time": 3.4509804
      },
      {
        "performance": 9.180746,
        "time": 3.5294118
      },
      {
        "performance": 8.740569,
        "time": 3.764706
      },
      {
        "performance": 8.022071,
        "time": 3.8431373
      },
      {
        "performance": 7.5047383,
        "time": 3.9215686
      },
      {
        "performance": 6.763006,
        "time": 4.0
      },
      {
        "performance": 6.3255863,
        "time": 4.1568627
      },
      {
        "performance": 6.0309634,
        "time": 4.2352943
      },
      {
        "performance": 5.620913,
        "time": 4.3137255
      },
      {
        "performance": 4.981235,
        "time": 4.392157
      },
      {
        "performance": 4.8696494,
        "time": 4.54902
      },
      {
        "performance": 5.009646,
        "time": 4.7058825
      },
      {
        "performance": 4.6324077,
        "time": 4.7843137
      },
      {
        "performance": 4.35104,
        "time": 5.019608
      },
      {
        "performance": 4.082617,
        "time": 5.1764708
      },
      {
        "performance": 3.7183049,
        "time": 5.4117646
      },
      {
        "performance": 3.8899868,
        "time": 5.72549
      },
      {
        "performance": 3.664826,
        "time": 5.8039217
      },
      {
        "performance": 3.4004312,
        "time": 5.882353
      },
      {
        "performance": 2.8264832,
        "time": 6.0392156
      },
      {
        "performance": 2.4314687,
        "time": 6.117647
      },
      {
        "performance": 1.9194933,
        "time": 6.1960783
      },
      {
        "performance": 1.566817,
        "time": 6.352941
      },
      {
        "performance": 1.318347,
        "time": 6.5882354
      },
      {
        "performance": 0.8716807,
        "time": 6.6666665
      },
      {
        "performance": 0.54790205,
        "time": 6.8235292
      },
      {
        "performance": 0.46270776,
        "time": 9.411765
      },
      {
        "performance": 0.0,
        "time": 9.490196
      }
    ],
    "tap": [
      {
        "performance": 7.0947285,
        "time": 1.254902
      },
      {
        "performance": 7.28328,
        "time": 1.3333334
      },
      {
        "performance": 7.397754,
        "time": 1.4117647
      },
      {
        "performance": 7.372181,
        "time": 1.4901961
      },
      {
        "performance": 7.616087,
        "time": 1.6470588
      },
      {
        "performance": 7.7940044,
        "time": 1.7254902
      },
      {
        "performance": 7.770218,
        "time": 1.8039216
      },
      {
        "performance": 7.720016,
        "time": 1.882353
      },
      {
        "performance": 8.103249,
        "time": 2.0392158
      },
      {
        "performance": 8.708935,
        "time": 2.1960785
      },
      {
        "performance": 9.021303,
        "time": 2.27451
      },
      {
        "performance": 8.994681,
        "time": 2.509804
      },
      {
        "performance": 8.724567,
        "time": 2.5882354
      },
      {
        "performance": 8.610225,
        "time": 2.6666667
      },
      {
        "performance": 8.428547,
        "time": 2.745098
      },
      {
        "performance": 8.433678,
        "time": 2.9019608
      },
      {
        "performance": 8.653499,
        "time": 2.9803922
      },
      {
        "performance": 8.676735,
        "time": 3.0588236
      },
      {
        "performance": 8.388403,
        "time": 3.137255
      },
      {
        "performance": 8.742479,
        "time": 3.2941177
      },
      {
        "performance": 9.297515,
        "time": 3.4509804
      },
      {
        "performance": 9.180746,
        "time": 3.5294118
      },
      {
        "performance": 8.740569,
        "time": 3.764706
      },
      {
        "performance": 8.022071,
        "time": 3.8431373
      },
      {
        "performance": 7.5047383,
        "time": 3.9215686
      },
      {
        "performance": 6.763006,
        "time": 4.0
      },
      {
        "performance": 6.3255863,
        "time": 4.1568627
      },
      {
        "performance": 6.0309634,
        "time": 4.2352943
      },
      {
        "performance": 5.620913,
        "time": 4.3137255
      },
      {
        "performance": 4.981235,
        "time": 4.392157
      },
      {
        "performance": 4.8696494,
        "time": 4.54902
      },
      {
        "performance": 5.009646,
        "time": 4.7058825
      },
      {
        "performance": 4.6324077,
        "time": 4.7843137
      },
      {
        "performance": 4.35104,
        "time": 5.019608
      },
      {
        "performance": 4.082617,
        "time": 5.1764708
      },
      {
        "performance": 3.7183049,
        "time": 5.4117646
      },
      {
        "performance": 3.8899868,
        "time": 5.72549
      },
      {
        "performance": 3.664826,
        "time": 5.8039217
      },
      {
        "performance": 3.4004312,
        "time": 5.882353
      },
      {
        "performance": 2.8264832,
        "time": 6.0392156
      },
      {
        "performance": 2.4314687,
        "time": 6.117647
      },
      {
        "performance": 1.9194933,
        "time": 6.1960783
      },
      {
        "performance": 1.566817,
        "time": 6.352941
      },
      {
        "performance": 1.318347,
        "time": 6.5882354
      },
      {
        "performance": 0.8716807,
        "time": 6.6666665
      },
      {
        "performance": 0.54790205,
        "time": 6.8235292
      },
      {
        "performance": 0.46270776,
        "time": 9.411765
      },
      {
        "performance": 0.0,
        "time": 9.490196
      }
    ],
    "acc": [
      {
        "performance": 7.0947285,
        "time": 1.254902
      },
      {
        "performance": 7.28328,
        "time": 1.3333334
      },
      {
        "performance": 7.397754,
        "time": 1.4117647
      },
      {
        "performance": 7.372181,
        "time": 1.4901961
      },
      {
        "performance": 7.616087,
        "time": 1.6470588
      },
      {
        "performance": 7.7940044,
        "time": 1.7254902
      },
      {
        "performance": 7.770218,
        "time": 1.8039216
      },
      {
        "performance": 7.720016,
        "time": 1.882353
      },
      {
        "performance": 8.103249,
        "time": 2.0392158
      },
      {
        "performance": 8.708935,
        "time": 2.1960785
      },
      {
        "performance": 9.021303,
        "time": 2.27451
      },
      {
        "performance": 8.994681,
        "time": 2.509804
      },
      {
        "performance": 8.724567,
        "time": 2.5882354
      },
      {
        "performance": 8.610225,
        "time": 2.6666667
      },
      {
        "performance": 8.428547,
        "time": 2.745098
      },
      {
        "performance": 8.433678,
        "time": 2.9019608
      },
      {
        "performance": 8.653499,
        "time": 2.9803922
      },
      {
        "performance": 8.676735,
        "time": 3.0588236
      },
      {
        "performance": 8.388403,
        "time": 3.137255
      },
      {
        "performance": 8.742479,
        "time": 3.2941177
      },
      {
        "performance": 9.297515,
        "time": 3.4509804
      },
      {
        "performance": 9.180746,
        "time": 3.5294118
      },
      {
        "performance": 8.740569,
        "time": 3.764706
      },
      {
        "performance": 8.022071,
        "time": 3.8431373
      },
      {
        "performance": 7.5047383,
        "time": 3.9215686
      },
      {
        "performance": 6.763006,
        "time": 4.0
      },
      {
        "performance": 6.3255863,
        "time": 4.1568627
      },
      {
        "performance": 6.0309634,
        "time": 4.2352943
      },
      {
        "performance": 5.620913,
        "time": 4.3137255
      },
      {
        "performance": 4.981235,
        "time": 4.392157
      },
      {
        "performance": 4.8696494,
        "time": 4.54902
      },
      {
        "performance": 5.009646,
        "time": 4.7058825
      },
      {
        "performance": 4.6324077,
        "time": 4.7843137
      },
      {
        "performance": 4.35104,
        "time": 5.019608
      },
      {
        "performance": 4.082617,
        "time": 5.1764708
      },
      {
        "performance": 3.7183049,
        "time": 5.4117646
      },
      {
        "performance": 3.8899868,
        "time": 5.72549
      },
      {
        "performance": 3.664826,
        "time": 5.8039217
      },
      {
        "performance": 3.4004312,
        "time": 5.882353
      },
      {
        "performance": 2.8264832,
        "time": 6.0392156
      },
      {
        "performance": 2.4314687,
        "time": 6.117647
      },
      {
        "performance": 1.9194933,
        "time": 6.1960783
      },
      {
        "performance": 1.566817,
        "time": 6.352941
      },
      {
        "performance": 1.318347,
        "time": 6.5882354
      },
      {
        "performance": 0.8716807,
        "time": 6.6666665
      },
      {
        "performance": 0.54790205,
        "time": 6.8235292
      },
      {
        "performance": 0.46270776,
        "time": 9.411765
      },
      {
        "performance": 0.0,
        "time": 9.490196
      }
    ]
  },
  "speed150": {
    "aim": [
      {
        "performance": 7.742431,
        "time": 1.0457517
      },
      {
        "performance": 7.9686356,
        "time": 1.1111112
      },
      {
        "performance": 8.113724,
        "time": 1.1764706
      },
      {
        "performance": 8.101815,
        "time": 1.2418301
      },
      {
        "performance": 8.390575,
        "time": 1.372549
      },
      {
        "performance": 8.598842,
        "time": 1.4379085
      },
      {
        "performance": 8.58402,
        "time": 1.503268
      },
      {
        "performance": 8.538517,
        "time": 1.5686275
      },
      {
        "performance": 8.973243,
        "time": 1.6993464
      },
      {
        "performance": 9.676021,
        "time": 1.8300654
      },
      {
        "performance": 10.063181,
        "time": 1.8954248
      },
      {
        "performance": 10.049941,
        "time": 2.0915034
      },
      {
        "performance": 9.75838,
        "time": 2.1568627
      },
      {
        "performance": 9.639158,
        "time": 2.2222223
      },
      {
        "performance": 9.442341,
        "time": 2.2875817
      },
      {
        "performance": 9.46169,
        "time": 2.4183006
      },
      {
        "performance": 9.714471,
        "time": 2.4836602
      },
      {
        "performance": 9.770028,
        "time": 2.5490196
      },
      {
        "performance": 9.451854,
        "time": 2.6143792
      },
      {
        "performance": 9.831542,
        "time": 2.745098
      },
      {
        "performance": 10.326446,
        "time": 2.875817
      },
      {
        "performance": 10.102709,
        "time": 2.9411764
      },
      {
        "performance": 9.627609,
        "time": 3.137255
      },
      {
        "performance": 8.840774,
        "time": 3.2026143
      },
      {
        "performance": 8.277846,
        "time": 3.267974
      },
      {
        "performance": 7.4708786,
        "time": 3.3333333
      },
      {
        "performance": 7.002807,
        "time": 3.4640522
      },
      {
        "performance": 6.6827593,
        "time": 3.5294118
      },
      {
        "performance": 6.239767,
        "time": 3.5947711
      },
      {
        "performance": 5.5429873,
        "time": 3.6601307
      },
      {
        "performance": 5.4272466,
        "time": 3.7908497
      },
      {
        "performance": 6.0072155,
        "time": 3.9215686
      },
      {
        "performance": 5.6049013,
        "time": 3.986928
      },
      {
        "performance": 5.31813,
        "time": 4.183007
      },
      {
        "performance": 4.99972,
        "time": 4.3137255
      },
      {
        "performance": 4.4759297,
        "time": 4.509804
      },
      {
        "performance": 4.2746897,
        "time": 4.7712417
      },
      {
        "performance": 4.0301495,
        "time": 4.8366013
      },
      {
        "performance": 3.74064,
        "time": 4.901961
      },
      {
        "performance": 3.1190484,
        "time": 5.0326796
      },
      {
        "performance": 2.6882486,
        "time": 5.098039
      },
      {
        "performance": 2.130151,
        "time": 5.1633987
      },
      {
        "performance": 1.7030997,
        "time": 5.2941175
      },
      {
        "performance": 1.4347854,
        "time": 5.490196
      },
      {
        "performance": 0.948187,
        "time": 5.5555553
      },
      {
        "performance": 0.59502685,
        "time": 5.6862745
      },
      {
        "performance": 0.50513977,
        "time": 7.8431373
      },
      {
        "performance": 0.0,
        "time": 7.908497
      }
    ],
    "tap": [
      {
        "performance": 7.742431,
        "time": 1.0457517
      },
      {
        "performance": 7.9686356,
        "time": 1.1111112
      },
      {
        "performance": 8.113724,
        "time": 1.1764706
      },
      {
        "performance": 8.101815,
        "time": 1.2418301
      },
      {
        "performance": 8.390575,
        "time": 1.372549
      },
      {
        "performance": 8.598842,
        "time": 1.4379085
      },
      {
        "performance": 8.58402,
        "time": 1.503268
      },
      {
        "performance": 8.538517,
        "time": 1.5686275
      },
      {
        "performance": 8.973243,
        "time": 1.6993464
      },
      {
        "performance": 9.676021,
        "time": 1.8300654
      },
      {
        "performance": 10.063181,
        "time": 1.8954248
      },
      {
        "performance": 10.049941,
        "time": 2.0915034
      },
      {
        "performance": 9.75838,
        "time": 2.1568627
      },
      {
        "performance": 9.639158,
        "time": 2.2222223
      },
      {
        "performance": 9.442341,
        "time": 2.2875817
      },
      {
        "performance": 9.46169,
        "time": 2.4183006
      },
      {
        "performance": 9.714471,
        "time": 2.4836602
      },
      {
        "performance": 9.770028,
        "time": 2.5490196
      },
      {
        "performance": 9.451854,
        "time": 2.6143792
      },
      {
        "performance": 9.831542,
        "time": 2.745098
      },
      {
        "performance": 10.326446,
        "time": 2.875817
      },
      {
        "performance": 10.102709,
        "time": 2.9411764
      },
      {
        "performance": 9.627609,
        "time": 3.137255
      },
      {
        "performance": 8.840774,
        "time": 3.2026143
      },
      {
        "performance": 8.277846,
        "time": 3.267974
      },
      {
        "performance": 7.4708786,
        "time": 3.3333333
      },
      {
        "performance": 7.002807,
        "time": 3.4640522
      },
      {
        "performance": 6.6827593,
        "time": 3.5294118
      },
      {
        "performance": 6.239767,
        "time": 3.5947711
      },
      {
        "performance": 5.5429873,
        "time": 3.6601307
      },
      {
        "performance": 5.4272466,
        "time": 3.7908497
      },
      {
        "performance": 6.0072155,
        "time": 3.9215686
      },
      {
        "performance": 5.6049013,
        "time": 3.986928
      },
      {
        "performance": 5.31813,
        "time": 4.183007
      },
      {
        "performance": 4.99972,
        "time": 4.3137255
      },
      {
        "performance": 4.4759297,
        "time": 4.509804
      },
      {
        "performance": 4.2746897,
        "time": 4.7712417
      },
      {
        "performance": 4.0301495,
        "time": 4.8366013
      },
      {
        "performance": 3.74064,
        "time": 4.901961
      },
      {
        "performance": 3.1190484,
        "time": 5.0326796
      },
      {
        "performance": 2.6882486,
        "time": 5.098039
      },
      {
        "performance": 2.130151,
        "time": 5.1633987
      },
      {
        "performance": 1.7030997,
        "time": 5.2941175
      },
      {
        "performance": 1.4347854,
        "time": 5.490196
      },
      {
        "performance": 0.948187,
        "time": 5.5555553
      },
      {
        "performance": 0.59502685,
        "time": 5.6862745
      },
      {
        "performance": 0.50513977,
        "time": 7.8431373
      },
      {
        "performance": 0.0,
        "time": 7.908497
      }
    ],
    "acc": [
      {
        "performance": 7.742431,
        "time": 1.0457517
      },
      {
        "performance": 7.9686356,
        "time": 1.1111112
      },
      {
        "performance": 8.113724,
        "time": 1.1764706
      },
      {
        "performance": 8.101815,
        "time": 1.2418301
      },
      {
        "performance": 8.390575,
        "time": 1.372549
      },
      {
        "performance": 8.598842,
        "time": 1.4379085
      },
      {
        "performance": 8.58402,
        "time": 1.503268
      },
      {
        "performance": 8.538517,
        "time": 1.5686275
      },
      {
        "performance": 8.973243,
        "time": 1.6993464
      },
      {
        "performance": 9.676021,
        "time": 1.8300654
      },
      {
        "performance": 10.063181,
        "time": 1.8954248
      },
      {
        "performance": 10.049941,
        "time": 2.0915034
      },
      {
        "performance": 9.75838,
        "time": 2.1568627
      },
      {
        "performance": 9.639158,
        "time": 2.2222223
      },
      {
        "performance": 9.442341,
        "time": 2.2875817
      },
      {
        "performance": 9.46169,
        "time": 2.4183006
      },
      {
        "performance": 9.714471,
        "time": 2.4836602
      },
      {
        "performance": 9.770028,
        "time": 2.5490196
      },
      {
        "performance": 9.451854,
        "time": 2.6143792
      },
      {
        "performance": 9.831542,
        "time": 2.745098
      },
      {
        "performance": 10.326446,
        "time": 2.875817
      },
      {
        "performance": 10.102709,
        "time": 2.9411764
      },
      {
        "performance": 9.627609,
        "time": 3.137255
      },
      {
        "performance": 8.840774,
        "time": 3.2026143
      },
      {
        "performance": 8.277846,
        "time": 3.267974
      },
      {
        "performance": 7.4708786,
        "time": 3.3333333
      },
      {
        "performance": 7.002807,
        "time": 3.4640522
      },
      {
        "performance": 6.6827593,
        "time": 3.5294118
      },
      {
        "performance": 6.239767,
        "time": 3.5947711
      },
      {
        "performance": 5.5429873,
        "time": 3.6601307
      },
      {
        "performance": 5.4272466,
        "time": 3.7908497
      },
      {
        "performance": 6.0072155,
        "time": 3.9215686
      },
      {
        "performance": 5.6049013,
        "time": 3.986928
      },
      {
        "performance": 5.31813,
        "time": 4.183007
      },
      {
        "performance": 4.99972,
        "time": 4.3137255
      },
      {
        "performance": 4.4759297,
        "time": 4.509804
      },
      {
        "performance": 4.2746897,
        "time": 4.7712417
      },
      {
        "performance": 4.0301495,
        "time": 4.8366013
      },
      {
        "performance": 3.74064,
        "time": 4.901961
      },
      {
        "performance": 3.1190484,
        "time": 5.0326796
      },
      {
        "performance": 2.6882486,
        "time": 5.098039
      },
      {
        "performance": 2.130151,
        "time": 5.1633987
      },
      {
        "performance": 1.7030997,
        "time": 5.2941175
      },
      {
        "performance": 1.4347854,
        "time": 5.490196
      },
      {
        "performance": 0.948187,
        "time": 5.5555553
      },
      {
        "performance": 0.59502685,
        "time": 5.6862745
      },
      {
        "performance": 0.50513977,
        "time": 7.8431373
      },
      {
        "performance": 0.0,
        "time": 7.908497
      }
    ]
  },
  "speed175": {
    "aim": [
      {
        "performance": 8.343861,
        "time": 0.89635855
      },
      {
        "performance": 8.608694,
        "time": 0.95238096
      },
      {
        "performance": 8.785075,
        "time": 1.0084034
      },
      {
        "performance": 8.788175,
        "time": 1.0644258
      },
      {
        "performance": 9.120324,
        "time": 1.1764706
      },
      {
        "performance": 9.358938,
        "time": 1.232493
      },
      {
        "performance": 9.354019,
        "time": 1.2885154
      },
      {
        "performance": 9.3141775,
        "time": 1.3445379
      },
      {
        "performance": 9.798689,
        "time": 1.4565827
      },
      {
        "performance": 10.59762,
        "time": 1.5686275
      },
      {
        "performance": 11.061505,
        "time": 1.6246499
      },
      {
        "performance": 11.061727,
        "time": 1.7927171
      },
      {
        "performance": 10.751009,
        "time": 1.8487395
      },
      {
        "performance": 10.628234,
        "time": 1.9047619
      },
      {
        "performance": 10.418119,
        "time": 1.9607843
      },
      {
        "performance": 10.45123,
        "time": 2.0728292
      },
      {
        "performance": 10.736365,
        "time": 2.1288517
      },
      {
        "performance": 10.821443,
        "time": 2.184874
      },
      {
        "performance": 10.368259,
        "time": 2.2408965
      },
      {
        "performance": 10.676477,
        "time": 2.3529413
      },
      {
        "performance": 11.205272,
        "time": 2.464986
      },
      {
        "performance": 10.967535,
        "time": 2.5210085
      },
      {
        "performance": 10.458981,
        "time": 2.6890757
      },
      {
        "performance": 9.678813,
        "time": 2.745098
      },
      {
        "performance": 9.397523,
        "time": 2.8011205
      },
      {
        "performance": 8.5356655,
        "time": 2.857143
      },
      {
        "performance": 8.045105,
        "time": 2.9691877
      },
      {
        "performance": 7.7150006,
        "time": 3.0252101
      },
      {
        "performance": 7.25178,
        "time": 3.0812325
      },
      {
        "performance": 6.5106363,
        "time": 3.137255
      },
      {
        "performance": 6.4028974,
        "time": 3.2492998
      },
      {
        "performance": 6.586374,
        "time": 3.3613446
      },
      {
        "performance": 6.1517816,
        "time": 3.417367
      },
      {
        "performance": 5.8527675,
        "time": 3.5854342
      },
      {
        "performance": 5.471447,
        "time": 3.697479
      },
      {
        "performance": 4.849446,
        "time": 3.8655462
      },
      {
        "performance": 4.6359544,
        "time": 4.089636
      },
      {
        "performance": 4.3740697,
        "time": 4.1456585
      },
      {
        "performance": 4.063404,
        "time": 4.2016807
      },
      {
        "performance": 3.394774,
        "time": 4.3137255
      },
      {
        "performance": 2.9317122,
        "time": 4.369748
      },
      {
        "performance": 2.330522,
        "time": 4.4257703
      },
      {
        "performance": 1.8289078,
        "time": 4.537815
      },
      {
        "performance": 1.5432334,
        "time": 4.7058825
      },
      {
        "performance": 1.0179403,
        "time": 4.7619047
      },
      {
        "performance": 0.6394546,
        "time": 4.8739495
      },
      {
        "performance": 0.543524,
        "time": 6.722689
      },
      {
        "performance": 0.0,
        "time": 6.7787113
      }
    ],
    "tap": [
      {
        "performance": 8.343861,
        "time": 0.89635855
      },
      {
        "performance": 8.608694,
        "time": 0.95238096
      },
      {
        "performance": 8.785075,
        "time": 1.0084034
      },
      {
        "performance": 8.788175,
        "time": 1.0644258
      },
      {
        "performance": 9.120324,
        "time": 1.1764706
      },
      {
        "performance": 9.358938,
        "time": 1.232493
      },
      {
        "performance": 9.354019,
        "time": 1.2885154
      },
      {
        "performance": 9.3141775,
        "time": 1.3445379
      },
      {
        "performance": 9.798689,
        "time": 1.4565827
      },
      {
        "performance": 10.59762,
        "time": 1.5686275
      },
      {
        "performance": 11.061505,
        "time": 1.6246499
      },
      {
        "performance": 11.061727,
        "time": 1.7927171
      },
      {
        "performance": 10.751009,
        "time": 1.8487395
      },
      {
        "performance": 10.628234,
        "time": 1.9047619
      },
      {
        "performance": 10.418119,
        "time": 1.9607843
      },
      {
        "performance": 10.45123,
        "time": 2.0728292
      },
      {
        "performance": 10.736365,
        "time": 2.1288517
      },
      {
        "performance": 10.821443,
        "time": 2.184874
      },
      {
        "performance": 10.368259,
        "time": 2.2408965
      },
      {
        "performance": 10.676477,
        "time": 2.3529413
      },
      {
        "performance": 11.205272,
        "time": 2.464986
      },
      {
        "performance": 10.967535,
        "time": 2.5210085
      },
      {
        "performance": 10.458981,
        "time": 2.6890757
      },
      {
        "performance": 9.678813,
        "time": 2.745098
      },
      {
        "performance": 9.397523,
        "time": 2.8011205
      },
      {
        "performance": 8.5356655,
        "time": 2.857143
      },
      {
        "performance": 8.045105,
        "time": 2.9691877
      },
      {
        "performance": 7.7150006,
        "time": 3.0252101
      },
      {
        "performance": 7.25178,
        "time": 3.0812325
      },
      {
        "performance": 6.5106363,
        "time": 3.137255
      },
      {
        "performance": 6.4028974,
        "time": 3.2492998
      },
      {
        "performance": 6.586374,
        "time": 3.3613446
      },
      {
        "performance": 6.1517816,
        "time": 3.417367
      },
      {
        "performance": 5.8527675,
        "time": 3.5854342
      },
      {
        "performance": 5.471447,
        "time": 3.697479
      },
      {
        "performance": 4.849446,
        "time": 3.8655462
      },
      {
        "performance": 4.6359544,
        "time": 4.089636
      },
      {
        "performance": 4.3740697,
        "time": 4.1456585
      },
      {
        "performance": 4.063404,
        "time": 4.2016807
      },
      {
        "performance": 3.394774,
        "time": 4.3137255
      },
      {
        "performance": 2.9317122,
        "time": 4.369748
      },
      {
        "performance": 2.330522,
        "time": 4.4257703
      },
      {
        "performance": 1.8289078,
        "time": 4.537815
      },
      {
        "performance": 1.5432334,
        "time": 4.7058825
      },
      {
        "performance": 1.0179403,
        "time": 4.7619047
      },
      {
        "performance": 0.6394546,
        "time": 4.8739495
      },
      {
        "performance": 0.543524,
        "time": 6.722689
      },
      {
        "performance": 0.0,
        "time": 6.7787113
      }
    ],
    "acc": [
      {
        "performance": 8.343861,
        "time": 0.89635855
      },
      {
        "performance": 8.608694,
        "time": 0.95238096
      },
      {
        "performance": 8.785075,
        "time": 1.0084034
      },
      {
        "performance": 8.788175,
        "time": 1.0644258
      },
      {
        "performance": 9.120324,
        "time": 1.1764706
      },
      {
        "performance": 9.358938,
        "time": 1.232493
      },
      {
        "performance": 9.354019,
        "time": 1.2885154
      },
      {
        "performance": 9.3141775,
        "time": 1.3445379
      },
      {
        "performance": 9.798689,
        "time": 1.4565827
      },
      {
        "performance": 10.59762,
        "time": 1.5686275
      },
      {
        "performance": 11.061505,
        "time": 1.6246499
      },
      {
        "performance": 11.061727,
        "time": 1.7927171
      },
      {
        "performance": 10.751009,
        "time": 1.8487395
      },
      {
        "performance": 10.628234,
        "time": 1.9047619
      },
      {
        "performance": 10.418119,
        "time": 1.9607843
      },
      {
        "performance": 10.45123,
        "time": 2.0728292
      },
      {
        "performance": 10.736365,
        "time": 2.1288517
      },
      {
        "performance": 10.821443,
        "time": 2.184874
      },
      {
        "performance": 10.368259,
        "time": 2.2408965
      },
      {
        "performance": 10.676477,
        "time": 2.3529413
      },
      {
        "performance": 11.205272,
        "time": 2.464986
      },
      {
        "performance": 10.967535,
        "time": 2.5210085
      },
      {
        "performance": 10.458981,
        "time": 2.6890757
      },
      {
        "performance": 9.678813,
        "time": 2.745098
      },
      {
        "performance": 9.397523,
        "time": 2.8011205
      },
      {
        "performance": 8.5356655,
        "time": 2.857143
      },
      {
        "performance": 8.045105,
        "time": 2.9691877
      },
      {
        "performance": 7.7150006,
        "time": 3.0252101
      },
      {
        "performance": 7.25178,
        "time": 3.0812325
      },
      {
        "performance": 6.5106363,
        "time": 3.137255
      },
      {
        "performance": 6.4028974,
        "time": 3.2492998
      },
      {
        "performance": 6.586374,
        "time": 3.3613446
      },
      {
        "performance": 6.1517816,
        "time": 3.417367
      },
      {
        "performance": 5.8527675,
        "time": 3.5854342
      },
      {
        "performance": 5.471447,
        "time": 3.697479
      },
      {
        "performance": 4.849446,
        "time": 3.8655462
      },
      {
        "performance": 4.6359544,
        "time": 4.089636
      },
      {
        "performance": 4.3740697,
        "time": 4.1456585
      },
      {
        "performance": 4.063404,
        "time": 4.2016807
      },
      {
        "performance": 3.394774,
        "time": 4.3137255
      },
      {
        "performance": 2.9317122,
        "time": 4.369748
      },
      {
        "performance": 2.330522,
        "time": 4.4257703
      },
      {
        "performance": 1.8289078,
        "time": 4.537815
      },
      {
        "performance": 1.5432334,
        "time": 4.7058825
      },
      {
        "performance": 1.0179403,
        "time": 4.7619047
      },
      {
        "performance": 0.6394546,
        "time": 4.8739495
      },
      {
        "performance": 0.543524,
        "time": 6.722689
      },
      {
        "performance": 0.0,
        "time": 6.7787113
      }
    ]
  },
  "speed200": {
    "aim": [
      {
        "performance": 8.907834,
        "time": 0.78431374
      },
      {
        "performance": 9.2119465,
        "time": 0.8333333
      },
      {
        "performance": 9.420095,
        "time": 0.88235295
      },
      {
        "performance": 9.439202,
        "time": 0.9313725
      },
      {
        "performance": 9.813623,
        "time": 1.0294118
      },
      {
        "performance": 10.082472,
        "time": 1.0784314
      },
      {
        "performance": 10.088133,
        "time": 1.127451
      },
      {
        "performance": 10.054656,
        "time": 1.1764706
      },
      {
        "performance": 10.5875025,
        "time": 1.2745098
      },
      {
        "performance": 11.481842,
        "time": 1.372549
      },
      {
        "performance": 12.024082,
        "time": 1.4215686
      },
      {
        "performance": 12.03792,
        "time": 1.5686275
      },
      {
        "performance": 11.709863,
        "time": 1.617647
      },
      {
        "performance": 11.58457,
        "time": 1.6666666
      },
      {
        "performance": 11.362597,
        "time": 1.7156863
      },
      {
        "performance": 11.409226,
        "time": 1.8137255
      },
      {
        "performance": 11.697212,
        "time": 1.862745
      },
      {
        "performance": 11.666498,
        "time": 1.9117647
      },
      {
        "performance": 11.13955,
        "time": 1.9607843
      },
      {
        "performance": 11.476362,
        "time": 2.0588236
      },
      {
        "performance": 12.037803,
        "time": 2.1568627
      },
      {
        "performance": 11.848429,
        "time": 2.2058823
      },
      {
        "performance": 11.645751,
        "time": 2.3529413
      },
      {
        "performance": 10.759703,
        "time": 2.4019608
      },
      {
        "performance": 10.120014,
        "time": 2.4509804
      },
      {
        "performance": 9.202026,
        "time": 2.5
      },
      {
        "performance": 8.683086,
        "time": 2.5980392
      },
      {
        "performance": 8.333219,
        "time": 2.6470587
      },
      {
        "performance": 7.8446264,
        "time": 2.6960785
      },
      {
        "performance": 7.0538626,
        "time": 2.745098
      },
      {
        "performance": 6.9448204,
        "time": 2.8431373
      },
      {
        "performance": 7.143431,
        "time": 2.9411764
      },
      {
        "performance": 6.683559,
        "time": 2.990196
      },
      {
        "performance": 6.3692784,
        "time": 3.137255
      },
      {
        "performance": 5.922467,
        "time": 3.235294
      },
      {
        "performance": 5.203862,
        "time": 3.3823528
      },
      {
        "performance": 4.976137,
        "time": 3.5784314
      },
      {
        "performance": 4.69748,
        "time": 3.627451
      },
      {
        "performance": 4.36527,
        "time": 3.6764705
      },
      {
        "performance": 3.6558928,
        "time": 3.77451
      },
      {
        "performance": 3.1637793,
        "time": 3.8235295
      },
      {
        "performance": 2.5237312,
        "time": 3.872549
      },
      {
        "performance": 1.9472469,
        "time": 3.9705882
      },
      {
        "performance": 1.6453873,
        "time": 4.117647
      },
      {
        "performance": 1.0840483,
        "time": 4.1666665
      },
      {
        "performance": 0.68011725,
        "time": 4.2647057
      },
      {
        "performance": 0.5808058,
        "time": 5.882353
      },
      {
        "performance": 0.0,
        "time": 5.9313726
      }
    ],
    "tap": [
      {
        "performance": 8.907834,
        "time": 0.78431374
      },
      {
        "performance": 9.2119465,
        "time": 0.8333333
      },
      {
        "performance": 9.420095,
        "time": 0.88235295
      },
      {
        "performance": 9.439202,
        "time": 0.9313725
      },
      {
        "performance": 9.813623,
        "time": 1.0294118
      },
      {
        "performance": 10.082472,
        "time": 1.0784314
      },
      {
        "performance": 10.088133,
        "time": 1.127451
      },
      {
        "performance": 10.054656,
        "time": 1.1764706
      },
      {
        "performance": 10.5875025,
        "time": 1.2745098
      },
      {
        "performance": 11.481842,
        "time": 1.372549
      },
      {
        "performance": 12.024082,
        "time": 1.4215686
      },
      {
        "performance": 12.03792,
        "time": 1.5686275
      },
      {
        "performance": 11.709863,
        "time": 1.617647
      },
      {
        "performance": 11.58457,
        "time": 1.6666666
      },
      {
        "performance": 11.362597,
        "time": 1.7156863
      },
      {
        "performance": 11.409226,
        "time": 1.8137255
      },
      {
        "performance": 11.697212,
        "time": 1.862745
      },
      {
        "performance": 11.666498,
        "time": 1.9117647
      },
      {
        "performance": 11.13955,
        "time": 1.9607843
      },
      {
        "performance": 11.476362,
        "time": 2.0588236
      },
      {
        "performance": 12.037803,
        "time": 2.1568627
      },
      {
        "performance": 11.848429,
        "time": 2.2058823
      },
      {
        "performance": 11.645751,
        "time": 2.3529413
      },
      {
        "performance": 10.759703,
        "time": 2.4019608
      },
      {
        "performance": 10.120014,
        "time": 2.4509804
      },
      {
        "performance": 9.202026,
        "time": 2.5
      },
      {
        "performance": 8.683086,
        "time": 2.5980392
      },
      {
        "performance": 8.333219,
        "time": 2.6470587
      },
      {
        "performance": 7.8446264,
        "time": 2.6960785
      },
      {
        "performance": 7.0538626,
        "time": 2.745098
      },
      {
        "performance": 6.9448204,
        "time": 2.8431373
      },
      {
        "performance": 7.143431,
        "time": 2.9411764
      },
      {
        "performance": 6.683559,
        "time": 2.990196
      },
      {
        "performance": 6.3692784,
        "time": 3.137255
      },
      {
        "performance": 5.922467,
        "time": 3.235294
      },
      {
        "performance": 5.203862,
        "time": 3.3823528
      },
      {
        "performance": 4.976137,
        "time": 3.5784314
      },
      {
        "performance": 4.69748,
        "time": 3.627451
      },
      {
        "performance": 4.36527,
        "time": 3.6764705
      },
      {
        "performance": 3.6558928,
        "time": 3.77451
      },
      {
        "performance": 3.1637793,
        "time": 3.8235295
      },
      {
        "performance": 2.5237312,
        "time": 3.872549
      },
      {
        "performance": 1.9472469,
        "time": 3.9705882
      },
      {
        "performance": 1.6453873,
        "time": 4.117647
      },
      {
        "performance": 1.0840483,
        "time": 4.1666665
      },
      {
        "performance": 0.68011725,
        "time": 4.2647057
      },
      {
        "performance": 0.5808058,
        "time": 5.882353
      },
      {
        "performance": 0.0,
        "time": 5.9313726
      }
    ],
    "acc": [
      {
        "performance": 8.907834,
        "time": 0.78431374
      },
      {
        "performance": 9.2119465,
        "time": 0.8333333
      },
      {
        "performance": 9.420095,
        "time": 0.88235295
      },
      {
        "performance": 9.439202,
        "time": 0.9313725
      },
      {
        "performance": 9.813623,
        "time": 1.0294118
      },
      {
        "performance": 10.082472,
        "time": 1.0784314
      },
      {
        "performance": 10.088133,
        "time": 1.127451
      },
      {
        "performance": 10.054656,
        "time": 1.1764706
      },
      {
        "performance": 10.5875025,
        "time": 1.2745098
      },
      {
        "performance": 11.481842,
        "time": 1.372549
      },
      {
        "performance": 12.024082,
        "time": 1.4215686
      },
      {
        "performance": 12.03792,
        "time": 1.5686275
      },
      {
        "performance": 11.709863,
        "time": 1.617647
      },
      {
        "performance": 11.58457,
        "time": 1.6666666
      },
      {
        "performance": 11.362597,
        "time": 1.7156863
      },
      {
        "performance": 11.409226,
        "time": 1.8137255
      },
      {
        "performance": 11.697212,
        "time": 1.862745
      },
      {
        "performance": 11.666498,
        "time": 1.9117647
      },
      {
        "performance": 11.13955,
        "time": 1.9607843
      },
      {
        "performance": 11.476362,
        "time": 2.0588236
      },
      {
        "performance": 12.037803,
        "time": 2.1568627
      },
      {
        "performance": 11.848429,
        "time": 2.2058823
      },
      {
        "performance": 11.645751,
        "time": 2.3529413
      },
      {
        "performance": 10.759703,
        "time": 2.4019608
      },
      {
        "performance": 10.120014,
        "time": 2.4509804
      },
      {
        "performance": 9.202026,
        "time": 2.5
      },
      {
        "performance": 8.683086,
        "time": 2.5980392
      },
      {
        "performance": 8.333219,
        "time": 2.6470587
      },
      {
        "performance": 7.8446264,
        "time": 2.6960785
      },
      {
        "performance": 7.0538626,
        "time": 2.745098
      },
      {
        "performance": 6.9448204,
        "time": 2.8431373
      },
      {
        "performance": 7.143431,
        "time": 2.9411764
      },
      {
        "performance": 6.683559,
        "time": 2.990196
      },
      {
        "performance": 6.3692784,
        "time": 3.137255
      },
      {
        "performance": 5.922467,
        "time": 3.235294
      },
      {
        "performance": 5.203862,
        "time": 3.3823528
      },
      {
        "performance": 4.976137,
        "time": 3.5784314
      },
      {
        "performance": 4.69748,
        "time": 3.627451
      },
      {
        "performance": 4.36527,
        "time": 3.6764705
      },
      {
        "performance": 3.6558928,
        "time": 3.77451
      },
      {
        "performance": 3.1637793,
        "time": 3.8235295
      },
      {
        "performance": 2.5237312,
        "time": 3.872549
      },
      {
        "performance": 1.9472469,
        "time": 3.9705882
      },
      {
        "performance": 1.6453873,
        "time": 4.117647
      },
      {
        "performance": 1.0840483,
        "time": 4.1666665
      },
      {
        "performance": 0.68011725,
        "time": 4.2647057
      },
      {
        "performance": 0.5808058,
        "time": 5.882353
      },
      {
        "performance": 0.0,
        "time": 5.9313726
      }
    ]
  }
}
