{
  "speed050": {
    "aim": [
      {
        "performance": 0.0,
        "time": 3.6923077
      },
      {
        "performance": 0.0,
        "time": 4.1538463
      },
      {
        "performance": 0.0,
        "time": 4.6153846
      },
      {
        "performance": 0.0,
        "time": 4.8461537
      },
      {
        "performance": 0.0,
        "time": 5.5384617
      },
      {
        "performance": 0.0,
        "time": 6.4615383
      },
      {
        "performance": 0.18333036,
        "time": 7.3846154
      },
      {
        "performance": 0.1888073,
        "time": 7.8461537
      },
      {
        "performance": 0.39243257,
        "time": 8.307693
      },
      {
        "performance": 0.40470722,
        "time": 8.538462
      },
      {
        "performance": 0.57559013,
        "time": 9.230769
      },
      {
        "performance": 0.7005066,
        "time": 10.153846
      },
      {
        "performance": 0.7422569,
        "time": 11.076923
      },
      {
        "performance": 0.766859,
        "time": 11.538462
      },
      {
        "performance": 0.92211115,
        "time": 11.769231
      },
      {
        "performance": 0.7048492,
        "time": 12.0
      },
      {
        "performance": 0.7279092,
        "time": 12.461538
      },
      {
        "performance": 0.8590931,
        "time": 12.692307
      },
      {
        "performance": 0.6823246,
        "time": 12.923077
      },
      {
        "performance": 0.70447165,
        "time": 13.384615
      },
      {
        "performance": 0.8359666,
        "time": 13.615385
      },
      {
        "performance": 0.7166808,
        "time": 13.846154
      },
      {
        "performance": 0.74003714,
        "time": 14.076923
      },
      {
        "performance": 0.76429933,
        "time": 14.307693
      },
      {
        "performance": 1.0545716,
        "time": 14.538462
      },
      {
        "performance": 0.72418445,
        "time": 14.769231
      },
      {
        "performance": 0.7475851,
        "time": 15.115385
      },
      {
        "performance": 0.9425897,
        "time": 15.346154
      },
      {
        "performance": 0.76988006,
        "time": 15.692307
      },
      {
        "performance": 0.7947981,
        "time": 16.038462
      },
      {
        "performance": 0.9577602,
        "time": 16.26923
      },
      {
        "performance": 0.82096183,
        "time": 16.615385
      },
      {
        "performance": 0.84764296,
        "time": 16.961538
      },
      {
        "performance": 0.99895996,
        "time": 17.192308
      },
      {
        "performance": 0.8615176,
        "time": 17.538462
      },
      {
        "performance": 0.8895315,
        "time": 17.76923
      },
      {
        "performance": 0.91862744,
        "time": 18.0
      },
      {
        "performance": 1.2088643,
        "time": 18.23077
      },
      {
        "performance": 0.8332338,
        "time": 18.461538
      },
      {
        "performance": 0.8600075,
        "time": 18.692308
      },
      {
        "performance": 0.88779277,
        "time": 18.923077
      },
      {
        "performance": 0.91663855,
        "time": 19.153847
      },
      {
        "performance": 0.6700757,
        "time": 19.384615
      },
      {
        "performance": 0.6911495,
        "time": 19.615385
      },
      {
        "performance": 0.7129861,
        "time": 19.846153
      },
      {
        "performance": 0.73562074,
        "time": 20.076923
      },
      {
        "performance": 0.53090036,
        "time": 20.307692
      },
      {
        "performance": 0.54731643,
        "time": 20.538462
      },
      {
        "performance": 0.56430554,
        "time": 20.76923
      },
      {
        "performance": 0.5818927,
        "time": 21.0
      },
      {
        "performance": 0.37453607,
        "time": 21.23077
      }
    ],
    "tap": [
      {
        "performance": 1.0961981,
        "time": 3.6923077
      },
      {
        "performance": 1.0943273,
        "time": 4.1538463
      },
      {
        "performance": 1.3719969,
        "time": 4.6153846
      },
      {
        "performance": 1.0925999,
        "time": 4.8461537
      },
      {
        "performance": 1.0980815,
        "time": 5.5384617
      },
      {
        "performance": 1.1082853,
        "time": 6.4615383
      },
      {
        "performance": 1.1410539,
        "time": 7.3846154
      },
      {
        "performance": 1.4323502,
        "time": 7.8461537
      },
      {
        "performance": 1.5449946,
        "time": 8.307693
      },
      {
        "performance": 1.4475716,
        "time": 8.538462
      },
      {
        "performance": 1.9107028,
        "time": 9.230769
      },
      {
        "performance": 2.8429248,
        "time": 10.153846
      },
      {
        "performance": 3.6949522,
        "time": 11.076923
      },
      {
        "performance": 3.8355,
        "time": 11.538462
      },
      {
        "performance": 3.7872193,
        "time": 11.769231
      },
      {
        "performance": 3.6603782,
        "time": 12.0
      },
      {
        "performance": 3.8731148,
        "time": 12.461538
      },
      {
        "performance": 3.8218882,
        "time": 12.692307
      },
      {
        "performance": 3.6923087,
        "time": 12.923077
      },
      {
        "performance": 3.9059298,
        "time": 13.384615
      },
      {
        "performance": 3.8525076,
        "time": 13.615385
      },
      {
        "performance": 3.8559296,
        "time": 13.846154
      },
      {
        "performance": 3.933308,
        "time": 14.076923
      },
      {
        "performance": 3.937829,
        "time": 14.307693
      },
      {
        "performance": 3.9432008,
        "time": 14.538462
      },
      {
        "performance": 3.8702867,
        "time": 14.769231
      },
      {
        "performance": 4.213777,
        "time": 15.115385
      },
      {
        "performance": 4.2193856,
        "time": 15.346154
      },
      {
        "performance": 4.2314253,
        "time": 15.692307
      },
      {
        "performance": 4.571023,
        "time": 16.038462
      },
      {
        "performance": 4.582551,
        "time": 16.26923
      },
      {
        "performance": 4.5894423,
        "time": 16.615385
      },
      {
        "performance": 4.9260178,
        "time": 16.961538
      },
      {
        "performance": 4.710085,
        "time": 17.192308
      },
      {
        "performance": 4.5743475,
        "time": 17.538462
      },
      {
        "performance": 4.343009,
        "time": 17.76923
      },
      {
        "performance": 4.1035647,
        "time": 18.0
      },
      {
        "performance": 3.9573119,
        "time": 18.23077
      },
      {
        "performance": 3.698559,
        "time": 18.461538
      },
      {
        "performance": 3.4309158,
        "time": 18.692308
      },
      {
        "performance": 3.1539674,
        "time": 18.923077
      },
      {
        "performance": 3.4620566,
        "time": 19.153847
      },
      {
        "performance": 5.1840444,
        "time": 19.384615
      },
      {
        "performance": 4.532473,
        "time": 19.615385
      },
      {
        "performance": 3.866178,
        "time": 19.846153
      },
      {
        "performance": 3.184605,
        "time": 20.076923
      },
      {
        "performance": 2.4836144,
        "time": 20.307692
      },
      {
        "performance": 1.7674924,
        "time": 20.538462
      },
      {
        "performance": 1.035733,
        "time": 20.76923
      },
      {
        "performance": 0.2878029,
        "time": 21.0
      },
      {
        "performance": 0.27632135,
        "time": 21.23077
      }
    ],
    "acc": [
      {
        "performance": 0.0,
        "time": 3.6923077
      },
      {
        "performance": 0.0,
        "time": 4.1538463
      },
      {
        "performance": 0.0,
        "time": 4.6153846
      },
      {
        "performance": 0.0,
        "time": 4.8461537
      },
      {
        "performance": 0.0,
        "time": 5.5384617
      },
      {
        "performance": 0.0,
        "time": 6.4615383
      },
      {
        "performance": 0.35790882,
        "time": 7.3846154
      },
      {
        "performance": 0.36817685,
        "time": 7.8461537
      },
      {
        "performance": 0.552703,
        "time": 8.307693
      },
      {
        "performance": 0.57938105,
        "time": 8.538462
      },
      {
        "performance": 0.7367103,
        "time": 9.230769
      },
      {
        "performance": 0.8696585,
        "time": 10.153846
      },
      {
        "performance": 0.6614102,
        "time": 11.076923
      },
      {
        "performance": 0.6803854,
        "time": 11.538462
      },
      {
        "performance": 0.84261996,
        "time": 11.769231
      },
      {
        "performance": 0.642036,
        "time": 12.0
      },
      {
        "performance": 0.6735235,
        "time": 12.461538
      },
      {
        "performance": 0.8093725,
        "time": 12.692307
      },
      {
        "performance": 0.646656,
        "time": 12.923077
      },
      {
        "performance": 0.67837,
        "time": 13.384615
      },
      {
        "performance": 0.8364057,
        "time": 13.615385
      },
      {
        "performance": 0.7148072,
        "time": 13.846154
      },
      {
        "performance": 0.7493097,
        "time": 14.076923
      },
      {
        "performance": 0.77080667,
        "time": 14.307693
      },
      {
        "performance": 1.0571027,
        "time": 14.538462
      },
      {
        "performance": 0.76722926,
        "time": 14.769231
      },
      {
        "performance": 0.7892403,
        "time": 15.115385
      },
      {
        "performance": 0.97686726,
        "time": 15.346154
      },
      {
        "performance": 0.7774552,
        "time": 15.692307
      },
      {
        "performance": 0.7997596,
        "time": 16.038462
      },
      {
        "performance": 0.9511155,
        "time": 16.26923
      },
      {
        "performance": 0.7922971,
        "time": 16.615385
      },
      {
        "performance": 0.8150273,
        "time": 16.961538
      },
      {
        "performance": 0.93909013,
        "time": 17.192308
      },
      {
        "performance": 0.76820123,
        "time": 17.538462
      },
      {
        "performance": 0.79024017,
        "time": 17.76923
      },
      {
        "performance": 0.81291133,
        "time": 18.0
      },
      {
        "performance": 0.9400071,
        "time": 18.23077
      },
      {
        "performance": 0.596868,
        "time": 18.461538
      },
      {
        "performance": 0.6139915,
        "time": 18.692308
      },
      {
        "performance": 0.63160634,
        "time": 18.923077
      },
      {
        "performance": 0.7845052,
        "time": 19.153847
      },
      {
        "performance": 0.8606792,
        "time": 19.384615
      },
      {
        "performance": 0.88084346,
        "time": 19.615385
      },
      {
        "performance": 0.90143234,
        "time": 19.846153
      },
      {
        "performance": 0.92245233,
        "time": 20.076923
      },
      {
        "performance": 0.55252725,
        "time": 20.307692
      },
      {
        "performance": 0.5653481,
        "time": 20.538462
      },
      {
        "performance": 0.5784329,
        "time": 20.76923
      },
      {
        "performance": 0.59178567,
        "time": 21.0
      },
      {
        "performance": 0.2616004,
        "time": 21.23077
      }
    ]
  },
  "speed075": {
    "aim": [
      {
        "performance": 0.0,
        "time": 2.4615386
      },
      {
        "performance": 0.0,
        "time": 2.7692308
      },
      {
        "performance": 0.0,
        "time": 3.0769231
      },
      {
        "performance": 0.0,
        "time": 3.2307692
      },
      {
        "performance": 0.21005104,
        "time": 3.6923077
      },
      {
        "performance": 0.4284898,
        "time": 4.3076925
      },
      {
        "performance": 0.6062125,
        "time": 4.923077
      },
      {
        "performance": 0.7361124,
        "time": 5.230769
      },
      {
        "performance": 0.7604761,
        "time": 5.5384617
      },
      {
        "performance": 0.7858107,
        "time": 5.6923075
      },
      {
        "performance": 1.0786009,
        "time": 6.1538463
      },
      {
        "performance": 1.2586187,
        "time": 6.769231
      },
      {
        "performance": 1.1400594,
        "time": 7.3846154
      },
      {
        "performance": 1.2847595,
        "time": 7.6923075
      },
      {
        "performance": 1.3303694,
        "time": 7.8461537
      },
      {
        "performance": 1.080084,
        "time": 8.0
      },
      {
        "performance": 1.362146,
        "time": 8.307693
      },
      {
        "performance": 1.4101844,
        "time": 8.461538
      },
      {
        "performance": 1.2125721,
        "time": 8.615385
      },
      {
        "performance": 1.4130883,
        "time": 8.923077
      },
      {
        "performance": 1.4626765,
        "time": 9.076923
      },
      {
        "performance": 1.3360361,
        "time": 9.230769
      },
      {
        "performance": 1.3822898,
        "time": 9.384615
      },
      {
        "performance": 1.5634882,
        "time": 9.538462
      },
      {
        "performance": 1.6191092,
        "time": 9.692307
      },
      {
        "performance": 1.2297164,
        "time": 9.846154
      },
      {
        "performance": 1.2712018,
        "time": 10.076923
      },
      {
        "performance": 1.4527125,
        "time": 10.230769
      },
      {
        "performance": 1.2481712,
        "time": 10.461538
      },
      {
        "performance": 1.289923,
        "time": 10.692307
      },
      {
        "performance": 1.53507,
        "time": 10.846154
      },
      {
        "performance": 1.3769281,
        "time": 11.076923
      },
      {
        "performance": 1.4233572,
        "time": 11.307693
      },
      {
        "performance": 1.4716942,
        "time": 11.461538
      },
      {
        "performance": 1.3078504,
        "time": 11.692307
      },
      {
        "performance": 1.351576,
        "time": 11.846154
      },
      {
        "performance": 1.3970737,
        "time": 12.0
      },
      {
        "performance": 1.444436,
        "time": 12.153846
      },
      {
        "performance": 0.9793559,
        "time": 12.307693
      },
      {
        "performance": 1.0107595,
        "time": 12.461538
      },
      {
        "performance": 1.0433447,
        "time": 12.615385
      },
      {
        "performance": 1.0771688,
        "time": 12.769231
      },
      {
        "performance": 0.77118915,
        "time": 12.923077
      },
      {
        "performance": 0.7953312,
        "time": 13.076923
      },
      {
        "performance": 0.8203388,
        "time": 13.230769
      },
      {
        "performance": 0.84625125,
        "time": 13.384615
      },
      {
        "performance": 0.5918101,
        "time": 13.538462
      },
      {
        "performance": 0.6099747,
        "time": 13.692307
      },
      {
        "performance": 0.6287629,
        "time": 13.846154
      },
      {
        "performance": 0.6482012,
        "time": 14.0
      },
      {
        "performance": 0.3657563,
        "time": 14.153846
      }
    ],
    "tap": [
      {
        "performance": 2.138902,
        "time": 2.4615386
      },
      {
        "performance": 2.0684025,
        "time": 2.7692308
      },
      {
        "performance": 1.8779919,
        "time": 3.0769231
      },
      {
        "performance": 1.5509251,
        "time": 3.2307692
      },
      {
        "performance": 1.72573,
        "time": 3.6923077
      },
      {
        "performance": 2.4234958,
        "time": 4.3076925
      },
      {
        "performance": 3.138726,
        "time": 4.923077
      },
      {
        "performance": 3.5461674,
        "time": 5.230769
      },
      {
        "performance": 3.9552672,
        "time": 5.5384617
      },
      {
        "performance": 3.9889503,
        "time": 5.6923075
      },
      {
        "performance": 4.404449,
        "time": 6.1538463
      },
      {
        "performance": 5.0594873,
        "time": 6.769231
      },
      {
        "performance": 5.6359797,
        "time": 7.3846154
      },
      {
        "performance": 5.988411,
        "time": 7.6923075
      },
      {
        "performance": 6.011532,
        "time": 7.8461537
      },
      {
        "performance": 5.9564795,
        "time": 8.0
      },
      {
        "performance": 6.4326067,
        "time": 8.307693
      },
      {
        "performance": 6.4596357,
        "time": 8.461538
      },
      {
        "performance": 6.4054656,
        "time": 8.615385
      },
      {
        "performance": 6.8934875,
        "time": 8.923077
      },
      {
        "performance": 6.9252453,
        "time": 9.076923
      },
      {
        "performance": 6.951499,
        "time": 9.230769
      },
      {
        "performance": 7.0569124,
        "time": 9.384615
      },
      {
        "performance": 7.0870614,
        "time": 9.538462
      },
      {
        "performance": 7.121769,
        "time": 9.692307
      },
      {
        "performance": 7.0623536,
        "time": 9.846154
      },
      {
        "performance": 7.1923785,
        "time": 10.076923
      },
      {
        "performance": 6.975725,
        "time": 10.230769
      },
      {
        "performance": 6.777858,
        "time": 10.461538
      },
      {
        "performance": 6.654274,
        "time": 10.692307
      },
      {
        "performance": 6.5164537,
        "time": 10.846154
      },
      {
        "performance": 6.3073797,
        "time": 11.076923
      },
      {
        "performance": 6.168451,
        "time": 11.307693
      },
      {
        "performance": 5.913348,
        "time": 11.461538
      },
      {
        "performance": 5.7545023,
        "time": 11.692307
      },
      {
        "performance": 5.4777417,
        "time": 11.846154
      },
      {
        "performance": 5.190813,
        "time": 12.0
      },
      {
        "performance": 4.8931775,
        "time": 12.153846
      },
      {
        "performance": 4.5729766,
        "time": 12.307693
      },
      {
        "performance": 4.241814,
        "time": 12.461538
      },
      {
        "performance": 3.8991818,
        "time": 12.615385
      },
      {
        "performance": 3.9740102,
        "time": 12.769231
      },
      {
        "performance": 5.2401853,
        "time": 12.923077
      },
      {
        "performance": 4.5847282,
        "time": 13.076923
      },
      {
        "performance": 3.9135,
        "time": 13.230769
      },
      {
        "performance": 3.2258892,
        "time": 13.384615
      },
      {
        "performance": 2.5174754,
        "time": 13.538462
      },
      {
        "performance": 1.7927773,
        "time": 13.692307
      },
      {
        "performance": 1.0512346,
        "time": 13.846154
      },
      {
        "performance": 0.29225674,
        "time": 14.0
      },
      {
        "performance": 0.2841372,
        "time": 14.153846
      }
    ],
    "acc": [
      {
        "performance": 0.0,
        "time": 2.4615386
      },
      {
        "performance": 0.0,
        "time": 2.7692308
      },
      {
        "performance": 0.0,
        "time": 3.0769231
      },
      {
        "performance": 0.0,
        "time": 3.2307692
      },
      {
        "performance": 0.29253498,
        "time": 3.6923077
      },
      {
        "performance": 0.4391503,
        "time": 4.3076925
      },
      {
        "performance": 0.56473875,
        "time": 4.923077
      },
      {
        "performance": 0.6666526,
        "time": 5.230769
      },
      {
        "performance": 0.6857782,
        "time": 5.5384617
      },
      {
        "performance": 0.7132824,
        "time": 5.6923075
      },
      {
        "performance": 0.9072739,
        "time": 6.1538463
      },
      {
        "performance": 1.0492569,
        "time": 6.769231
      },
      {
        "performance": 0.78501576,
        "time": 7.3846154
      },
      {
        "performance": 0.9069788,
        "time": 7.6923075
      },
      {
        "performance": 0.9329991,
        "time": 7.8461537
      },
      {
        "performance": 0.76558477,
        "time": 8.0
      },
      {
        "performance": 0.97733814,
        "time": 8.307693
      },
      {
        "performance": 1.0053769,
        "time": 8.461538
      },
      {
        "performance": 0.87285966,
        "time": 8.615385
      },
      {
        "performance": 1.0231855,
        "time": 8.923077
      },
      {
        "performance": 1.0525396,
        "time": 9.076923
      },
      {
        "performance": 0.95537996,
        "time": 9.230769
      },
      {
        "performance": 0.9936969,
        "time": 9.384615
      },
      {
        "performance": 1.1172205,
        "time": 9.538462
      },
      {
        "performance": 1.1492724,
        "time": 9.692307
      },
      {
        "performance": 0.90694237,
        "time": 9.846154
      },
      {
        "performance": 0.93296164,
        "time": 10.076923
      },
      {
        "performance": 1.0757582,
        "time": 10.230769
      },
      {
        "performance": 0.9107913,
        "time": 10.461538
      },
      {
        "performance": 0.93692094,
        "time": 10.692307
      },
      {
        "performance": 1.0404375,
        "time": 10.846154
      },
      {
        "performance": 0.90996474,
        "time": 11.076923
      },
      {
        "performance": 0.9360707,
        "time": 11.307693
      },
      {
        "performance": 0.9629256,
        "time": 11.461538
      },
      {
        "performance": 0.8145086,
        "time": 11.692307
      },
      {
        "performance": 0.8378761,
        "time": 11.846154
      },
      {
        "performance": 0.86191386,
        "time": 12.0
      },
      {
        "performance": 0.8866413,
        "time": 12.153846
      },
      {
        "performance": 0.58273304,
        "time": 12.307693
      },
      {
        "performance": 0.59945107,
        "time": 12.461538
      },
      {
        "performance": 0.6166487,
        "time": 12.615385
      },
      {
        "performance": 0.71119905,
        "time": 12.769231
      },
      {
        "performance": 0.721793,
        "time": 12.923077
      },
      {
        "performance": 0.7393152,
        "time": 13.076923
      },
      {
        "performance": 0.7572345,
        "time": 13.230769
      },
      {
        "performance": 0.7755587,
        "time": 13.384615
      },
      {
        "performance": 0.50850374,
        "time": 13.538462
      },
      {
        "performance": 0.5207684,
        "time": 13.692307
      },
      {
        "performance": 0.5333075,
        "time": 13.846154
      },
      {
        "performance": 0.54612625,
        "time": 14.0
      },
      {
        "performance": 0.19401799,
        "time": 14.153846
      }
    ]
  },
  "speed100": {
    "aim": [
      {
        "performance": 0.21552475,
        "time": 1.8461539
      },
      {
        "performance": 0.43586406,
        "time": 2.0769231
      },
      {
        "performance": 0.44940218,
        "time": 2.3076923
      },
      {
        "performance": 0.46341756,
        "time": 2.4230769
      },
      {
        "performance": 0.6540954,
        "time": 2.7692308
      },
      {
        "performance": 0.79351676,
        "time": 3.2307692
      },
      {
        "performance": 1.0872117,
        "time": 3.6923077
      },
      {
        "performance": 1.2685294,
        "time": 3.9230769
      },
      {
        "performance": 1.3133643,
        "time": 4.1538463
      },
      {
        "performance": 1.3601726,
        "time": 4.269231
      },
      {
        "performance": 1.5290059,
        "time": 4.6153846
      },
      {
        "performance": 1.6994349,
        "time": 5.076923
      },
      {
        "performance": 1.4397148,
        "time": 5.5384617
      },
      {
        "performance": 1.7474996,
        "time": 5.769231
      },
      {
        "performance": 1.8118521,
        "time": 5.8846154
      },
      {
        "performance": 1.5327147,
        "time": 6.0
      },
      {
        "performance": 1.5870013,
        "time": 6.230769
      },
      {
        "performance": 1.8164258,
        "time": 6.3461537
      },
      {
        "performance": 1.594075,
        "time": 6.4615383
      },
      {
        "performance": 1.6502048,
        "time": 6.6923075
      },
      {
        "performance": 1.7087928,
        "time": 6.8076925
      },
      {
        "performance": 1.7067114,
        "time": 6.923077
      },
      {
        "performance": 1.7670996,
        "time": 7.0384617
      },
      {
        "performance": 1.8301499,
        "time": 7.1538463
      },
      {
        "performance": 1.8960103,
        "time": 7.269231
      },
      {
        "performance": 1.6067321,
        "time": 7.3846154
      },
      {
        "performance": 1.8535037,
        "time": 7.5576925
      },
      {
        "performance": 1.9185026,
        "time": 7.673077
      },
      {
        "performance": 1.6852921,
        "time": 7.8461537
      },
      {
        "performance": 1.7429861,
        "time": 8.019231
      },
      {
        "performance": 1.8031069,
        "time": 8.134615
      },
      {
        "performance": 1.6160573,
        "time": 8.307693
      },
      {
        "performance": 1.6708671,
        "time": 8.480769
      },
      {
        "performance": 1.7279496,
        "time": 8.596154
      },
      {
        "performance": 1.5339375,
        "time": 8.769231
      },
      {
        "performance": 1.5854716,
        "time": 8.884615
      },
      {
        "performance": 1.639111,
        "time": 9.0
      },
      {
        "performance": 1.6949662,
        "time": 9.115385
      },
      {
        "performance": 1.1489601,
        "time": 9.230769
      },
      {
        "performance": 1.1859,
        "time": 9.346154
      },
      {
        "performance": 1.2242371,
        "time": 9.461538
      },
      {
        "performance": 1.2640392,
        "time": 9.576923
      },
      {
        "performance": 0.9046175,
        "time": 9.692307
      },
      {
        "performance": 0.93296856,
        "time": 9.807693
      },
      {
        "performance": 0.96233857,
        "time": 9.923077
      },
      {
        "performance": 0.9927739,
        "time": 10.038462
      },
      {
        "performance": 0.6937902,
        "time": 10.153846
      },
      {
        "performance": 0.7150779,
        "time": 10.269231
      },
      {
        "performance": 0.73709583,
        "time": 10.384615
      },
      {
        "performance": 0.7598752,
        "time": 10.5
      },
      {
        "performance": 0.39872155,
        "time": 10.615385
      }
    ],
    "tap": [
      {
        "performance": 2.9369235,
        "time": 1.8461539
      },
      {
        "performance": 3.367116,
        "time": 2.0769231
      },
      {
        "performance": 3.3773205,
        "time": 2.3076923
      },
      {
        "performance": 3.3557088,
        "time": 2.4230769
      },
      {
        "performance": 3.7468123,
        "time": 2.7692308
      },
      {
        "performance": 4.868579,
        "time": 3.2307692
      },
      {
        "performance": 5.9162903,
        "time": 3.6923077
      },
      {
        "performance": 6.023075,
        "time": 3.9230769
      },
      {
        "performance": 6.3980746,
        "time": 4.1538463
      },
      {
        "performance": 6.1849165,
        "time": 4.269231
      },
      {
        "performance": 6.841714,
        "time": 4.6153846
      },
      {
        "performance": 7.596405,
        "time": 5.076923
      },
      {
        "performance": 7.862468,
        "time": 5.5384617
      },
      {
        "performance": 8.078953,
        "time": 5.769231
      },
      {
        "performance": 8.123772,
        "time": 5.8846154
      },
      {
        "performance": 8.096289,
        "time": 6.0
      },
      {
        "performance": 8.376495,
        "time": 6.230769
      },
      {
        "performance": 8.417487,
        "time": 6.3461537
      },
      {
        "performance": 8.391174,
        "time": 6.4615383
      },
      {
        "performance": 8.680805,
        "time": 6.6923075
      },
      {
        "performance": 8.725361,
        "time": 6.8076925
      },
      {
        "performance": 8.7627325,
        "time": 6.923077
      },
      {
        "performance": 8.867328,
        "time": 7.0384617
      },
      {
        "performance": 8.913088,
        "time": 7.1538463
      },
      {
        "performance": 8.961552,
        "time": 7.269231
      },
      {
        "performance": 8.658067,
        "time": 7.3846154
      },
      {
        "performance": 8.6469555,
        "time": 7.5576925
      },
      {
        "performance": 8.402042,
        "time": 7.673077
      },
      {
        "performance": 8.209559,
        "time": 7.8461537
      },
      {
        "performance": 8.071762,
        "time": 8.019231
      },
      {
        "performance": 7.796498,
        "time": 8.134615
      },
      {
        "performance": 7.580782,
        "time": 8.307693
      },
      {
        "performance": 7.415265,
        "time": 8.480769
      },
      {
        "performance": 7.110074,
        "time": 8.596154
      },
      {
        "performance": 6.920171,
        "time": 8.769231
      },
      {
        "performance": 6.5884447,
        "time": 8.884615
      },
      {
        "performance": 6.244426,
        "time": 9.0
      },
      {
        "performance": 5.8874545,
        "time": 9.115385
      },
      {
        "performance": 5.5026493,
        "time": 9.230769
      },
      {
        "performance": 5.1046133,
        "time": 9.346154
      },
      {
        "performance": 4.692728,
        "time": 9.461538
      },
      {
        "performance": 4.5934296,
        "time": 9.576923
      },
      {
        "performance": 5.4948626,
        "time": 9.692307
      },
      {
        "performance": 4.811548,
        "time": 9.807693
      },
      {
        "performance": 4.1105947,
        "time": 9.923077
      },
      {
        "performance": 3.3912876,
        "time": 10.038462
      },
      {
        "performance": 2.6487286,
        "time": 10.153846
      },
      {
        "performance": 1.8878226,
        "time": 10.269231
      },
      {
        "performance": 1.107905,
        "time": 10.384615
      },
      {
        "performance": 0.3082752,
        "time": 10.5
      },
      {
        "performance": 0.30322817,
        "time": 10.615385
      }
    ],
    "acc": [
      {
        "performance": 0.24607627,
        "time": 1.8461539
      },
      {
        "performance": 0.369407,
        "time": 2.0769231
      },
      {
        "performance": 0.3800049,
        "time": 2.3076923
      },
      {
        "performance": 0.39372572,
        "time": 2.4230769
      },
      {
        "performance": 0.5006408,
        "time": 2.7692308
      },
      {
        "performance": 0.59098744,
        "time": 3.2307692
      },
      {
        "performance": 0.7570619,
        "time": 3.6923077
      },
      {
        "performance": 0.87553763,
        "time": 3.9230769
      },
      {
        "performance": 0.9006559,
        "time": 4.1538463
      },
      {
        "performance": 0.9329886,
        "time": 4.269231
      },
      {
        "performance": 1.03931,
        "time": 4.6153846
      },
      {
        "performance": 1.1585307,
        "time": 5.076923
      },
      {
        "performance": 0.832983,
        "time": 5.5384617
      },
      {
        "performance": 1.0138404,
        "time": 5.769231
      },
      {
        "performance": 1.0429265,
        "time": 5.8846154
      },
      {
        "performance": 0.89126647,
        "time": 6.0
      },
      {
        "performance": 0.9233534,
        "time": 6.230769
      },
      {
        "performance": 1.0525979,
        "time": 6.3461537
      },
      {
        "performance": 0.9330762,
        "time": 6.4615383
      },
      {
        "performance": 0.9666683,
        "time": 6.6923075
      },
      {
        "performance": 0.99440104,
        "time": 6.8076925
      },
      {
        "performance": 0.98650676,
        "time": 6.923077
      },
      {
        "performance": 1.0219214,
        "time": 7.0384617
      },
      {
        "performance": 1.0512393,
        "time": 7.1538463
      },
      {
        "performance": 1.0813982,
        "time": 7.269231
      },
      {
        "performance": 0.99496937,
        "time": 7.3846154
      },
      {
        "performance": 1.0889065,
        "time": 7.5576925
      },
      {
        "performance": 1.1201463,
        "time": 7.673077
      },
      {
        "performance": 0.9701408,
        "time": 7.8461537
      },
      {
        "performance": 0.9979732,
        "time": 8.019231
      },
      {
        "performance": 1.026604,
        "time": 8.134615
      },
      {
        "performance": 0.9074358,
        "time": 8.307693
      },
      {
        "performance": 0.9334692,
        "time": 8.480769
      },
      {
        "performance": 0.9602495,
        "time": 8.596154
      },
      {
        "performance": 0.82004875,
        "time": 8.769231
      },
      {
        "performance": 0.8435751,
        "time": 8.884615
      },
      {
        "performance": 0.86777645,
        "time": 9.0
      },
      {
        "performance": 0.8926721,
        "time": 9.115385
      },
      {
        "performance": 0.6044517,
        "time": 9.230769
      },
      {
        "performance": 0.62179285,
        "time": 9.346154
      },
      {
        "performance": 0.63963145,
        "time": 9.461538
      },
      {
        "performance": 0.7084284,
        "time": 9.576923
      },
      {
        "performance": 0.6784164,
        "time": 9.692307
      },
      {
        "performance": 0.6954366,
        "time": 9.807693
      },
      {
        "performance": 0.7128661,
        "time": 9.923077
      },
      {
        "performance": 0.73071414,
        "time": 10.038462
      },
      {
        "performance": 0.5109757,
        "time": 10.153846
      },
      {
        "performance": 0.52374214,
        "time": 10.269231
      },
      {
        "performance": 0.53681344,
        "time": 10.384615
      },
      {
        "performance": 0.55019635,
        "time": 10.5
      },
      {
        "performance": 0.16390805,
        "time": 10.615385
      }
    ]
  },
  "speed125": {
    "aim": [
      {
        "performance": 0.64166355,
        "time": 1.4769231
      },
      {
        "performance": 0.7776982,
        "time": 1.6615385
      },
      {
        "performance": 0.80310905,
        "time": 1.8461539
      },
      {
        "performance": 1.0991981,
        "time": 1.9384615
      },
      {
        "performance": 1.1367604,
        "time": 2.2153847
      },
      {
        "performance": 1.3265846,
        "time": 2.5846155
      },
      {
        "performance": 1.4904635,
        "time": 2.9538462
      },
      {
        "performance": 1.5440813,
        "time": 3.1384616
      },
      {
        "performance": 1.6001141,
        "time": 3.323077
      },
      {
        "performance": 1.778511,
        "time": 3.4153845
      },
      {
        "performance": 1.8449165,
        "time": 3.6923077
      },
      {
        "performance": 1.9144468,
        "time": 4.0615387
      },
      {
        "performance": 1.6201338,
        "time": 4.4307694
      },
      {
        "performance": 1.9670453,
        "time": 4.6153846
      },
      {
        "performance": 2.040513,
        "time": 4.707692
      },
      {
        "performance": 1.7273692,
        "time": 4.8
      },
      {
        "performance": 1.7892792,
        "time": 4.9846153
      },
      {
        "performance": 2.048576,
        "time": 5.076923
      },
      {
        "performance": 1.7989502,
        "time": 5.169231
      },
      {
        "performance": 1.8630015,
        "time": 5.353846
      },
      {
        "performance": 1.9298997,
        "time": 5.4461536
      },
      {
        "performance": 1.9283932,
        "time": 5.5384617
      },
      {
        "performance": 1.9973743,
        "time": 5.6307693
      },
      {
        "performance": 2.06944,
        "time": 5.723077
      },
      {
        "performance": 2.1447632,
        "time": 5.8153844
      },
      {
        "performance": 1.8330275,
        "time": 5.9076924
      },
      {
        "performance": 2.1051629,
        "time": 6.046154
      },
      {
        "performance": 2.1796842,
        "time": 6.1384616
      },
      {
        "performance": 1.9153732,
        "time": 6.276923
      },
      {
        "performance": 1.9814668,
        "time": 6.415385
      },
      {
        "performance": 2.0503738,
        "time": 6.5076923
      },
      {
        "performance": 1.8382268,
        "time": 6.646154
      },
      {
        "performance": 1.901015,
        "time": 6.7846155
      },
      {
        "performance": 1.9664356,
        "time": 6.876923
      },
      {
        "performance": 1.7461404,
        "time": 7.0153847
      },
      {
        "performance": 1.805171,
        "time": 7.1076922
      },
      {
        "performance": 1.8666372,
        "time": 7.2
      },
      {
        "performance": 1.930668,
        "time": 7.292308
      },
      {
        "performance": 1.3124322,
        "time": 7.3846154
      },
      {
        "performance": 1.3547978,
        "time": 7.476923
      },
      {
        "performance": 1.398778,
        "time": 7.5692306
      },
      {
        "performance": 1.4444517,
        "time": 7.6615386
      },
      {
        "performance": 1.0373507,
        "time": 7.753846
      },
      {
        "performance": 1.0699464,
        "time": 7.8461537
      },
      {
        "performance": 1.1037202,
        "time": 7.9384613
      },
      {
        "performance": 1.1387258,
        "time": 8.030769
      },
      {
        "performance": 0.8000104,
        "time": 8.123077
      },
      {
        "performance": 0.82459015,
        "time": 8.2153845
      },
      {
        "performance": 0.85001564,
        "time": 8.307693
      },
      {
        "performance": 0.87632316,
        "time": 8.4
      },
      {
        "performance": 0.43575525,
        "time": 8.492308
      }
    ],
    "tap": [
      {
        "performance": 5.369671,
        "time": 1.4769231
      },
      {
        "performance": 5.80307,
        "time": 1.6615385
      },
      {
        "performance": 6.238853,
        "time": 1.8461539
      },
      {
        "performance": 6.230297,
        "time": 1.9384615
      },
      {
        "performance": 6.688483,
        "time": 2.2153847
      },
      {
        "performance": 7.3981357,
        "time": 2.5846155
      },
      {
        "performance": 7.6879573,
        "time": 2.9538462
      },
      {
        "performance": 7.8285093,
        "time": 3.1384616
      },
      {
        "performance": 8.04134,
        "time": 3.323077
      },
      {
        "performance": 8.028531,
        "time": 3.4153845
      },
      {
        "performance": 8.340409,
        "time": 3.6923077
      },
      {
        "performance": 8.714892,
        "time": 4.0615387
      },
      {
        "performance": 9.04438,
        "time": 4.4307694
      },
      {
        "performance": 9.297713,
        "time": 4.6153846
      },
      {
        "performance": 9.354255,
        "time": 4.707692
      },
      {
        "performance": 9.347886,
        "time": 4.8
      },
      {
        "performance": 9.653331,
        "time": 4.9846153
      },
      {
        "performance": 9.704859,
        "time": 5.076923
      },
      {
        "performance": 9.700473,
        "time": 5.169231
      },
      {
        "performance": 10.016246,
        "time": 5.353846
      },
      {
        "performance": 10.071794,
        "time": 5.4461536
      },
      {
        "performance": 10.118583,
        "time": 5.5384617
      },
      {
        "performance": 10.220474,
        "time": 5.6307693
      },
      {
        "performance": 10.277394,
        "time": 5.723077
      },
      {
        "performance": 10.33761,
        "time": 5.8153844
      },
      {
        "performance": 10.012815,
        "time": 5.9076924
      },
      {
        "performance": 10.0031,
        "time": 6.046154
      },
      {
        "performance": 9.723007,
        "time": 6.1384616
      },
      {
        "performance": 9.524566,
        "time": 6.276923
      },
      {
        "performance": 9.367237,
        "time": 6.415385
      },
      {
        "performance": 9.050367,
        "time": 6.5076923
      },
      {
        "performance": 8.822693,
        "time": 6.646154
      },
      {
        "performance": 8.632135,
        "time": 6.7846155
      },
      {
        "performance": 8.278953,
        "time": 6.876923
      },
      {
        "performance": 8.059456,
        "time": 7.0153847
      },
      {
        "performance": 7.67475,
        "time": 7.1076922
      },
      {
        "performance": 7.2756276,
        "time": 7.2
      },
      {
        "performance": 6.8613048,
        "time": 7.292308
      },
      {
        "performance": 6.4136467,
        "time": 7.3846154
      },
      {
        "performance": 5.950495,
        "time": 7.476923
      },
      {
        "performance": 5.471115,
        "time": 7.5692306
      },
      {
        "performance": 5.233905,
        "time": 7.6615386
      },
      {
        "performance": 5.838114,
        "time": 7.753846
      },
      {
        "performance": 5.1159797,
        "time": 7.8461537
      },
      {
        "performance": 4.374045,
        "time": 7.9384613
      },
      {
        "performance": 3.6114786,
        "time": 8.030769
      },
      {
        "performance": 2.822788,
        "time": 8.123077
      },
      {
        "performance": 2.0133884,
        "time": 8.2153845
      },
      {
        "performance": 1.1824992,
        "time": 8.307693
      },
      {
        "performance": 0.3292959,
        "time": 8.4
      },
      {
        "performance": 0.32700858,
        "time": 8.492308
      }
    ],
    "acc": [
      {
        "performance": 0.43335068,
        "time": 1.4769231
      },
      {
        "performance": 0.511554,
        "time": 1.6615385
      },
      {
        "performance": 0.52623,
        "time": 1.8461539
      },
      {
        "performance": 0.6725937,
        "time": 1.9384615
      },
      {
        "performance": 0.6918897,
        "time": 2.2153847
      },
      {
        "performance": 0.80016637,
        "time": 2.5846155
      },
      {
        "performance": 0.8956314,
        "time": 2.9538462
      },
      {
        "performance": 0.92132616,
        "time": 3.1384616
      },
      {
        "performance": 0.9477581,
        "time": 3.323077
      },
      {
        "performance": 1.0615009,
        "time": 3.4153845
      },
      {
        "performance": 1.0919544,
        "time": 3.6923077
      },
      {
        "performance": 1.1232814,
        "time": 4.0615387
      },
      {
        "performance": 0.80945,
        "time": 4.4307694
      },
      {
        "performance": 0.98519796,
        "time": 4.6153846
      },
      {
        "performance": 1.0134623,
        "time": 4.707692
      },
      {
        "performance": 0.86807555,
        "time": 4.8
      },
      {
        "performance": 0.8972673,
        "time": 4.9846153
      },
      {
        "performance": 1.0228604,
        "time": 5.076923
      },
      {
        "performance": 0.9087974,
        "time": 5.169231
      },
      {
        "performance": 0.9393585,
        "time": 5.353846
      },
      {
        "performance": 0.9663077,
        "time": 5.4461536
      },
      {
        "performance": 0.95863646,
        "time": 5.5384617
      },
      {
        "performance": 0.9908285,
        "time": 5.6307693
      },
      {
        "performance": 1.0192543,
        "time": 5.723077
      },
      {
        "performance": 1.0484958,
        "time": 5.8153844
      },
      {
        "performance": 1.0004152,
        "time": 5.9076924
      },
      {
        "performance": 1.0926613,
        "time": 6.046154
      },
      {
        "performance": 1.1240087,
        "time": 6.1384616
      },
      {
        "performance": 0.9812499,
        "time": 6.276923
      },
      {
        "performance": 1.0094011,
        "time": 6.415385
      },
      {
        "performance": 1.0383598,
        "time": 6.5076923
      },
      {
        "performance": 0.9252835,
        "time": 6.646154
      },
      {
        "performance": 0.95182896,
        "time": 6.7846155
      },
      {
        "performance": 0.97913593,
        "time": 6.876923
      },
      {
        "performance": 0.8434577,
        "time": 7.0153847
      },
      {
        "performance": 0.86765563,
        "time": 7.1076922
      },
      {
        "performance": 0.89254785,
        "time": 7.2
      },
      {
        "performance": 0.9181541,
        "time": 7.292308
      },
      {
        "performance": 0.6381119,
        "time": 7.3846154
      },
      {
        "performance": 0.6564187,
        "time": 7.476923
      },
      {
        "performance": 0.6752507,
        "time": 7.5692306
      },
      {
        "performance": 0.73081183,
        "time": 7.6615386
      },
      {
        "performance": 0.673921,
        "time": 7.753846
      },
      {
        "performance": 0.69129276,
        "time": 7.8461537
      },
      {
        "performance": 0.70910084,
        "time": 7.9384613
      },
      {
        "performance": 0.72735584,
        "time": 8.030769
      },
      {
        "performance": 0.5337781,
        "time": 8.123077
      },
      {
        "performance": 0.5475013,
        "time": 8.2153845
      },
      {
        "performance": 0.56156796,
        "time": 8.307693
      },
      {
        "performance": 0.575986,
        "time": 8.4
      },
      {
        "performance": 0.1479107,
        "time": 8.492308
      }
    ]
  },
  "speed150": {
    "aim": [
      {
        "performance": 1.086513,
        "time": 1.2307693
      },
      {
        "performance": 1.1232789,
        "time": 1.3846154
      },
      {
        "performance": 1.1615639,
        "time": 1.5384616
      },
      {
        "performance": 1.355619,
        "time": 1.6153846
      },
      {
        "performance": 1.4032884,
        "time": 1.8461539
      },
      {
        "performance": 1.4530418,
        "time": 2.1538463
      },
      {
        "performance": 1.6335033,
        "time": 2.4615386
      },
      {
        "performance": 1.6931341,
        "time": 2.6153846
      },
      {
        "performance": 1.7554992,
        "time": 2.7692308
      },
      {
        "performance": 1.9524635,
        "time": 2.8461537
      },
      {
        "performance": 2.026537,
        "time": 3.0769231
      },
      {
        "performance": 2.1041563,
        "time": 3.3846154
      },
      {
        "performance": 1.7797824,
        "time": 3.6923077
      },
      {
        "performance": 2.1616907,
        "time": 3.8461537
      },
      {
        "performance": 2.2436137,
        "time": 3.9230769
      },
      {
        "performance": 1.9005091,
        "time": 4.0
      },
      {
        "performance": 1.9694598,
        "time": 4.1538463
      },
      {
        "performance": 2.255707,
        "time": 4.230769
      },
      {
        "performance": 1.9819697,
        "time": 4.3076925
      },
      {
        "performance": 2.053344,
        "time": 4.4615383
      },
      {
        "performance": 2.1279373,
        "time": 4.5384617
      },
      {
        "performance": 2.1271913,
        "time": 4.6153846
      },
      {
        "performance": 2.204134,
        "time": 4.6923075
      },
      {
        "performance": 2.2845657,
        "time": 4.769231
      },
      {
        "performance": 2.368684,
        "time": 4.8461537
      },
      {
        "performance": 2.0402293,
        "time": 4.923077
      },
      {
        "performance": 2.3368063,
        "time": 5.0384617
      },
      {
        "performance": 2.420331,
        "time": 5.1153846
      },
      {
        "performance": 2.1283853,
        "time": 5.230769
      },
      {
        "performance": 2.2024376,
        "time": 5.3461537
      },
      {
        "performance": 2.2796793,
        "time": 5.423077
      },
      {
        "performance": 2.0452313,
        "time": 5.5384617
      },
      {
        "performance": 2.1156101,
        "time": 5.6538463
      },
      {
        "performance": 2.1889725,
        "time": 5.730769
      },
      {
        "performance": 1.9452423,
        "time": 5.8461537
      },
      {
        "performance": 2.0114403,
        "time": 5.923077
      },
      {
        "performance": 2.080398,
        "time": 6.0
      },
      {
        "performance": 2.1522627,
        "time": 6.076923
      },
      {
        "performance": 1.4684869,
        "time": 6.1538463
      },
      {
        "performance": 1.5161002,
        "time": 6.230769
      },
      {
        "performance": 1.5655427,
        "time": 6.3076925
      },
      {
        "performance": 1.6169053,
        "time": 6.3846154
      },
      {
        "performance": 1.1665341,
        "time": 6.4615383
      },
      {
        "performance": 1.2033018,
        "time": 6.5384617
      },
      {
        "performance": 1.2414067,
        "time": 6.6153846
      },
      {
        "performance": 1.2809105,
        "time": 6.6923075
      },
      {
        "performance": 0.90613174,
        "time": 6.769231
      },
      {
        "performance": 0.9340249,
        "time": 6.8461537
      },
      {
        "performance": 0.96288186,
        "time": 6.923077
      },
      {
        "performance": 0.9927443,
        "time": 7.0
      },
      {
        "performance": 0.47235912,
        "time": 7.076923
      }
    ],
    "tap": [
      {
        "performance": 7.5235133,
        "time": 1.2307693
      },
      {
        "performance": 7.6315193,
        "time": 1.3846154
      },
      {
        "performance": 7.814458,
        "time": 1.5384616
      },
      {
        "performance": 7.7400146,
        "time": 1.6153846
      },
      {
        "performance": 7.9528856,
        "time": 1.8461539
      },
      {
        "performance": 8.297659,
        "time": 2.1538463
      },
      {
        "performance": 8.615186,
        "time": 2.4615386
      },
      {
        "performance": 8.777351,
        "time": 2.6153846
      },
      {
        "performance": 9.02092,
        "time": 2.7692308
      },
      {
        "performance": 8.999656,
        "time": 2.8461537
      },
      {
        "performance": 9.354869,
        "time": 3.0769231
      },
      {
        "performance": 9.780866,
        "time": 3.3846154
      },
      {
        "performance": 10.168972,
        "time": 3.6923077
      },
      {
        "performance": 10.458879,
        "time": 3.8461537
      },
      {
        "performance": 10.528324,
        "time": 3.9230769
      },
      {
        "performance": 10.540005,
        "time": 4.0
      },
      {
        "performance": 10.874411,
        "time": 4.1538463
      },
      {
        "performance": 10.937478,
        "time": 4.230769
      },
      {
        "performance": 10.951761,
        "time": 4.3076925
      },
      {
        "performance": 11.297518,
        "time": 4.4615383
      },
      {
        "performance": 11.364992,
        "time": 4.5384617
      },
      {
        "performance": 11.422032,
        "time": 4.6153846
      },
      {
        "performance": 11.526315,
        "time": 4.6923075
      },
      {
        "performance": 11.595347,
        "time": 4.769231
      },
      {
        "performance": 11.668299,
        "time": 4.8461537
      },
      {
        "performance": 11.320137,
        "time": 4.923077
      },
      {
        "performance": 11.312766,
        "time": 5.0384617
      },
      {
        "performance": 10.999792,
        "time": 5.1153846
      },
      {
        "performance": 10.792882,
        "time": 5.230769
      },
      {
        "performance": 10.617612,
        "time": 5.3461537
      },
      {
        "performance": 10.261487,
        "time": 5.423077
      },
      {
        "performance": 10.019603,
        "time": 5.5384617
      },
      {
        "performance": 9.805672,
        "time": 5.6538463
      },
      {
        "performance": 9.406969,
        "time": 5.730769
      },
      {
        "performance": 9.159535,
        "time": 5.8461537
      },
      {
        "performance": 8.724293,
        "time": 5.923077
      },
      {
        "performance": 8.272545,
        "time": 6.0
      },
      {
        "performance": 7.803378,
        "time": 6.076923
      },
      {
        "performance": 7.295256,
        "time": 6.1538463
      },
      {
        "performance": 6.769417,
        "time": 6.230769
      },
      {
        "performance": 6.2250123,
        "time": 6.3076925
      },
      {
        "performance": 5.8730936,
        "time": 6.3846154
      },
      {
        "performance": 6.2334113,
        "time": 6.4615383
      },
      {
        "performance": 5.4658575,
        "time": 6.5384617
      },
      {
        "performance": 4.676214,
        "time": 6.6153846
      },
      {
        "performance": 3.8635278,
        "time": 6.6923075
      },
      {
        "performance": 3.0216374,
        "time": 6.769231
      },
      {
        "performance": 2.156558,
        "time": 6.8461537
      },
      {
        "performance": 1.2673882,
        "time": 6.923077
      },
      {
        "performance": 0.35317668,
        "time": 7.0
      },
      {
        "performance": 0.35333028,
        "time": 7.076923
      }
    ],
    "acc": [
      {
        "performance": 0.60662085,
        "time": 1.2307693
      },
      {
        "performance": 0.6240242,
        "time": 1.3846154
      },
      {
        "performance": 0.6419268,
        "time": 1.5384616
      },
      {
        "performance": 0.7449543,
        "time": 1.6153846
      },
      {
        "performance": 0.7663263,
        "time": 1.8461539
      },
      {
        "performance": 0.7883114,
        "time": 2.1538463
      },
      {
        "performance": 0.8811645,
        "time": 2.4615386
      },
      {
        "performance": 0.90644425,
        "time": 2.6153846
      },
      {
        "performance": 0.9324492,
        "time": 2.7692308
      },
      {
        "performance": 1.0429605,
        "time": 2.8461537
      },
      {
        "performance": 1.0728819,
        "time": 3.0769231
      },
      {
        "performance": 1.1036619,
        "time": 3.3846154
      },
      {
        "performance": 0.79637516,
        "time": 3.6923077
      },
      {
        "performance": 0.96928436,
        "time": 3.8461537
      },
      {
        "performance": 0.9970921,
        "time": 3.9230769
      },
      {
        "performance": 0.8552145,
        "time": 4.0
      },
      {
        "performance": 0.88277394,
        "time": 4.1538463
      },
      {
        "performance": 1.0063385,
        "time": 4.230769
      },
      {
        "performance": 0.89533293,
        "time": 4.3076925
      },
      {
        "performance": 0.9241853,
        "time": 4.4615383
      },
      {
        "performance": 0.9506992,
        "time": 4.5384617
      },
      {
        "performance": 0.9431519,
        "time": 4.6153846
      },
      {
        "performance": 0.9735224,
        "time": 4.6923075
      },
      {
        "performance": 1.0014518,
        "time": 4.769231
      },
      {
        "performance": 1.0301825,
        "time": 4.8461537
      },
      {
        "performance": 1.0172691,
        "time": 4.923077
      },
      {
        "performance": 1.1089722,
        "time": 5.0384617
      },
      {
        "performance": 1.1407875,
        "time": 5.1153846
      },
      {
        "performance": 1.0025259,
        "time": 5.230769
      },
      {
        "performance": 1.0312874,
        "time": 5.3461537
      },
      {
        "performance": 1.060874,
        "time": 5.423077
      },
      {
        "performance": 0.9516853,
        "time": 5.5384617
      },
      {
        "performance": 0.9789882,
        "time": 5.6538463
      },
      {
        "performance": 1.0070744,
        "time": 5.730769
      },
      {
        "performance": 0.87440103,
        "time": 5.8461537
      },
      {
        "performance": 0.8994868,
        "time": 5.923077
      },
      {
        "performance": 0.92529213,
        "time": 6.0
      },
      {
        "performance": 0.95183784,
        "time": 6.076923
      },
      {
        "performance": 0.6768842,
        "time": 6.1538463
      },
      {
        "performance": 0.6963033,
        "time": 6.230769
      },
      {
        "performance": 0.71627957,
        "time": 6.3076925
      },
      {
        "performance": 0.76441616,
        "time": 6.3846154
      },
      {
        "performance": 0.68897545,
        "time": 6.4615383
      },
      {
        "performance": 0.7071156,
        "time": 6.5384617
      },
      {
        "performance": 0.7257256,
        "time": 6.6153846
      },
      {
        "performance": 0.7448174,
        "time": 6.6923075
      },
      {
        "performance": 0.56748986,
        "time": 6.769231
      },
      {
        "performance": 0.58240634,
        "time": 6.8461537
      },
      {
        "performance": 0.5977083,
        "time": 6.923077
      },
      {
        "performance": 0.61340547,
        "time": 7.0
      },
      {
        "performance": 0.13844818,
        "time": 7.076923
      }
    ]
  },
  "speed175": {
    "aim": [
      {
        "performance": 1.1681089,
        "time": 1.0549451
      },
      {
        "performance": 1.2080845,
        "time": 1.1868132
      },
      {
        "performance": 1.2497407,
        "time": 1.3186814
      },
      {
        "performance": 1.4593079,
        "time": 1.3846154
      },
      {
        "performance": 1.5113047,
        "time": 1.5824176
      },
      {
        "performance": 1.5656149,
        "time": 1.8461539
      },
      {
        "performance": 1.7610556,
        "time": 2.1098902
      },
      {
        "performance": 1.8262932,
        "time": 2.2417583
      },
      {
        "performance": 1.8945738,
        "time": 2.3736265
      },
      {
        "performance": 2.1084483,
        "time": 2.4395604
      },
      {
        "performance": 2.189719,
        "time": 2.6373627
      },
      {
        "performance": 2.2749426,
        "time": 2.901099
      },
      {
        "performance": 1.9238616,
        "time": 3.1648352
      },
      {
        "performance": 2.337662,
        "time": 3.2967033
      },
      {
        "performance": 2.4275427,
        "time": 3.3626373
      },
      {
        "performance": 2.0575185,
        "time": 3.4285715
      },
      {
        "performance": 2.1330705,
        "time": 3.5604396
      },
      {
        "performance": 2.4440687,
        "time": 3.6263735
      },
      {
        "performance": 2.1485982,
        "time": 3.6923077
      },
      {
        "performance": 2.2268436,
        "time": 3.8241758
      },
      {
        "performance": 2.3086665,
        "time": 3.8901098
      },
      {
        "performance": 2.308818,
        "time": 3.956044
      },
      {
        "performance": 2.3932443,
        "time": 4.021978
      },
      {
        "performance": 2.4815497,
        "time": 4.087912
      },
      {
        "performance": 2.5739555,
        "time": 4.1538463
      },
      {
        "performance": 2.2331443,
        "time": 4.2197804
      },
      {
        "performance": 2.5530577,
        "time": 4.3186812
      },
      {
        "performance": 2.645181,
        "time": 4.3846154
      },
      {
        "performance": 2.328171,
        "time": 4.4835167
      },
      {
        "performance": 2.4098337,
        "time": 4.5824175
      },
      {
        "performance": 2.495054,
        "time": 4.6483517
      },
      {
        "performance": 2.2403758,
        "time": 4.747253
      },
      {
        "performance": 2.3180354,
        "time": 4.8461537
      },
      {
        "performance": 2.3990226,
        "time": 4.912088
      },
      {
        "performance": 2.1339676,
        "time": 5.010989
      },
      {
        "performance": 2.2070653,
        "time": 5.076923
      },
      {
        "performance": 2.2832408,
        "time": 5.142857
      },
      {
        "performance": 2.3626595,
        "time": 5.2087913
      },
      {
        "performance": 1.6183974,
        "time": 5.2747254
      },
      {
        "performance": 1.6711044,
        "time": 5.340659
      },
      {
        "performance": 1.7258532,
        "time": 5.4065933
      },
      {
        "performance": 1.7827455,
        "time": 5.4725275
      },
      {
        "performance": 1.2924343,
        "time": 5.5384617
      },
      {
        "performance": 1.3332992,
        "time": 5.6043954
      },
      {
        "performance": 1.3756597,
        "time": 5.6703296
      },
      {
        "performance": 1.4195858,
        "time": 5.7362638
      },
      {
        "performance": 1.0115147,
        "time": 5.802198
      },
      {
        "performance": 1.042716,
        "time": 5.8681316
      },
      {
        "performance": 1.0750006,
        "time": 5.934066
      },
      {
        "performance": 1.1084156,
        "time": 6.0
      },
      {
        "performance": 0.5077443,
        "time": 6.065934
      }
    ],
    "tap": [
      {
        "performance": 8.280205,
        "time": 1.0549451
      },
      {
        "performance": 8.4023,
        "time": 1.1868132
      },
      {
        "performance": 8.6071615,
        "time": 1.3186814
      },
      {
        "performance": 8.521314,
        "time": 1.3846154
      },
      {
        "performance": 8.7597475,
        "time": 1.5824176
      },
      {
        "performance": 9.143889,
        "time": 1.8461539
      },
      {
        "performance": 9.490302,
        "time": 2.1098902
      },
      {
        "performance": 9.674161,
        "time": 2.2417583
      },
      {
        "performance": 9.948141,
        "time": 2.3736265
      },
      {
        "performance": 9.921969,
        "time": 2.4395604
      },
      {
        "performance": 10.319829,
        "time": 2.6373627
      },
      {
        "performance": 10.796396,
        "time": 2.901099
      },
      {
        "performance": 11.239649,
        "time": 3.1648352
      },
      {
        "performance": 11.565729,
        "time": 3.2967033
      },
      {
        "performance": 11.649019,
        "time": 3.3626373
      },
      {
        "performance": 11.677044,
        "time": 3.4285715
      },
      {
        "performance": 12.042451,
        "time": 3.5604396
      },
      {
        "performance": 12.1178465,
        "time": 3.6263735
      },
      {
        "performance": 12.148957,
        "time": 3.6923077
      },
      {
        "performance": 12.526792,
        "time": 3.8241758
      },
      {
        "performance": 12.606921,
        "time": 3.8901098
      },
      {
        "performance": 12.674861,
        "time": 3.956044
      },
      {
        "performance": 12.784824,
        "time": 4.021978
      },
      {
        "performance": 12.8667,
        "time": 4.087912
      },
      {
        "performance": 12.95314,
        "time": 4.1538463
      },
      {
        "performance": 12.580983,
        "time": 4.2197804
      },
      {
        "performance": 12.576735,
        "time": 4.3186812
      },
      {
        "performance": 12.232959,
        "time": 4.3846154
      },
      {
        "performance": 12.01645,
        "time": 4.4835167
      },
      {
        "performance": 11.824627,
        "time": 4.5824175
      },
      {
        "performance": 11.43137,
        "time": 4.6483517
      },
      {
        "performance": 11.174342,
        "time": 4.747253
      },
      {
        "performance": 10.938498,
        "time": 4.8461537
      },
      {
        "performance": 10.496492,
        "time": 4.912088
      },
      {
        "performance": 10.2225895,
        "time": 5.010989
      },
      {
        "performance": 9.739024,
        "time": 5.076923
      },
      {
        "performance": 9.236903,
        "time": 5.142857
      },
      {
        "performance": 8.715181,
        "time": 5.2087913
      },
      {
        "performance": 8.148812,
        "time": 5.2747254
      },
      {
        "performance": 7.562547,
        "time": 5.340659
      },
      {
        "performance": 6.955423,
        "time": 5.4065933
      },
      {
        "performance": 6.504177,
        "time": 5.4725275
      },
      {
        "performance": 6.6611013,
        "time": 5.5384617
      },
      {
        "performance": 5.843932,
        "time": 5.6043954
      },
      {
        "performance": 5.002331,
        "time": 5.6703296
      },
      {
        "performance": 4.1352186,
        "time": 5.7362638
      },
      {
        "performance": 3.2357166,
        "time": 5.802198
      },
      {
        "performance": 2.3105028,
        "time": 5.8681316
      },
      {
        "performance": 1.3585556,
        "time": 5.934066
      },
      {
        "performance": 0.37879515,
        "time": 6.0
      },
      {
        "performance": 0.38110986,
        "time": 6.065934
      }
    ],
    "acc": [
      {
        "performance": 0.60157746,
        "time": 1.0549451
      },
      {
        "performance": 0.61883616,
        "time": 1.1868132
      },
      {
        "performance": 0.63658994,
        "time": 1.3186814
      },
      {
        "performance": 0.7381171,
        "time": 1.3846154
      },
      {
        "performance": 0.75929296,
        "time": 1.5824176
      },
      {
        "performance": 0.7810763,
        "time": 1.8461539
      },
      {
        "performance": 0.87232554,
        "time": 2.1098902
      },
      {
        "performance": 0.8973517,
        "time": 2.2417583
      },
      {
        "performance": 0.9230958,
        "time": 2.3736265
      },
      {
        "performance": 1.0316201,
        "time": 2.4395604
      },
      {
        "performance": 1.0612162,
        "time": 2.6373627
      },
      {
        "performance": 1.0916616,
        "time": 2.901099
      },
      {
        "performance": 0.7883867,
        "time": 3.1648352
      },
      {
        "performance": 0.9595614,
        "time": 3.2967033
      },
      {
        "performance": 0.9870903,
        "time": 3.3626373
      },
      {
        "performance": 0.8473653,
        "time": 3.4285715
      },
      {
        "performance": 0.87391883,
        "time": 3.5604396
      },
      {
        "performance": 0.9962439,
        "time": 3.6263735
      },
      {
        "performance": 0.8871156,
        "time": 3.6923077
      },
      {
        "performance": 0.9149147,
        "time": 3.8241758
      },
      {
        "performance": 0.9411627,
        "time": 3.8901098
      },
      {
        "performance": 0.9336911,
        "time": 3.956044
      },
      {
        "performance": 0.9629371,
        "time": 4.021978
      },
      {
        "performance": 0.9905628,
        "time": 4.087912
      },
      {
        "performance": 1.0189811,
        "time": 4.1538463
      },
      {
        "performance": 1.0397469,
        "time": 4.2197804
      },
      {
        "performance": 1.1314678,
        "time": 4.3186812
      },
      {
        "performance": 1.1639285,
        "time": 4.3846154
      },
      {
        "performance": 1.0288098,
        "time": 4.4835167
      },
      {
        "performance": 1.0583253,
        "time": 4.5824175
      },
      {
        "performance": 1.0886877,
        "time": 4.6483517
      },
      {
        "performance": 0.9823011,
        "time": 4.747253
      },
      {
        "performance": 1.0104823,
        "time": 4.8461537
      },
      {
        "performance": 1.0394721,
        "time": 4.912088
      },
      {
        "performance": 0.90907145,
        "time": 5.010989
      },
      {
        "performance": 0.93515176,
        "time": 5.076923
      },
      {
        "performance": 0.96198034,
        "time": 5.142857
      },
      {
        "performance": 0.9895786,
        "time": 5.2087913
      },
      {
        "performance": 0.71822065,
        "time": 5.2747254
      },
      {
        "performance": 0.7388257,
        "time": 5.340659
      },
      {
        "performance": 0.76002187,
        "time": 5.4065933
      },
      {
        "performance": 0.80379486,
        "time": 5.4725275
      },
      {
        "performance": 0.7151404,
        "time": 5.5384617
      },
      {
        "performance": 0.73427826,
        "time": 5.6043954
      },
      {
        "performance": 0.75392294,
        "time": 5.6703296
      },
      {
        "performance": 0.77408767,
        "time": 5.7362638
      },
      {
        "performance": 0.6077545,
        "time": 5.802198
      },
      {
        "performance": 0.6240008,
        "time": 5.8681316
      },
      {
        "performance": 0.6406767,
        "time": 5.934066
      },
      {
        "performance": 0.6577934,
        "time": 6.0
      },
      {
        "performance": 0.13241619,
        "time": 6.065934
      }
    ]
  },
  "speed200": {
    "aim": [
      {
        "performance": 1.2444848,
        "time": 0.9230769
      },
      {
        "performance": 1.2875208,
        "time": 1.0384616
      },
      {
        "performance": 1.3323942,
        "time": 1.1538461
      },
      {
        "performance": 1.5565631,
        "time": 1.2115384
      },
      {
        "performance": 1.612701,
        "time": 1.3846154
      },
      {
        "performance": 1.6713755,
        "time": 1.6153846
      },
      {
        "performance": 1.8809816,
        "time": 1.8461539
      },
      {
        "performance": 1.9516009,
        "time": 1.9615384
      },
      {
        "performance": 2.0255635,
        "time": 2.0769231
      },
      {
        "performance": 2.2554886,
        "time": 2.1346154
      },
      {
        "performance": 2.343685,
        "time": 2.3076923
      },
      {
        "performance": 2.4362304,
        "time": 2.5384614
      },
      {
        "performance": 2.060144,
        "time": 2.7692308
      },
      {
        "performance": 2.5042512,
        "time": 2.8846154
      },
      {
        "performance": 2.6017973,
        "time": 2.9423077
      },
      {
        "performance": 2.206347,
        "time": 3.0
      },
      {
        "performance": 2.2882466,
        "time": 3.1153846
      },
      {
        "performance": 2.6228414,
        "time": 3.1730769
      },
      {
        "performance": 2.306813,
        "time": 3.2307692
      },
      {
        "performance": 2.3916652,
        "time": 3.3461537
      },
      {
        "performance": 2.4804437,
        "time": 3.4038463
      },
      {
        "performance": 2.4815276,
        "time": 3.4615386
      },
      {
        "performance": 2.5731537,
        "time": 3.5192308
      },
      {
        "performance": 2.6690376,
        "time": 3.5769231
      },
      {
        "performance": 2.769424,
        "time": 3.6346154
      },
      {
        "performance": 2.4190357,
        "time": 3.6923077
      },
      {
        "performance": 2.7617722,
        "time": 3.7788463
      },
      {
        "performance": 2.8622696,
        "time": 3.8365386
      },
      {
        "performance": 2.5215728,
        "time": 3.9230769
      },
      {
        "performance": 2.6106591,
        "time": 4.0096154
      },
      {
        "performance": 2.7036648,
        "time": 4.0673075
      },
      {
        "performance": 2.4298828,
        "time": 4.1538463
      },
      {
        "performance": 2.5146604,
        "time": 4.2403846
      },
      {
        "performance": 2.6031039,
        "time": 4.298077
      },
      {
        "performance": 2.3178878,
        "time": 4.3846154
      },
      {
        "performance": 2.397749,
        "time": 4.4423075
      },
      {
        "performance": 2.4810019,
        "time": 4.5
      },
      {
        "performance": 2.56783,
        "time": 4.5576925
      },
      {
        "performance": 1.7658572,
        "time": 4.6153846
      },
      {
        "performance": 1.8235949,
        "time": 4.673077
      },
      {
        "performance": 1.8835852,
        "time": 4.730769
      },
      {
        "performance": 1.9459411,
        "time": 4.7884617
      },
      {
        "performance": 1.4175506,
        "time": 4.8461537
      },
      {
        "performance": 1.4624988,
        "time": 4.9038463
      },
      {
        "performance": 1.5091017,
        "time": 4.9615383
      },
      {
        "performance": 1.5574371,
        "time": 5.019231
      },
      {
        "performance": 1.1176424,
        "time": 5.076923
      },
      {
        "performance": 1.1521826,
        "time": 5.1346154
      },
      {
        "performance": 1.1879269,
        "time": 5.1923075
      },
      {
        "performance": 1.2249281,
        "time": 5.25
      },
      {
        "performance": 0.5425377,
        "time": 5.3076925
      }
    ],
    "tap": [
      {
        "performance": 9.012656,
        "time": 0.9230769
      },
      {
        "performance": 9.148834,
        "time": 1.0384616
      },
      {
        "performance": 9.3754015,
        "time": 1.1538461
      },
      {
        "performance": 9.280112,
        "time": 1.2115384
      },
      {
        "performance": 9.543906,
        "time": 1.3846154
      },
      {
        "performance": 9.966877,
        "time": 1.6153846
      },
      {
        "performance": 10.343221,
        "time": 1.8461539
      },
      {
        "performance": 10.548865,
        "time": 1.9615384
      },
      {
        "performance": 10.853179,
        "time": 2.0769231
      },
      {
        "performance": 10.824182,
        "time": 2.1346154
      },
      {
        "performance": 11.264478,
        "time": 2.3076923
      },
      {
        "performance": 11.791301,
        "time": 2.5384614
      },
      {
        "performance": 12.287721,
        "time": 2.7692308
      },
      {
        "performance": 12.649855,
        "time": 2.8846154
      },
      {
        "performance": 12.747436,
        "time": 2.9423077
      },
      {
        "performance": 12.790518,
        "time": 3.0
      },
      {
        "performance": 13.188429,
        "time": 3.1153846
      },
      {
        "performance": 13.276522,
        "time": 3.1730769
      },
      {
        "performance": 13.323089,
        "time": 3.2307692
      },
      {
        "performance": 13.734539,
        "time": 3.3461537
      },
      {
        "performance": 13.827654,
        "time": 3.4038463
      },
      {
        "performance": 13.906787,
        "time": 3.4615386
      },
      {
        "performance": 14.024475,
        "time": 3.5192308
      },
      {
        "performance": 14.119523,
        "time": 3.5769231
      },
      {
        "performance": 14.219787,
        "time": 3.6346154
      },
      {
        "performance": 13.822721,
        "time": 3.6923077
      },
      {
        "performance": 13.821929,
        "time": 3.7788463
      },
      {
        "performance": 13.448221,
        "time": 3.8365386
      },
      {
        "performance": 13.221039,
        "time": 3.9230769
      },
      {
        "performance": 13.013254,
        "time": 4.0096154
      },
      {
        "performance": 12.583766,
        "time": 4.0673075
      },
      {
        "performance": 12.310655,
        "time": 4.1538463
      },
      {
        "performance": 12.053528,
        "time": 4.2403846
      },
      {
        "performance": 11.5691805,
        "time": 4.298077
      },
      {
        "performance": 11.2694435,
        "time": 4.3846154
      },
      {
        "performance": 10.738519,
        "time": 4.4423075
      },
      {
        "performance": 10.187001,
        "time": 4.5
      },
      {
        "performance": 9.613718,
        "time": 4.5576925
      },
      {
        "performance": 8.9900675,
        "time": 4.6153846
      },
      {
        "performance": 8.344363,
        "time": 4.673077
      },
      {
        "performance": 7.6755257,
        "time": 4.730769
      },
      {
        "performance": 7.134747,
        "time": 4.7884617
      },
      {
        "performance": 7.1185465,
        "time": 4.8461537
      },
      {
        "performance": 6.247873,
        "time": 4.9038463
      },
      {
        "performance": 5.350381,
        "time": 4.9615383
      },
      {
        "performance": 4.4248686,
        "time": 5.019231
      },
      {
        "performance": 3.4637113,
        "time": 5.076923
      },
      {
        "performance": 2.4742851,
        "time": 5.1346154
      },
      {
        "performance": 1.4554487,
        "time": 5.1923075
      },
      {
        "performance": 0.40599453,
        "time": 5.25
      },
      {
        "performance": 0.41024446,
        "time": 5.3076925
      }
    ],
    "acc": [
      {
        "performance": 0.5982814,
        "time": 0.9230769
      },
      {
        "performance": 0.6154455,
        "time": 1.0384616
      },
      {
        "performance": 0.633102,
        "time": 1.1538461
      },
      {
        "performance": 0.7336454,
        "time": 1.2115384
      },
      {
        "performance": 0.754693,
        "time": 1.3846154
      },
      {
        "performance": 0.77634436,
        "time": 1.6153846
      },
      {
        "performance": 0.86654043,
        "time": 1.8461539
      },
      {
        "performance": 0.89140064,
        "time": 1.9615384
      },
      {
        "performance": 0.916974,
        "time": 2.0769231
      },
      {
        "performance": 1.0241926,
        "time": 2.1346154
      },
      {
        "performance": 1.0535756,
        "time": 2.3076923
      },
      {
        "performance": 1.0838017,
        "time": 2.5384614
      },
      {
        "performance": 0.78315824,
        "time": 2.7692308
      },
      {
        "performance": 0.9531978,
        "time": 2.8846154
      },
      {
        "performance": 0.9805441,
        "time": 2.9423077
      },
      {
        "performance": 0.84223175,
        "time": 3.0
      },
      {
        "performance": 0.8681232,
        "time": 3.1153846
      },
      {
        "performance": 0.98963696,
        "time": 3.1730769
      },
      {
        "performance": 0.8817412,
        "time": 3.2307692
      },
      {
        "performance": 0.9088472,
        "time": 3.3461537
      },
      {
        "performance": 0.9349211,
        "time": 3.4038463
      },
      {
        "performance": 0.92749906,
        "time": 3.4615386
      },
      {
        "performance": 0.9560041,
        "time": 3.5192308
      },
      {
        "performance": 0.9834309,
        "time": 3.5769231
      },
      {
        "performance": 1.0116446,
        "time": 3.6346154
      },
      {
        "performance": 1.0653169,
        "time": 3.6923077
      },
      {
        "performance": 1.1573609,
        "time": 3.7788463
      },
      {
        "performance": 1.1905644,
        "time": 3.8365386
      },
      {
        "performance": 1.0578471,
        "time": 3.9230769
      },
      {
        "performance": 1.0881957,
        "time": 4.0096154
      },
      {
        "performance": 1.1194149,
        "time": 4.0673075
      },
      {
        "performance": 1.0152359,
        "time": 4.1538463
      },
      {
        "performance": 1.044362,
        "time": 4.2403846
      },
      {
        "performance": 1.0743237,
        "time": 4.298077
      },
      {
        "performance": 0.9458008,
        "time": 4.3846154
      },
      {
        "performance": 0.97293484,
        "time": 4.4423075
      },
      {
        "performance": 1.0008473,
        "time": 4.5
      },
      {
        "performance": 1.0295607,
        "time": 4.5576925
      },
      {
        "performance": 0.7609921,
        "time": 4.6153846
      },
      {
        "performance": 0.7828242,
        "time": 4.673077
      },
      {
        "performance": 0.80528265,
        "time": 4.730769
      },
      {
        "performance": 0.8464598,
        "time": 4.7884617
      },
      {
        "performance": 0.74815696,
        "time": 4.8461537
      },
      {
        "performance": 0.7684298,
        "time": 4.9038463
      },
      {
        "performance": 0.7892482,
        "time": 4.9615383
      },
      {
        "performance": 0.8106268,
        "time": 5.019231
      },
      {
        "performance": 0.6522521,
        "time": 5.076923
      },
      {
        "performance": 0.6699132,
        "time": 5.1346154
      },
      {
        "performance": 0.68804914,
        "time": 5.1923075
      },
      {
        "performance": 0.7066726,
        "time": 5.25
      },
      {
        "performance": 0.12834959,
        "time": 5.3076925
      }
    ]
  }
}
